Workbook

Sheet Recon
A1: Member | B1: Balance Brought Forward | C1: July 2021 - April 2022 Cont (Planned) | D1: Total July 2021 - April 2022 Cont (Planned)2 | E1: Contribution made (Actual) | F1: Outstanding | G1: % outstanding | H1: Column1 | J1: Members in good standing (not owing) | K1: Members owing < 10% | L1: Members owing < 20% | M1: Members owing < 30% | N1: Members owing < 50% | O1: Members owing < 65% | P1: Members owing > 65%
A2: Member 1 | B2: 500 | C2: =200*10 -> 2000 | D2: =B2+C2 -> 2500 | E2: 2200 | F2: =B2+C2-E2 -> 300 | G2: =F2/D2 -> 0.12 | J2: 9 | K2: 2 | L2: 4 | M2: 1 | N2: 2 | O2: 2 | P2: 67
A3: Member 2 | B3: 1100 | C3: =200*10 -> 2000 | D3: =B3+C3 -> 3100 | E3: 1400 | F3: =B3+C3-E3 -> 1700 | G3: =F3/D3 -> 0.5483871 | P3: =SUM(J2:P2) -> 87
A4: Member 3 | B4: 5700 | C4: =200*10 -> 2000 | D4: =B4+C4 -> 7700 | E4: 0 | F4: =B4+C4-E4 -> 7700 | G4: =F4/D4 -> 1
A5: Member 4 | B5: 7000 | C5: =200*10 -> 2000 | D5: =B5+C5 -> 9000 | E5: 0 | F5: =B5+C5-E5 -> 9000 | G5: =F5/D5 -> 1
A6: Member 5 | B6: 1761.33 | C6: =200*10 -> 2000 | D6: =B6+C6 -> 3761.33 | E6: 0 | F6: =B6+C6-E6 -> 3761.33 | G6: =F6/D6 -> 1
A7: Member 6 | B7: 4100 | C7: =200*10 -> 2000 | D7: =B7+C7 -> 6100 | E7: 500 | F7: =B7+C7-E7 -> 5600 | G7: =F7/D7 -> 0.91803279
A8: Member 7 | B8: 7300 | C8: 2000 | D8: =B8+C8 -> 9300 | E8: 0 | F8: =B8+C8-E8 -> 9300 | G8: =F8/D8 -> 1
A9: Member 8 | B9: 5100 | C9: =200*10 -> 2000 | D9: =B9+C9 -> 7100 | E9: 200 | F9: =B9+C9-E9 -> 6900 | G9: =F9/D9 -> 0.97183099
A10: Member 9 | B10: 2400 | C10: =200*10 -> 2000 | D10: =B10+C10 -> 4400 | E10: 0 | F10: =B10+C10-E10 -> 4400 | G10: =F10/D10 -> 1
A11: Member 10 | B11: 6600 | C11: =200*10 -> 2000 | D11: =B11+C11 -> 8600 | E11: 800 | F11: =B11+C11-E11 -> 7800 | G11: =F11/D11 -> 0.90697674
A12: Member 11 | B12: 850 | C12: =200*10 -> 2000 | D12: =B12+C12 -> 2850 | E12: 0 | F12: =B12+C12-E12 -> 2850 | G12: =F12/D12 -> 1
A13: Member 12 | B13: -650 | C13: =200*10 -> 2000 | D13: =B13+C13 -> 1350 | E13: 1300 | F13: =B13+C13-E13 -> 50 | G13: =F13/D13 -> 0.037037037
A14: Member 13 | B14: 500 | C14: =200*10 -> 2000 | D14: =B14+C14 -> 2500 | E14: 0 | F14: =B14+C14-E14 -> 2500 | G14: =F14/D14 -> 1
A15: Member 14 | B15: 7100 | C15: =200*10 -> 2000 | D15: =B15+C15 -> 9100 | E15: 800 | F15: =B15+C15-E15 -> 8300 | G15: =F15/D15 -> 0.91208791
A16: Member 15 | B16: 5100 | C16: =200*10 -> 2000 | D16: =B16+C16 -> 7100 | E16: 0 | F16: =B16+C16-E16 -> 7100 | G16: =F16/D16 -> 1
A17: Member 16 | B17: 5900 | C17: =200*10 -> 2000 | D17: =B17+C17 -> 7900 | E17: 0 | F17: =B17+C17-E17 -> 7900 | G17: =F17/D17 -> 1
A18: Member 17 | B18: -4100 | C18: =200*10 -> 2000 | D18: =B18+C18 -> -2100 | E18: 1500 | F18: 0 | G18: =F18/D18 -> 0 | H18: =2100+1500 -> 3600
A19: Member 18 | B19: 100 | C19: =200*10 -> 2000 | D19: =B19+C19 -> 2100 | E19: 1400 | F19: =B19+C19-E19 -> 700 | G19: =F19/D19 -> 0.33333333
A20: Member 19 | B20: 6700 | C20: =200*10 -> 2000 | D20: =B20+C20 -> 8700 | E20: 0 | F20: =B20+C20-E20 -> 8700 | G20: =F20/D20 -> 1 | J20: Members in good standing (not owing) | K20: Members owing < 10% | L20: Members owing < 20% | M20: Members owing < 30% | N20: Members owing < 50% | O20: Members owing < 65% | P20: Members owing > 65%
A21: Member 20 | B21: 430 | C21: =200*10 -> 2000 | D21: =B21+C21 -> 2430 | E21: 200 | F21: =B21+C21-E21 -> 2230 | G21: =F21/D21 -> 0.91769547 | I21: 86 | J21: =J2/I21 -> 0.10465116 | K21: =K2/I21 -> 0.023255814 | L21: =L2/I21 -> 0.046511628 | M21: =M2/I21 -> 0.011627907 | N21: =N2/I21 -> 0.023255814 | O21: =O2/I21 -> 0.023255814 | P21: =P2/I21 -> 0.77906977
A22: Member 21 | B22: 5900 | C22: =200*10 -> 2000 | D22: =B22+C22 -> 7900 | E22: 0 | F22: =B22+C22-E22 -> 7900 | G22: =F22/D22 -> 1
A23: Member 22 | B23: 2700 | C23: =200*10 -> 2000 | D23: =B23+C23 -> 4700 | E23: 200 | F23: =B23+C23-E23 -> 4500 | G23: =F23/D23 -> 0.95744681
A24: Member 23 | B24: 6700 | C24: =200*10 -> 2000 | D24: =B24+C24 -> 8700 | E24: 0 | F24: =B24+C24-E24 -> 8700 | G24: =F24/D24 -> 1
A25: Member 24 | B25: 0 | C25: =200*10 -> 2000 | D25: =B25+C25 -> 2000 | E25: 2700 | F25: 0 | G25: =F25/D25 -> 0 | H25: =Table1[[#This Row],[Contribution made (Actual)]]-Table1[[#This Row],[Total July 2021 - April 2022 Cont (Planned)2]] -> 700
A26: Member 25 | B26: 350 | C26: =200*10 -> 2000 | D26: =B26+C26 -> 2350 | E26: 2700 | F26: 0 | G26: =F26/D26 -> 0 | H26: =Table1[[#This Row],[Contribution made (Actual)]]-Table1[[#This Row],[Total July 2021 - April 2022 Cont (Planned)2]] -> 350
A27: Member 26 | B27: 5100 | C27: =200*10 -> 2000 | D27: =B27+C27 -> 7100 | E27: 0 | F27: =B27+C27-E27 -> 7100 | G27: =F27/D27 -> 1
A28: Member 27 | B28: 6100 | C28: =200*10 -> 2000 | D28: =B28+C28 -> 8100 | E28: 0 | F28: =B28+C28-E28 -> 8100 | G28: =F28/D28 -> 1
A29: Member 28 | B29: 6700 | C29: =200*10 -> 2000 | D29: =B29+C29 -> 8700 | E29: 0 | F29: =B29+C29-E29 -> 8700 | G29: =F29/D29 -> 1
A30: Member 29 | B30: 1600 | C30: =200*10 -> 2000 | D30: =B30+C30 -> 3600 | E30: 0 | F30: =B30+C30-E30 -> 3600 | G30: =F30/D30 -> 1
A31: Member 30 | B31: 1100 | C31: =200*10 -> 2000 | D31: =B31+C31 -> 3100 | E31: 3300 | F31: 0 | G31: =F31/D31 -> 0 | H31: =Table1[[#This Row],[Contribution made (Actual)]]-Table1[[#This Row],[Total July 2021 - April 2022 Cont (Planned)2]] -> 200
A32: Member 31 | B32: 400 | C32: =200*10 -> 2000 | D32: =B32+C32 -> 2400 | E32: 2500 | F32: 0 | G32: =F32/D32 -> 0 | H32: =Table1[[#This Row],[Contribution made (Actual)]]-Table1[[#This Row],[Total July 2021 - April 2022 Cont (Planned)2]] -> 100
A33: Member 32 | B33: 5900 | C33: =200*10 -> 2000 | D33: =B33+C33 -> 7900 | E33: 0 | F33: =B33+C33-E33 -> 7900 | G33: =F33/D33 -> 1
A34: Member 33 | B34: 7300 | C34: 2000 | D34: =B34+C34 -> 9300 | E34: 500 | F34: =B34+C34-E34 -> 8800 | G34: =F34/D34 -> 0.94623656
A35: Member 34 | B35: 6700 | C35: =200*10 -> 2000 | D35: =B35+C35 -> 8700 | E35: 0 | F35: =B35+C35-E35 -> 8700 | G35: =F35/D35 -> 1
A36: Member 35 | B36: 7300 | C36: =200*10 -> 2000 | D36: =B36+C36 -> 9300 | E36: 1100 | F36: =B36+C36-E36 -> 8200 | G36: =F36/D36 -> 0.88172043
A37: Member 36 | B37: 3900 | C37: 2000 | D37: =B37+C37 -> 5900 | E37: 0 | F37: =B37+C37-E37 -> 5900 | G37: =F37/D37 -> 1
A38: Member 37 | B38: 3850 | C38: =200*10 -> 2000 | D38: =B38+C38 -> 5850 | E38: 400 | F38: =B38+C38-E38 -> 5450 | G38: =F38/D38 -> 0.93162393
A39: Member 38 | B39: 6700 | C39: =200*10 -> 2000 | D39: =B39+C39 -> 8700 | E39: 0 | F39: =B39+C39-E39 -> 8700 | G39: =F39/D39 -> 1
A40: Member 39 | B40: 4890 | C40: =200*10 -> 2000 | D40: =B40+C40 -> 6890 | E40: 690 | F40: =B40+C40-E40 -> 6200 | G40: =F40/D40 -> 0.89985486
A41: Member 40 | B41: 500 | C41: =200*10 -> 2000 | D41: =B41+C41 -> 2500 | E41: 0 | F41: =B41+C41-E41 -> 2500 | G41: =F41/D41 -> 1
A42: Member 41 | B42: 4100 | C42: =200*10 -> 2000 | D42: =B42+C42 -> 6100 | E42: 0 | F42: =B42+C42-E42 -> 6100 | G42: =F42/D42 -> 1
A43: Member 42 | B43: 3461.11 | C43: =200*10 -> 2000 | D43: =B43+C43 -> 5461.11 | E43: 900 | F43: =B43+C43-E43 -> 4561.11 | G43: =F43/D43 -> 0.83519834
A44: Member 43 | B44: -1130 | C44: =200*10 -> 2000 | D44: =B44+C44 -> 870 | E44: 2500 | F44: 0 | G44: =F44/D44 -> 0 | H44: =Table1[[#This Row],[Contribution made (Actual)]]-Table1[[#This Row],[Total July 2021 - April 2022 Cont (Planned)2]] -> 1630
A45: Member 44 | B45: 1500 | C45: =200*10 -> 2000 | D45: =B45+C45 -> 3500 | E45: 0 | F45: =B45+C45-E45 -> 3500 | G45: =F45/D45 -> 1 | H45: Nick
A46: Member 45 | B46: 1600 | C46: =200*10 -> 2000 | D46: =B46+C46 -> 3600 | E46: 2900 | F46: =B46+C46-E46 -> 700 | G46: =F46/D46 -> 0.19444444
A47: Member 46 | B47: 4700 | C47: =200*10 -> 2000 | D47: =B47+C47 -> 6700 | E47: 0 | F47: =B47+C47-E47 -> 6700 | G47: =F47/D47 -> 1
A48: Member 47 | B48: -710 | C48: =200*10 -> 2000 | D48: =B48+C48 -> 1290 | E48: 2000 | F48: 0 | G48: =F48/D48 -> 0 | H48: 1420 | J48: =710+2000-1290 -> 1420
A49: Member 48 | B49: 1890 | C49: =200*10 -> 2000 | D49: =B49+C49 -> 3890 | E49: 2500 | F49: =B49+C49-E49 -> 1390 | G49: =F49/D49 -> 0.35732648
A50: Member 49 | B50: 6700 | C50: =200*10 -> 2000 | D50: =B50+C50 -> 8700 | E50: 0 | F50: =B50+C50-E50 -> 8700 | G50: =F50/D50 -> 1
A51: Member 50 | B51: 6300 | C51: =200*10 -> 2000 | D51: =B51+C51 -> 8300 | E51: 0 | F51: =B51+C51-E51 -> 8300 | G51: =F51/D51 -> 1
A52: Member 51 | B52: 7050 | C52: =200*10 -> 2000 | D52: =B52+C52 -> 9050 | E52: 0 | F52: =B52+C52-E52 -> 9050 | G52: =F52/D52 -> 1
A53: Member 52 | B53: 1800 | C53: =200*10 -> 2000 | D53: =B53+C53 -> 3800 | E53: 0 | F53: =B53+C53-E53 -> 3800 | G53: =F53/D53 -> 1
A54: Member 53 | B54: -520 | C54: =200*10 -> 2000 | D54: =B54+C54 -> 1480 | E54: 1250 | F54: =B54+C54-E54 -> 230 | G54: =F54/D54 -> 0.15540541
A55: Member 54 | B55: 1700 | C55: =200*10 -> 2000 | D55: =B55+C55 -> 3700 | E55: 1600 | F55: =B55+C55-E55 -> 2100 | G55: =F55/D55 -> 0.56756757
A56: Member 55 | B56: 90 | C56: =200*10 -> 2000 | D56: =B56+C56 -> 2090 | E56: 2750 | F56: 0 | G56: =F56/D56 -> 0 | H56: =Table1[[#This Row],[Contribution made (Actual)]]-Table1[[#This Row],[Total July 2021 - April 2022 Cont (Planned)2]] -> 660
A57: Member 56 | B57: 4100 | C57: =200*10 -> 2000 | D57: =B57+C57 -> 6100 | E57: 0 | F57: =B57+C57-E57 -> 6100 | G57: =F57/D57 -> 1
A58: Member 57 | B58: 6200 | C58: =200*10 -> 2000 | D58: =B58+C58 -> 8200 | E58: 0 | F58: =B58+C58-E58 -> 8200 | G58: =F58/D58 -> 1
A59: Member 58 | B59: 6500 | C59: =200*10 -> 2000 | D59: =B59+C59 -> 8500 | E59: 0 | F59: =B59+C59-E59 -> 8500 | G59: =F59/D59 -> 1 | H59: Want to resign
A60: Member 59 | B60: 2400 | C60: =200*10 -> 2000 | D60: =B60+C60 -> 4400 | E60: 3250 | F60: =B60+C60-E60 -> 1150 | G60: =F60/D60 -> 0.26136364 | J60: Contribution | K60: 5100
A61: Member 60 | B61: 6900 | C61: =200*10 -> 2000 | D61: =B61+C61 -> 8900 | E61: 0 | F61: =B61+C61-E61 -> 8900 | G61: =F61/D61 -> 1 | J61: Outstanding | K61: 2100 | L61: Pay
A62: Member 61 | B62: 4500 | C62: =200*10 -> 2000 | D62: =B62+C62 -> 6500 | E62: 400 | F62: =B62+C62-E62 -> 6100 | G62: =F62/D62 -> 0.93846154 | J62: Penalties | K62: 1691.6647 | L62: Interest
A63: Member 62 | B63: 3600 | C63: =200*10 -> 2000 | D63: =B63+C63 -> 5600 | E63: 0 | F63: =B63+C63-E63 -> 5600 | G63: =F63/D63 -> 1 | H63: resign | J63: 4 Months Outstanding | K63: 800 | L63: Pay
A64: Member 63 | B64: 6490 | C64: =200*10 -> 2000 | D64: =B64+C64 -> 8490 | E64: 0 | F64: =B64+C64-E64 -> 8490 | G64: =F64/D64 -> 1 | J64: 4 Months Penalties | K64: =K63*5.5% -> 44 | L64: Interest
A65: Member 64 | B65: 6900 | C65: =200*10 -> 2000 | D65: =B65+C65 -> 8900 | E65: 0 | F65: =B65+C65-E65 -> 8900 | G65: =F65/D65 -> 1 | H65: resign
A66: Member 65 | B66: 4700 | C66: =200*10 -> 2000 | D66: =B66+C66 -> 6700 | E66: 0 | F66: =B66+C66-E66 -> 6700 | G66: =F66/D66 -> 1 | J66: 5.5% | K66: wait 3 months
A67: Member 66 | B67: 4100 | C67: =200*10 -> 2000 | D67: =B67+C67 -> 6100 | E67: 1300 | F67: =B67+C67-E67 -> 4800 | G67: =F67/D67 -> 0.78688525
A68: Member 67 | B68: 600 | C68: =200*10 -> 2000 | D68: =B68+C68 -> 2600 | E68: 2500 | F68: =B68+C68-E68 -> 100 | G68: =F68/D68 -> 0.038461538
A69: Member 68 | B69: 2100 | C69: =200*10 -> 2000 | D69: =B69+C69 -> 4100 | E69: 0 | F69: =B69+C69-E69 -> 4100 | G69: =F69/D69 -> 1
A70: Member 69 | B70: 150 | C70: =200*10 -> 2000 | D70: =B70+C70 -> 2150 | E70: 2700 | F70: 0 | G70: =F70/D70 -> 0 | H70: 550
A71: Member 70 | B71: 3400 | C71: =200*10 -> 2000 | D71: =B71+C71 -> 5400 | E71: 0 | F71: =B71+C71-E71 -> 5400 | G71: =F71/D71 -> 1
A72: Member 71 | B72: 6200 | C72: =200*10 -> 2000 | D72: =B72+C72 -> 8200 | E72: 0 | F72: =B72+C72-E72 -> 8200 | G72: =F72/D72 -> 1
A73: Member 72 | B73: -100 | C73: =200*10 -> 2000 | D73: =B73+C73 -> 1900 | E73: 1600 | F73: =B73+C73-E73 -> 300 | G73: =F73/D73 -> 0.15789474
A74: Member 73 | B74: 1684.85 | C74: =200*10 -> 2000 | D74: =B74+C74 -> 3684.85 | E74: 0 | F74: =B74+C74-E74 -> 3684.85 | G74: =F74/D74 -> 1
A75: Member 74 | B75: 1900 | C75: =200*10 -> 2000 | D75: =B75+C75 -> 3900 | E75: 600 | F75: =B75+C75-E75 -> 3300 | G75: =F75/D75 -> 0.84615385
A76: Member 75 | B76: 4900 | C76: =200*10 -> 2000 | D76: =B76+C76 -> 6900 | E76: 0 | F76: =B76+C76-E76 -> 6900 | G76: =F76/D76 -> 1
A77: Member 76 | B77: 6900 | C77: =200*10 -> 2000 | D77: =B77+C77 -> 8900 | E77: 0 | F77: =B77+C77-E77 -> 8900 | G77: =F77/D77 -> 1
A78: Member 77 | B78: 2900 | C78: =200*10 -> 2000 | D78: =B78+C78 -> 4900 | E78: 0 | F78: =B78+C78-E78 -> 4900 | G78: =F78/D78 -> 1
A79: Member 78 | B79: 6400 | C79: =200*10 -> 2000 | D79: =B79+C79 -> 8400 | E79: 0 | F79: =B79+C79-E79 -> 8400 | G79: =F79/D79 -> 1
A80: Member 79 | B80: 5300 | C80: =200*10 -> 2000 | D80: =B80+C80 -> 7300 | E80: 0 | F80: =B80+C80-E80 -> 7300 | G80: =F80/D80 -> 1
A81: Member 80 | B81: 2450 | C81: =200*10 -> 2000 | D81: =B81+C81 -> 4450 | E81: 900 | F81: =B81+C81-E81 -> 3550 | G81: =F81/D81 -> 0.79775281
A82: Member 81 | B82: 1100 | C82: =200*10 -> 2000 | D82: =B82+C82 -> 3100 | E82: 0 | F82: =B82+C82-E82 -> 3100 | G82: =F82/D82 -> 1
... A90: Member 89 | B90: 4800 | C90: =200*10 -> 2000 | D90: =B90+C90 -> 6800 | E90: 1600 | F90: =B90+C90-E90 -> 5200 | G90: =F90/D90 -> 0.76470588
B91: =SUBTOTAL(109,B2:B90) -> 323937.29 | C91: =SUBTOTAL(109,C2:C90) -> 178000 | D91: =B91+C91 -> 501937.29 | E91: =SUBTOTAL(109,E2:E90) -> 58840 | F91: =SUBTOTAL(109,F2:F90) -> 451597.29

Sheet 2018-2019 B STATEMENT 
A1: TransactionDate | B1: Amount | C1: Fee | D1: Group | E1: Member | F1: PayType | G1: Reference | H1: Bank Charge
A2: 43284.75 | B2: 150 | C2: 1.335 | D2: Peoples Liberator Fund | F2: EFT | G2: 115719367211
A3: 43290.723 | B3: 100 | C3: 9.99 | D3: Peoples Liberator Fund | F3: EFT | G3: 115719367251
A4: 43290.723 | B4: 100 | C4: 0.89 | D4: Peoples Liberator Fund | F4: EFT | G4: 115719367255
A5: 43291.744 | B5: 300 | C5: 2.67 | D5: Peoples Liberator Fund | F5: EFT | G5: 115719367269
A6: 43291.748 | B6: 150 | C6: 1.335 | D6: Peoples Liberator Fund | F6: EFT | G6: 115719367213
A7: 43292.746 | B7: 200 | C7: 1.78 | D7: Peoples Liberator Fund | F7: EFT | G7: 115719367302
A8: 43292.746 | B8: 300 | C8: 2.67 | D8: Peoples Liberator Fund | F8: EFT | G8: 115719367243
A9: 43293.722 | B9: 300 | C9: 2.67 | D9: Peoples Liberator Fund | F9: EFT | G9: 115719367253
A10: 43294.744 | B10: 300 | C10: 2.67 | D10: Peoples Liberator Fund | F10: EFT | G10: 115719367265
A11: 43294.744 | B11: 200 | C11: 1.78 | D11: Peoples Liberator Fund | F11: EFT | G11: 115719367211
A12: 43306.743 | B12: 300 | C12: 2.67 | D12: Peoples Liberator Fund | F12: EFT | G12: 115719367362
A13: 43307.743 | B13: 100 | C13: 0.89 | D13: Peoples Liberator Fund | F13: EFT | G13: 115719367421
... A16: 43310.655 | B16: 300 | C16: 9.99 | D16: Peoples Liberator Fund | F16: Retail Shop | G16: 115719367441
A17: 43311.744 | B17: 300 | C17: 2.67 | D17: Peoples Liberator Fund | F17: EFT | G17: 115719367256 | H17: =C17/B17*100 -> 0.89
A18: 43311.744 | B18: 310 | C18: 9.99 | D18: Peoples Liberator Fund | F18: EFT | G18: 115719367414
A19: 43311.744 | B19: 200 | C19: 1.78 | D19: Peoples Liberator Fund | F19: EFT | G19: 115719367255
A20: 43312.715 | B20: 400 | C20: 3.56 | D20: Peoples Liberator Fund | F20: EFT | G20: 115719367421
A21: 43312.715 | B21: 300 | C21: 2.67 | D21: Peoples Liberator Fund | F21: EFT | G21: 115719367410
A22: 43312.715 | B22: 300 | C22: 2.67 | D22: Peoples Liberator Fund | F22: EFT | G22: 115719367446
A23: 43312.715 | B23: 300 | C23: 2.67 | D23: Peoples Liberator Fund | F23: EFT | G23: 115719367252
A24: 43312.715 | B24: 300 | C24: 2.67 | D24: Peoples Liberator Fund | F24: EFT | G24: 115719367447
A25: 43312.715 | B25: 300 | C25: 2.67 | D25: Peoples Liberator Fund | F25: EFT | G25: 115719367360 | H25: =C25/B25*100 -> 0.89
A26: 43312.715 | B26: 300 | C26: 2.67 | D26: Peoples Liberator Fund | F26: EFT | G26: 115719367448
A27: 43312.715 | B27: 200 | C27: 1.78 | D27: Peoples Liberator Fund | F27: EFT | G27: 115719367213
A28: 43313.743 | B28: 300 | C28: 2.67 | D28: Peoples Liberator Fund | F28: EFT | G28: 115719367430
A29: 43314.688 | B29: 300 | C29: 2.67 | D29: Peoples Liberator Fund | F29: EFT | G29: 115719367450
A30: 43318.684 | B30: 200 | C30: 1.78 | D30: Peoples Liberator Fund | F30: EFT | G30: 115719367269
A31: 43318.684 | B31: 400 | C31: 9.99 | D31: Peoples Liberator Fund | F31: EFT | G31: 115719367464
A32: 43318.684 | B32: 300 | C32: 2.67 | D32: Peoples Liberator Fund | F32: EFT | G32: 115719367474
A33: 43318.684 | B33: 300 | C33: 2.67 | D33: Peoples Liberator Fund | F33: EFT | G33: 115719367428
A34: 43320.724 | B34: 300 | C34: 2.67 | D34: Peoples Liberator Fund | F34: EFT | G34: 115719367440
A35: 43320.724 | B35: 300 | C35: 2.67 | D35: Peoples Liberator Fund | F35: EFT | G35: 115719367364
A36: 43328.75 | B36: 200 | C36: 1.78 | D36: Peoples Liberator Fund | F36: EFT | G36: 115719367265
A37: 43328.75 | B37: 200 | C37: 1.78 | D37: Peoples Liberator Fund | F37: EFT | G37: 115719367447
A38: 43332.717 | B38: 300 | C38: 2.67 | D38: Peoples Liberator Fund | F38: EFT | G38: 115719367501
A39: 43332.717 | B39: 200 | C39: 1.78 | D39: Peoples Liberator Fund | F39: EFT | G39: 115719367256 | H39: =C39/B39*100 -> 0.89
A40: 43332.717 | B40: 500 | C40: 4.45 | D40: Peoples Liberator Fund | F40: EFT | G40: 115719367411
A41: 43332.717 | B41: 300 | C41: 2.67 | D41: Peoples Liberator Fund | F41: EFT | G41: 115719367466
A42: 43332.717 | B42: 300 | C42: 2.67 | D42: Peoples Liberator Fund | F42: EFT | G42: 115719367472
A43: 43332.717 | B43: 300 | C43: 2.67 | D43: Peoples Liberator Fund | F43: EFT | G43: 115719367431
A44: 43332.717 | B44: 300 | C44: 2.67 | D44: Peoples Liberator Fund | F44: EFT | G44: 115719367260
A45: 43333.739 | B45: 500 | C45: 4.45 | D45: Peoples Liberator Fund | F45: EFT | G45: 115719367553
A46: 43339.612 | B46: 200 | C46: 1.78 | D46: Peoples Liberator Fund | F46: EFT | G46: 115719367235
A47: 43339.612 | B47: 200 | C47: 1.78 | D47: Peoples Liberator Fund | F47: EFT | G47: 115719367362
A48: 43339.612 | B48: 1000 | C48: 8.9 | D48: Peoples Liberator Fund | F48: EFT | G48: 115719367414
A49: 43340.734 | B49: 200 | C49: 1.78 | D49: Peoples Liberator Fund | F49: EFT | G49: 115719367410
A50: 43340.734 | B50: 2500 | C50: 22.25 | D50: Peoples Liberator Fund | F50: EFT | G50: 115719367521
A51: 43340.734 | B51: 300 | C51: 2.67 | D51: Peoples Liberator Fund | F51: EFT | G51: 115719367477
... A78: 43356.527 | B78: 1000 | C78: 8.9 | D78: Peoples Liberator Fund | F78: EFT | G78: 115719367211
A79: 43356.527 | B79: 500 | C79: 4.45 | D79: Peoples Liberator Fund | F79: EFT | G79: 115719367360 | H79: =C79/B79*100 -> 0.89
A80: 43356.527 | B80: 200 | C80: 1.78 | D80: Peoples Liberator Fund | F80: EFT | G80: 115719367497
A81: 43356.527 | B81: 800 | C81: 7.12 | D81: Peoples Liberator Fund | F81: EFT | G81: 115719367260
A82: 43356.527 | B82: 300 | C82: 2.67 | D82: Peoples Liberator Fund | F82: EFT | G82: 115719367586
A83: 43360.739 | B83: 400 | C83: 3.56 | D83: Peoples Liberator Fund | F83: EFT | G83: 115719367243
A84: 43360.739 | B84: 200 | C84: 1.78 | D84: Peoples Liberator Fund | F84: EFT | G84: 115719367364
A85: 43365.262 | B85: 500 | C85: 4.45 | D85: Peoples Liberator Fund | F85: EFT | G85: 115719367589
A86: 43365.262 | B86: 200 | C86: 1.78 | D86: Peoples Liberator Fund | F86: EFT | G86: 115719367553
A87: 43366.71 | B87: 400 | C87: 23.96 | D87: Peoples Liberator Fund | F87: Credit Card | G87: SFc88f1892368517
A88: 43368.708 | B88: 200 | C88: 1.78 | D88: Peoples Liberator Fund | F88: EFT | G88: 115719367235
A89: 43368.708 | B89: 200 | C89: 1.78 | D89: Peoples Liberator Fund | F89: EFT | G89: 115719367362
A90: 43368.708 | B90: 100 | C90: 9.99 | D90: Peoples Liberator Fund | F90: EFT | G90: 115719367511
A91: 43369.738 | B91: 400 | C91: 3.56 | D91: Peoples Liberator Fund | F91: EFT | G91: 115719367477
A92: 43371.747 | B92: 200 | C92: 1.78 | D92: Peoples Liberator Fund | F92: EFT | G92: 115719367256 | H92: =C92/B92*100 -> 0.89
A93: 43371.747 | B93: 400 | C93: 3.56 | D93: Peoples Liberator Fund | F93: EFT | G93: 115719367518
A94: 43371.747 | B94: 700 | C94: 6.23 | D94: Peoples Liberator Fund | F94: EFT | G94: 115719367646
A95: 43371.747 | B95: 1000 | C95: 8.9 | D95: Peoples Liberator Fund | F95: EFT | G95: 115719367246
A96: 43374.736 | B96: 200 | C96: 1.78 | D96: Peoples Liberator Fund | F96: EFT | G96: 115719367410
A97: 43374.736 | B97: 310 | C97: 9.99 | D97: Peoples Liberator Fund | F97: EFT | G97: 115719367463
A98: 43693.747 | B98: 300 | C98: 2.97 | D98: Peoples Liberator Fund | F98: EFT | G98: 115719367593 | H98: =C98/B98*100 -> 0.99
A99: 43374.736 | B99: 200 | C99: 1.78 | D99: Peoples Liberator Fund | F99: EFT | G99: 115719367450
A100: 43375.694 | B100: 150 | C100: 1.335 | D100: Peoples Liberator Fund | F100: EFT | G100: 115719367213
A101: 43375.728 | B101: 210 | C101: 9.99 | D101: Peoples Liberator Fund | F101: Retail Shop | G101: 115719367441
A102: 43376.651 | B102: 200 | C102: 1.78 | D102: Peoples Liberator Fund | F102: EFT | G102: 115719367501
A103: 43376.651 | B103: 250 | C103: 2.225 | D103: Peoples Liberator Fund | F103: EFT | G103: 115719367665
A104: 43378.709 | B104: 200 | C104: 1.78 | D104: Peoples Liberator Fund | F104: EFT | G104: 115719367567
A105: 43384.711 | B105: 200 | C105: 1.78 | D105: Peoples Liberator Fund | F105: EFT | G105: 115719367490
A106: 43385.747 | B106: 1000 | C106: 8.9 | D106: Peoples Liberator Fund | F106: EFT | G106: 115719367360 | H106: =C106/B106*100 -> 0.89
A107: 43385.747 | B107: 1000 | C107: 8.9 | D107: Peoples Liberator Fund | F107: EFT | G107: 115719367448
A108: 43389.511 | B108: 200 | C108: 11.98 | D108: Peoples Liberator Fund | F108: Credit Card | G108: SFc8f618101632337
A109: 43389.513 | B109: 200 | C109: 11.98 | D109: Peoples Liberator Fund | F109: Credit Card
A110: 43389.516 | B110: 200 | C110: 11.98 | D110: Peoples Liberator Fund | F110: Credit Card
A111: 43389.747 | B111: 200 | C111: 1.78 | D111: Peoples Liberator Fund | F111: EFT | G111: 115719367265
A112: 43389.747 | B112: 200 | C112: 1.78 | D112: Peoples Liberator Fund | F112: EFT | G112: 115719367256 | H112: =C112/B112*100 -> 0.89
A113: 43389.747 | B113: 200 | C113: 1.78 | D113: Peoples Liberator Fund | F113: EFT | G113: 115719367589
A114: 43389.747 | B114: 900 | C114: 8.01 | D114: Peoples Liberator Fund | F114: EFT | G114: 115719367626
A115: 43395.737 | B115: 900 | C115: 8.01 | D115: Peoples Liberator Fund | F115: EFT | G115: 115719367495
A116: 43398.751 | B116: 200 | C116: 1.78 | D116: Peoples Liberator Fund | F116: EFT | G116: 115719367235
A117: 43398.751 | B117: 600 | C117: 13.74 | D117: Peoples Liberator Fund | F117: EFT | G117: 115719367463
A118: 43399.721 | B118: 200 | C118: 1.78 | D118: Peoples Liberator Fund | F118: EFT | G118: 115719367362
A119: 43399.721 | B119: 250 | C119: 2.225 | D119: Peoples Liberator Fund | F119: EFT | G119: 115719367665
A120: 43402.579 | B120: 200 | C120: 9.99 | D120: Peoples Liberator Fund | F120: Retail Shop | G120: 115719367441
A121: 43402.745 | B121: 200 | C121: 1.78 | D121: Peoples Liberator Fund | F121: EFT | G121: 115719367410
A122: 43402.745 | B122: 400 | C122: 3.56 | D122: Peoples Liberator Fund | F122: EFT | G122: 115719367837
A123: 43402.745 | B123: 200 | C123: 1.78 | D123: Peoples Liberator Fund | F123: EFT | G123: 115719367477
A124: 43402.745 | B124: 200 | C124: 1.78 | D124: Peoples Liberator Fund | F124: EFT | G124: 115719367450
... A142: 43426.735 | B142: 300 | C142: 2.67 | D142: Peoples Liberator Fund | F142: EFT | G142: 115719367495
A143: 43426.735 | B143: 200 | C143: 1.78 | D143: Peoples Liberator Fund | F143: EFT | G143: 115719367256 | H143: =C143/B143*100 -> 0.89
A144: 43426.735 | B144: 100 | C144: 0.89 | D144: Peoples Liberator Fund | F144: EFT | G144: 115719367511
A145: 43426.735 | B145: 200 | C145: 1.78 | D145: Peoples Liberator Fund | F145: EFT | G145: 115719367553
...

Sheet  2018-2019
A1: Member | B1: Date Join | C1: Membership Fee | D1: Expected Contribution | E1: Balance Brought Forward (Catch-up fee) | F1: Catch-Up Fee | G1: Estimated 12 Months Contribution (Jul 2018-June 2019) | H1: Total Contribution incl membership fee for 12 Months | I1: Total outstanding contribution for 12 Months | J1: Closing Balance (Inc. Penalties) | K1: Total Bank Charges @ 0,89% | L1: Total Interest Earned @ 5,5% | M1: Penalty | N1: Share Value | O1: 43282 | P1: Bank Charges @ 0,89% | Q1: Penalty | R1: 43313 | S1: Bank Charges @ 0,89% | T1: Penalty | U1: 43344 | V1: Bank Charges @ 0,89% | W1: Penalty | X1: 43374 | Y1: Bank Charges @ 0,89% | Z1: Penalty | AA1: 43405 | AB1: Bank Charges @ 0,89% | AC1: Penalty | AD1: 43435 | AE1: Bank Charges @ 0,89% | AF1: Penalty | AG1: 43466 | AH1: Bank Charges @ 0,89% | AI1: Penalty | AJ1: 43497 | AK1: Bank Charges @ 0,89% | AL1: Penalty | AM1: 43525 | AN1: Bank Charges @ 0,99% | AO1: Penalty | AP1: 43556 | AQ1: Bank Charges @ 0,99% | AR1: Penalty | AS1: 43586 | AT1: Bank Charges @ 0,99% | AU1: Penalty | AV1: 43617 | AW1: Bank Charges @ 0,99% | AX1: Penalty | AY1: Total Contribution for Current Year
A2: Member 1 | B2: 14/08/2018 | C2: 100 | D2: =200*12 -> 2400 | E2: 0 | F2: ='Catch up Fee'!D2 -> 200 | G2: =C2+D2 -> 2500 | H2: =AY2 -> 1700 | I2: =G2-H2 -> 800 | J2: =I2+M2 -> 800 | K2: =P2+S2+V2+Y2+AB2+AE2+AH2+AK2+AN2+AQ2+AT2+AW2 -> 15.73 | L2: =(H2-K2-C2)*5.5% -> 87.13485 | M2: 0 | N2: =H2-K2-M2+L2 -> 1771.4048 | O2: 0 | P2: =O2*0.89% -> 0 | Q2: 0 | S2: =R2*0.89% -> 0 | T2: 0 | U2: ='2018-2019 B STATEMENT '!B38+'2018-2019 B STATEMENT '!B62 -> 500 | V2: =U2*0.89% -> 4.45 | W2: 0 | X2: ='2018-2019 B STATEMENT '!B102 -> 200 | Y2: =X2*0.89% -> 1.78 | Z2: 0 | AA2: ='2018-2019 B STATEMENT '!B140 -> 400 | AB2: =AA2*0.89% -> 3.56 | AC2: 0 | AD2: 0 | AE2: =AD2*0.89% -> 0 | AF2: 0 | AG2: 0 | AH2: =AG2*0.89% -> 0 | AI2: 0 | AJ2: 0 | AK2: =AJ2*0.89% -> 0 | AL2: 0 | AM2: ='2018-2019 B STATEMENT '!B233 -> 600 | AN2: =AM2*0.99% -> 5.94 | AO2: 0 | AP2: 0 | AQ2: =AP2*0.99% -> 0 | AR2: 0 | AS2: 0 | AT2: =AS2*0.99% -> 0 | AU2: 0 | AV2: 0 | AW2: =AV2*0.99% -> 0 | AX2: 0 | AY2: =O2+R2+U2+X2+AA2+AD2+AJ2+AG2+AM2+AP2+AS2+AV2 -> 1700
A3: Member 2 | B3: 16/02/2019 | C3: 100 | D3: =200*12 -> 2400 | E3: 0 | F3: ='Catch up Fee'!D3 -> 1600 | G3: =C3+D3 -> 2500 | H3: =AY3 -> 2500 | I3: =G3-H3 -> 0 | J3: =I3+M3 -> 0 | K3: =P3+S3+V3+Y3+AB3+AE3+AH3+AK3+AN3+AQ3+AT3+AW3 -> 24.75 | L3: =(H3-K3-C3)*5.5% -> 130.63875 | M3: 0 | N3: =H3-K3-M3+L3 -> 2605.8888 | O3: 0 | P3: =O3*0.89% -> 0 | Q3: 0 | R3: 0 | S3: =R3*0.89% -> 0 | T3: 0 | U3: 0 | V3: =U3*0.89% -> 0 | W3: 0 | X3: 0 | Y3: =X3*0.89% -> 0 | Z3: 0 | AA3: 0 | AB3: =AA3*0.89% -> 0 | AC3: 0 | AD3: 0 | AE3: =AD3*0.89% -> 0 | AF3: 0 | AG3: 0 | AH3: =AG3*0.89% -> 0 | AI3: 0 | AJ3: 0 | AK3: =AJ3*0.89% -> 0 | AL3: 0 | AM3: 0 | AN3: =AM3*0.99% -> 0 | AO3: 0 | AP3: 2500 | AQ3: =AP3*0.99% -> 24.75 | AR3: 0 | AS3: 0 | AT3: =AS3*0.99% -> 0 | AU3: 0 | AV3: 0 | AW3: =AV3*0.99% -> 0 | AX3: 0 | AY3: =O3+R3+U3+X3+AA3+AD3+AJ3+AG3+AM3+AP3+AS3+AV3 -> 2500
A4: Member 3 | B4: 30/07/2018 | C4: 100 | D4: =200*12 -> 2400 | E4: 0 | F4: ='Catch up Fee'!D4 -> 0 | G4: =C4+D4 -> 2500 | H4: =AY4 -> 1500 | I4: =G4-H4-C4 -> 900 | J4: =I4+M4 -> 900 | K4: =P4+S4+V4+Y4+AB4+AE4+AH4+AK4+AN4+AQ4+AT4+AW4 -> 14.35 | L4: =(H4-K4-C4)*5.5% -> 76.21075 | M4: 0 | N4: =H4-K4-M4+L4 -> 1561.8608 | O4: 0 | P4: =O4*0.89% -> 0 | Q4: 0 | R4: 0 | S4: =R4*0.89% -> 0 | T4: 0 | U4: ='2018-2019 B STATEMENT '!B63 -> 500 | V4: =U4*0.89% -> 4.45 | W4: 0 | X4: 0 | Y4: =X4*0.89% -> 0 | Z4: 0 | AA4: 0 | AB4: =AA4*0.89% -> 0 | AC4: 0 | AD4: 0 | AE4: =AD4*0.89% -> 0 | AF4: 0 | AG4: 0 | AH4: =AG4*0.89% -> 0 | AI4: 0 | AJ4: 0 | AK4: =AJ4*0.89% -> 0 | AL4: 0 | AM4: ='2018-2019 B STATEMENT '!B209 -> 500 | AN4: =AM4*0.99% -> 4.95 | AO4: 0 | AP4: ='2018-2019 B STATEMENT '!B260 -> 500 | AQ4: =AP4*0.99% -> 4.95 | AR4: 0 | AS4: 0 | AT4: =AS4*0.99% -> 0 | AU4: 0 | AV4: 0 | AW4: =AV4*0.99% -> 0 | AX4: 0 | AY4: =O4+R4+U4+X4+AA4+AD4+AJ4+AG4+AM4+AP4+AS4+AV4 -> 1500
A5: Member 4 | B5: 11/7/2018 | C5: 100 | D5: =200*12 -> 2400 | E5: 0 | F5: ='Catch up Fee'!D5 -> 0 | G5: =C5+D5 -> 2500 | H5: =AY5 -> 200 | I5: =G5-H5-C5 -> 2200 | J5: =I5+M5 -> 2200 | K5: =P5+S5+V5+Y5+AB5+AE5+AH5+AK5+AN5+AQ5+AT5+AW5 -> 1.78 | L5: =(H5-K5-C5)*5.5% -> 5.4021 | M5: 0 | N5: =H5-K5-M5+L5 -> 203.6221 | O5: 0 | P5: =O5*0.89% -> 0 | Q5: 0 | R5: ='2018-2019 B STATEMENT '!B7 -> 200 | S5: =R5*0.89% -> 1.78 | T5: 0 | U5: 0 | V5: =U5*0.89% -> 0 | W5: 0 | X5: 0 | Y5: =X5*0.89% -> 0 | Z5: 0 | AA5: 0 | AB5: =AA5*0.89% -> 0 | AC5: 0 | AD5: 0 | AE5: =AD5*0.89% -> 0 | AF5: 0 | AG5: 0 | AH5: =AG5*0.89% -> 0 | AI5: 0 | AJ5: 0 | AK5: =AJ5*0.89% -> 0 | AL5: 0 | AM5: 0 | AN5: =AM5*0.99% -> 0 | AO5: 0 | AP5: 0 | AQ5: =AP5*0.99% -> 0 | AR5: 0 | AS5: 0 | AT5: =AS5*0.99% -> 0 | AU5: 0 | AV5: 0 | AW5: =AV5*0.99% -> 0 | AX5: 0 | AY5: =O5+R5+U5+X5+AA5+AD5+AJ5+AG5+AM5+AP5+AS5+AV5 -> 200
A6: Member 5 | B6: 4/7/2018 | C6: 100 | D6: =200*12 -> 2400 | E6: 0 | F6: ='Catch up Fee'!D6 -> 0 | G6: =C6+D6 -> 2500 | H6: =AY6 -> 2500 | I6: =G6-H6-C6 -> -100 | J6: =I6+M6 -> -100 | K6: =P6+S6+V6+Y6+AB6+AE6+AH6+AK6+AN6+AQ6+AT6+AW6 -> 23.05 | L6: =(H6-K6-C6)*5.5% -> 130.73225 | M6: 0 | N6: =H6-K6-M6+L6 -> 2607.6822 | O6: 0 | P6: =O6*0.89% -> 0 | Q6: 0 | R6: ='2018-2019 B STATEMENT '!B10 -> 300 | S6: =R6*0.89% -> 2.67 | T6: 0 | U6: ='2018-2019 B STATEMENT '!B36+'2018-2019 B STATEMENT '!B65 -> 400 | V6: =U6*0.89% -> 3.56 | W6: 0 | X6: 0 | Y6: =X6*0.89% -> 0 | Z6: 0 | AA6: ='2018-2019 B STATEMENT '!B111 -> 200 | AB6: =AA6*0.89% -> 1.78 | AC6: 0 | AD6: ='2018-2019 B STATEMENT '!B154 -> 200 | AE6: =AD6*0.89% -> 1.78 | AF6: 0 | AG6: ='2018-2019 B STATEMENT '!B164+'2018-2019 B STATEMENT '!B165 -> 400 | AH6: =AG6*0.89% -> 3.56 | AI6: 0 | AJ6: ='2018-2019 B STATEMENT '!B190 -> 200 | AK6: =AJ6*0.89% -> 1.78 | AL6: 0 | AM6: ='2018-2019 B STATEMENT '!B217 -> 200 | AN6: =AM6*0.99% -> 1.98 | AO6: 0 | AP6: ='2018-2019 B STATEMENT '!B261 -> 200 | AQ6: =AP6*0.99% -> 1.98 | AR6: 0 | AS6: ='2018-2019 B STATEMENT '!B274 -> 200 | AT6: =AS6*0.99% -> 1.98 | AU6: 0 | AV6: ='2018-2019 B STATEMENT '!B300 -> 200 | AW6: =AV6*0.99% -> 1.98 | AX6: 0 | AY6: =O6+R6+U6+X6+AA6+AD6+AJ6+AG6+AM6+AP6+AS6+AV6 -> 2500
A7: Member 6 | B7: 14/10/2018 | C7: 100 | D7: =200*12 -> 2400 | E7: 0 | F7: ='Catch up Fee'!D7 -> 600 | G7: =C7+D7 -> 2500 | H7: =AY7 -> 1100 | I7: =G7-H7 -> 1400 | J7: =I7+M7 -> 1400 | K7: =P7+S7+V7+Y7+AB7+AE7+AH7+AK7+AN7+AQ7+AT7+AW7 -> 10.89 | L7: =(H7-K7-C7)*5.5% -> 54.40105 | M7: 0 | N7: =H7-K7-M7+L7 -> 1143.511 | O7: 0 | P7: =O7*0.89% -> 0 | Q7: 0 | R7: 0 | S7: =R7*0.89% -> 0 | T7: 0 | U7: 0 | V7: =U7*0.89% -> 0 | W7: 0 | X7: 0 | Y7: =X7*0.89% -> 0 | Z7: 0 | AA7: 0 | AB7: =AA7*0.89% -> 0 | AC7: 0 | AD7: 0 | AE7: =AD7*0.89% -> 0 | AF7: 0 | AG7: 0 | AH7: =AG7*0.89% -> 0 | AI7: 0 | AJ7: 0 | AK7: =AJ7*0.89% -> 0 | AL7: 0 | AM7: ='2018-2019 B STATEMENT '!B228 -> 300 | AN7: =AM7*0.99% -> 2.97 | AO7: 0 | AP7: ='2018-2019 B STATEMENT '!B252 -> 300 | AQ7: =AP7*0.99% -> 2.97 | AR7: 0 | AS7: ='2018-2019 B STATEMENT '!B271 -> 500 | AT7: =AS7*0.99% -> 4.95 | AU7: 0 | AV7: 0 | AW7: =AV7*0.99% -> 0 | AX7: 0 | AY7: =O7+R7+U7+X7+AA7+AD7+AJ7+AG7+AM7+AP7+AS7+AV7 -> 1100
A8: Member 7 | B8: 27/10/2021 | C8: 0 | D8: =200*12 -> 2400 | E8: 0 | F8: ='Catch up Fee'!D8 -> 7800 | G8: =C8+D8 -> 2400 | H8: =AY8 -> 0 | I8: =G8-H8 -> 2400 | J8: =I8+M8 -> 2400 | K8: =P8+S8+V8+Y8+AB8+AE8+AH8+AK8+AN8+AQ8+AT8+AW8 -> 0 | L8: =(H8-K8-C8)*5.5% -> 0 | M8: 0 | N8: =H8-K8-M8+L8 -> 0 | O8: 0 | P8: =O8*0.89% -> 0 | Q8: 0 | R8: 0 | S8: =R8*0.89% -> 0 | T8: 0 | U8: 0 | V8: =U8*0.89% -> 0 | W8: 0 | X8: 0 | Y8: =X8*0.89% -> 0 | Z8: 0 | AA8: 0 | AB8: =AA8*0.89% -> 0 | AC8: 0 | AD8: 0 | AE8: =AD8*0.89% -> 0 | AF8: 0 | AG8: 0 | AH8: =AG8*0.89% -> 0 | AI8: 0 | AJ8: 0 | AK8: =AJ8*0.89% -> 0 | AL8: 0 | AM8: 0 | AN8: =AM8*0.99% -> 0 | AO8: 0 | AP8: 0 | AQ8: =AP8*0.99% -> 0 | AR8: 0 | AS8: 0 | AT8: =AS8*0.99% -> 0 | AU8: 0 | AV8: 0 | AW8: =AV8*0.99% -> 0 | AX8: 0 | AY8: =O8+R8+U8+X8+AA8+AD8+AJ8+AG8+AM8+AP8+AS8+AV8 -> 0
A9: Member 8 | B9: 23/07/2018 | C9: 100 | D9: =200*12 -> 2400 | E9: 0 | F9: ='Catch up Fee'!D9 -> 0 | G9: =C9+D9 -> 2500 | H9: =AY9 -> 1300 | I9: =G9-H9-C9 -> 1100 | J9: =I9+M9 -> 1100 | K9: =P9+S9+V9+Y9+AB9+AE9+AH9+AK9+AN9+AQ9+AT9+AW9 -> 11.57 | L9: =(H9-K9-C9)*5.5% -> 65.36365 | M9: 0 | N9: =H9-K9-M9+L9 -> 1353.7937 | O9: 0 | P9: =O9*0.89% -> 0 | Q9: 0 | R9: ='2018-2019 B STATEMENT '!B13+'2018-2019 B STATEMENT '!B20 -> 500 | S9: =R9*0.89% -> 4.45 | T9: 0 | U9: 0 | V9: =U9*0.89% -> 0 | W9: 0 | X9: 0 | Y9: =X9*0.89% -> 0 | Z9: 0 | AA9: 0 | AB9: =AA9*0.89% -> 0 | AC9: 0 | AD9: 0 | AE9: =AD9*0.89% -> 0 | AF9: 0 | AG9: ='2018-2019 B STATEMENT '!B171 -> 400 | AH9: =AG9*0.89% -> 3.56 | AI9: 0 | AJ9: ='2018-2019 B STATEMENT '!B201 -> 400 | AK9: =AJ9*0.89% -> 3.56 | AL9: 0 | AM9: 0 | AN9: =AM9*0.99% -> 0 | AO9: 0 | AP9: 0 | AQ9: =AP9*0.99% -> 0 | AR9: 0 | AS9: 0 | AT9: =AS9*0.99% -> 0 | AU9: 0 | AV9: 0 | AW9: =AV9*0.99% -> 0 | AX9: 0 | AY9: =O9+R9+U9+X9+AA9+AD9+AJ9+AG9+AM9+AP9+AS9+AV9 -> 1300
A10: Member 9 | B10: 21/07/2018 | C10: 100 | D10: =200*12 -> 2400 | E10: 0 | F10: ='Catch up Fee'!D10 -> 0 | G10: =C10+D10 -> 2500 | H10: =AY10 -> 2100 | I10: =G10-H10-C10 -> 300 | J10: =I10+M10 -> 300 | K10: =P10+S10+V10+Y10+AB10+AE10+AH10+AK10+AN10+AQ10+AT10+AW10 -> 19.49 | L10: =(H10-K10-C10)*5.5% -> 108.92805 | M10: 0 | N10: =H10-K10-M10+L10 -> 2189.4381 | O10: 0 | P10: =O10*0.89% -> 0 | Q10: 0 | R10: ='2018-2019 B STATEMENT '!B21 -> 300 | S10: =R10*0.89% -> 2.67 | T10: 0 | U10: ='2018-2019 B STATEMENT '!B49 -> 200 | V10: =U10*0.89% -> 1.78 | W10: 0 | X10: ='2018-2019 B STATEMENT '!B96 -> 200 | Y10: =X10*0.89% -> 1.78 | Z10: 0 | AA10: ='2018-2019 B STATEMENT '!B121 -> 200 | AB10: =AA10*0.89% -> 1.78 | AC10: 0 | AD10: ='2018-2019 B STATEMENT '!B150 -> 200 | AE10: =AD10*0.89% -> 1.78 | AF10: 0 | AG10: 0 | AH10: =AG10*0.89% -> 0 | AI10: 0 | AJ10: ='2018-2019 B STATEMENT '!B191 -> 200 | AK10: =AJ10*0.89% -> 1.78 | AL10: 0 | AM10: ='2018-2019 B STATEMENT '!B221 -> 200 | AN10: =AM10*0.99% -> 1.98 | AO10: 0 | AP10: ='2018-2019 B STATEMENT '!B253 -> 200 | AQ10: =AP10*0.99% -> 1.98 | AR10: 0 | AS10: ='2018-2019 B STATEMENT '!B280 -> 200 | AT10: =AS10*0.99% -> 1.98 | AU10: 0 | AV10: ='2018-2019 B STATEMENT '!B304 -> 200 | AW10: =AV10*0.99% -> 1.98 | AX10: 0 | AY10: =O10+R10+U10+X10+AA10+AD10+AJ10+AG10+AM10+AP10+AS10+AV10 -> 2100
A11: Member 10 | B11: 30/06/2020 | C11: 0 | D11: =200*12 -> 2400 | E11: 0 | F11: ='Catch up Fee'!D11 -> 2400 | G11: =C11+D11 -> 2400 | H11: =AY11 -> 0 | I11: =G11-H11 -> 2400 | J11: =I11+M11 -> 2400 | K11: =P11+S11+V11+Y11+AB11+AE11+AH11+AK11+AN11+AQ11+AT11+AW11 -> 0 | L11: =(H11-K11-C11)*5.5% -> 0 | M11: 0 | N11: =H11-K11-M11+L11 -> 0 | O11: 0 | P11: =O11*0.89% -> 0 | Q11: 0 | R11: 0 | S11: =R11*0.89% -> 0 | T11: 0 | U11: 0 | V11: =U11*0.89% -> 0 | W11: 0 | X11: 0 | Y11: =X11*0.89% -> 0 | Z11: 0 | AA11: 0 | AB11: =AA11*0.89% -> 0 | AC11: 0 | AD11: 0 | AE11: =AD11*0.89% -> 0 | AF11: 0 | AG11: 0 | AH11: =AG11*0.89% -> 0 | AI11: 0 | AJ11: 0 | AK11: =AJ11*0.89% -> 0 | AL11: 0 | AM11: 0 | AN11: =AM11*0.99% -> 0 | AO11: 0 | AP11: 0 | AQ11: =AP11*0.99% -> 0 | AR11: 0 | AS11: 0 | AT11: =AS11*0.99% -> 0 | AU11: 0 | AV11: 0 | AW11: =AV11*0.99% -> 0 | AX11: 0 | AY11: =O11+R11+U11+X11+AA11+AD11+AJ11+AG11+AM11+AP11+AS11+AV11 -> 0
A12: Member 11 | B12: 15/08/2018 | C12: 100 | D12: =200*12 -> 2400 | E12: 0 | F12: ='Catch up Fee'!D12 -> 200 | G12: =C12+D12 -> 2500 | H12: =AY12 -> 3000 | I12: =G12-H12 -> -500 | J12: =I12+M12 -> -500 | K12: =P12+S12+V12+Y12+AB12+AE12+AH12+AK12+AN12+AQ12+AT12+AW12 -> 27.9 | L12: =(H12-K12-C12)*5.5% -> 157.9655 | M12: 0 | N12: =H12-K12-M12+L12 -> 3130.0655 | O12: 0 | P12: =O12*0.89% -> 0 | Q12: 0 | R12: 0 | S12: =R12*0.89% -> 0 | T12: 0 | U12: 0 | V12: =U12*0.89% -> 0 | W12: 0 | X12: 0 | Y12: =X12*0.89% -> 0 | Z12: 0 | AA12: ='2018-2019 B STATEMENT '!B115 -> 900 | AB12: =AA12*0.89% -> 8.01 | AC12: 0 | AD12: ='2018-2019 B STATEMENT '!B142 -> 300 | AE12: =AD12*0.89% -> 2.67 | AF12: 0 | AG12: 0 | AH12: =AG12*0.89% -> 0 | AI12: 0 | AJ12: ='2018-2019 B STATEMENT '!B188 -> 600 | AK12: =AJ12*0.89% -> 5.34 | AL12: 0 | AM12: ='2018-2019 B STATEMENT '!B236 -> 600 | AN12: =AM12*0.99% -> 5.94 | AO12: 0 | AP12: 0 | AQ12: =AP12*0.99% -> 0 | AR12: 0 | AS12: 0 | AT12: =AS12*0.99% -> 0 | AU12: 0 | AV12: ='2018-2019 B STATEMENT '!B296 -> 600 | AW12: =AV12*0.99% -> 5.94 | AX12: 0 | AY12: =O12+R12+U12+X12+AA12+AD12+AJ12+AG12+AM12+AP12+AS12+AV12 -> 3000
A13: Member 12 | B13: 3/7/2018 | C13: 100 | D13: =200*12 -> 2400 | E13: 0 | F13: ='Catch up Fee'!D13 -> 0 | G13: =C13+D13 -> 2500 | H13: =AY13 -> 2300 | I13: =G13-H13-C13 -> 100 | J13: =I13+M13 -> 100 | K13: =P13+S13+V13+Y13+AB13+AE13+AH13+AK13+AN13+AQ13+AT13+AW13 -> 21.27 | L13: =(H13-K13-C13)*5.5% -> 119.83015 | M13: 0 | N13: =H13-K13-M13+L13 -> 2398.5602 | O13: 0 | P13: =O13*0.89% -> 0 | Q13: 0 | R13: ='2018-2019 B STATEMENT '!B17 -> 300 | S13: =R13*0.89% -> 2.67 | T13: 0 | U13: ='2018-2019 B STATEMENT '!B39 -> 200 | V13: =U13*0.89% -> 1.78 | W13: 0 | X13: ='2018-2019 B STATEMENT '!B92 -> 200 | Y13: =X13*0.89% -> 1.78 | Z13: 0 | AA13: ='2018-2019 B STATEMENT '!B112 -> 200 | AB13: =AA13*0.89% -> 1.78 | AC13: 0 | AD13: ='2018-2019 B STATEMENT '!B143 -> 200 | AE13: =AD13*0.89% -> 1.78 | AF13: 0 | AG13: ='2018-2019 B STATEMENT '!B166 -> 200 | AH13: =AG13*0.89% -> 1.78 | AI13: 0 | AJ13: ='2018-2019 B STATEMENT '!B184 -> 200 | AK13: =AJ13*0.89% -> 1.78 | AL13: 0 | AM13: ='2018-2019 B STATEMENT '!B210 -> 200 | AN13: =AM13*0.99% -> 1.98 | AO13: 0 | AP13: ='2018-2019 B STATEMENT '!B242 -> 200 | AQ13: =AP13*0.99% -> 1.98 | AR13: 0 | AS13: ='2018-2019 B STATEMENT '!B273 -> 200 | AT13: =AS13*0.99% -> 1.98 | AU13: 0 | AV13: ='2018-2019 B STATEMENT '!B297 -> 200 | AW13: =AV13*0.99% -> 1.98 | AX13: 0 | AY13: =O13+R13+U13+X13+AA13+AD13+AJ13+AG13+AM13+AP13+AS13+AV13 -> 2300
A14: Member 13 | B14: 28/07/2018 | C14: 100 | D14: =200*12 -> 2400 | E14: 0 | F14: ='Catch up Fee'!D14 -> 0 | G14: =C14+D14 -> 2500 | H14: =AY14 -> 2100 | I14: =G14-H14-C14 -> 300 | J14: =I14+M14 -> 300 | K14: =P14+S14+V14+Y14+AB14+AE14+AH14+AK14+AN14+AQ14+AT14+AW14 -> 19.29 | L14: =(H14-K14-C14)*5.5% -> 108.93905 | M14: 0 | N14: =H14-K14-M14+L14 -> 2189.649 | O14: 0 | P14: =O14*0.89% -> 0 | Q14: 0 | R14: ='2018-2019 B STATEMENT '!B22 -> 300 | S14: =R14*0.89% -> 2.67 | T14: 0 | U14: 0 | V14: =U14*0.89% -> 0 | W14: 0 | X14: ='2018-2019 B STATEMENT '!B72 -> 600 | Y14: =X14*0.89% -> 5.34 | Z14: 0 | AA14: 0 | AB14: =AA14*0.89% -> 0 | AC14: 0 | AD14: 0 | AE14: =AD14*0.89% -> 0 | AF14: 0 | AG14: 0 | AH14: =AG14*0.89% -> 0 | AI14: 0 | AJ14: ='2018-2019 B STATEMENT '!B186 -> 600 | AK14: =AJ14*0.89% -> 5.34 | AL14: 0 | AM14: 0 | AN14: =AM14*0.99% -> 0 | AO14: 0 | AP14: 0 | AQ14: =AP14*0.99% -> 0 | AR14: 0 | AS14: ='2018-2019 B STATEMENT '!B286 -> 600 | AT14: =AS14*0.99% -> 5.94 | AU14: 0 | AV14: 0 | AW14: =AV14*0.99% -> 0 | AX14: 0 | AY14: =O14+R14+U14+X14+AA14+AD14+AJ14+AG14+AM14+AP14+AS14+AV14 -> 2100
A15: Member 14 | B15: 3/7/2018 | C15: 100 | D15: =200*12 -> 2400 | E15: 0 | F15: ='Catch up Fee'!D15 -> 0 | G15: =C15+D15 -> 2500 | H15: =AY15 -> 100 | I15: =G15-H15-C15 -> 2300 | J15: =I15+M15 -> 2300 | K15: =P15+S15+V15+Y15+AB15+AE15+AH15+AK15+AN15+AQ15+AT15+AW15 -> 0.89 | L15: =(H15-K15-C15)*5.5% -> -0.04895 | M15: 0 | N15: =H15-K15-M15+L15 -> 99.06105 | O15: 0 | P15: =O15*0.89% -> 0 | Q15: 0 | R15: ='2018-2019 B STATEMENT '!B3 -> 100 | S15: =R15*0.89% -> 0.89 | T15: 0 | U15: 0 | V15: =U15*0.89% -> 0 | W15: 0 | X15: 0 | Y15: =X15*0.89% -> 0 | Z15: 0 | AA15: 0 | AB15: =AA15*0.89% -> 0 | AC15: 0 | AD15: 0 | AE15: =AD15*0.89% -> 0 | AF15: 0 | AG15: 0 | AH15: =AG15*0.89% -> 0 | AI15: 0 | AJ15: 0 | AK15: =AJ15*0.89% -> 0 | AL15: 0 | AM15: 0 | AN15: =AM15*0.99% -> 0 | AO15: 0 | AP15: 0 | AQ15: =AP15*0.99% -> 0 | AR15: 0 | AS15: 0 | AT15: =AS15*0.99% -> 0 | AU15: 0 | AV15: 0 | AW15: =AV15*0.99% -> 0 | AX15: 0 | AY15: =O15+R15+U15+X15+AA15+AD15+AJ15+AG15+AM15+AP15+AS15+AV15 -> 100
A16: Member 15 | C16: 100 | D16: =200*12 -> 2400 | E16: 0 | F16: ='Catch up Fee'!D16 -> 0 | G16: =C16+D16 -> 2500 | H16: =AY16 -> 0 | I16: =G16-H16-C16 -> 2400 | J16: =I16+M16 -> 2400 | K16: =P16+S16+V16+Y16+AB16+AE16+AH16+AK16+AN16+AQ16+AT16+AW16 -> 0 | L16: =(H16-K16-C16)*5.5% -> -5.5 | M16: 0 | N16: =H16-K16-M16+L16 -> -5.5 | O16: 0 | P16: =O16*0.89% -> 0 | Q16: 0 | R16: 0 | S16: =R16*0.89% -> 0 | T16: 0 | U16: 0 | V16: =U16*0.89% -> 0 | W16: 0 | X16: 0 | Y16: =X16*0.89% -> 0 | Z16: 0 | AA16: 0 | AB16: =AA16*0.89% -> 0 | AC16: 0 | AD16: 0 | AE16: =AD16*0.89% -> 0 | AF16: 0 | AG16: 0 | AH16: =AG16*0.89% -> 0 | AI16: 0 | AJ16: 0 | AK16: =AJ16*0.89% -> 0 | AL16: 0 | AM16: 0 | AN16: =AM16*0.99% -> 0 | AO16: 0 | AP16: 0 | AQ16: =AP16*0.99% -> 0 | AR16: 0 | AS16: 0 | AT16: =AS16*0.99% -> 0 | AU16: 0 | AV16: 0 | AW16: =AV16*0.99% -> 0 | AX16: 0 | AY16: =O16+R16+U16+X16+AA16+AD16+AJ16+AG16+AM16+AP16+AS16+AV16 -> 0
A17: Member 16 | B17: 28/07/2018 | C17: 100 | D17: =200*12 -> 2400 | E17: 0 | F17: ='Catch up Fee'!D17 -> 0 | G17: =C17+D17 -> 2500 | H17: =AY17 -> 1300 | I17: =G17-H17-C17 -> 1100 | J17: =I17+M17 -> 1100 | K17: =P17+S17+V17+Y17+AB17+AE17+AH17+AK17+AN17+AQ17+AT17+AW17 -> 11.97 | L17: =(H17-K17-C17)*5.5% -> 65.34165 | M17: 0 | N17: =H17-K17-M17+L17 -> 1353.3717 | O17: 0 | P17: =O17*0.89% -> 0 | Q17: 0 | R17: 0 | S17: =R17*0.89% -> 0 | T17: 0 | U17: ='2018-2019 B STATEMENT '!B34+'2018-2019 B STATEMENT '!B64 -> 500 | V17: =U17*0.89% -> 4.45 | W17: 0 | X17: 0 | Y17: =X17*0.89% -> 0 | Z17: 0 | AA17: ='2018-2019 B STATEMENT '!B135 -> 200 | AB17: =AA17*0.89% -> 1.78 | AC17: 0 | AD17: 0 | AE17: =AD17*0.89% -> 0 | AF17: 0 | AG17: ='2018-2019 B STATEMENT '!B174 -> 200 | AH17: =AG17*0.89% -> 1.78 | AI17: 0 | AJ17: 0 | AK17: =AJ17*0.89% -> 0 | AL17: 0 | AM17: ='2018-2019 B STATEMENT '!B206 -> 200 | AN17: =AM17*0.99% -> 1.98 | AO17: 0 | AP17: 0 | AQ17: =AP17*0.99% -> 0 | AR17: 0 | AS17: 0 | AT17: =AS17*0.99% -> 0 | AU17: 0 | AV17: ='2018-2019 B STATEMENT '!B315 -> 200 | AW17: =AV17*0.99% -> 1.98 | AX17: 0 | AY17: =O17+R17+U17+X17+AA17+AD17+AJ17+AG17+AM17+AP17+AS17+AV17 -> 1300
A18: Member 17 | B18: 25/01/2019 | C18: 100 | D18: =200*12 -> 2400 | E18: 0 | F18: ='Catch up Fee'!D18 -> 1200 | G18: =C18+D18 -> 2500 | H18: =AY18 -> 2350 | I18: =G18-H18 -> 150 | J18: =I18+M18 -> 150 | K18: =P18+S18+V18+Y18+AB18+AE18+AH18+AK18+AN18+AQ18+AT18+AW18 -> 22.915 | L18: =(H18-K18-C18)*5.5% -> 122.48968 | M18: 0 | N18: =H18-K18-M18+L18 -> 2449.5747 | O18: 0 | P18: =O18*0.89% -> 0 | Q18: 0 | R18: 0 | S18: =R18*0.89% -> 0 | T18: 0 | U18: 0 | V18: =U18*0.89% -> 0 | W18: 0 | X18: 0 | Y18: =X18*0.89% -> 0 | Z18: 0 | AA18: 0 | AB18: =AA18*0.89% -> 0 | AC18: 0 | AD18: 0 | AE18: =AD18*0.89% -> 0 | AF18: 0 | AG18: 0 | AH18: =AG18*0.89% -> 0 | AI18: 0 | AJ18: ='2018-2019 B STATEMENT '!B192 -> 350 | AK18: =AJ18*0.89% -> 3.115 | AL18: 0 | AM18: ='2018-2019 B STATEMENT '!B211 -> 1500 | AN18: =AM18*0.99% -> 14.85 | AO18: 0 | AP18: ='2018-2019 B STATEMENT '!B243 -> 500 | AQ18: =AP18*0.99% -> 4.95 | AR18: 0 | AS18: 0 | AT18: =AS18*0.99% -> 0 | AU18: 0 | AV18: 0 | AW18: =AV18*0.99% -> 0 | AX18: 0 | AY18: =O18+R18+U18+X18+AA18+AD18+AJ18+AG18+AM18+AP18+AS18+AV18 -> 2350
A19: Member 18 | B19: 3/7/2018 | C19: 100 | D19: =200*12 -> 2400 | E19: 0 | F19: ='Catch up Fee'!D19 -> 0 | G19: =C19+D19 -> 2500 | H19: =AY19 -> 2300 | I19: =G19-H19-C19 -> 100 | J19: =I19+M19 -> 100 | K19: =P19+S19+V19+Y19+AB19+AE19+AH19+AK19+AN19+AQ19+AT19+AW19 -> 21.27 | L19: =(H19-K19-C19)*5.5% -> 119.83015 | M19: 0 | N19: =H19-K19-M19+L19 -> 2398.5602 | O19: 0 | P19: =O19*0.89% -> 0 | Q19: 0 | R19: ='2018-2019 B STATEMENT '!B14 -> 300 | S19: =R19*0.89% -> 2.67 | T19: 0 | U19: ='2018-2019 B STATEMENT '!B46 -> 200 | V19: =U19*0.89% -> 1.78 | W19: 0 | X19: ='2018-2019 B STATEMENT '!B88 -> 200 | Y19: =X19*0.89% -> 1.78 | Z19: 0 | AA19: ='2018-2019 B STATEMENT '!B116 -> 200 | AB19: =AA19*0.89% -> 1.78 | AC19: 0 | AD19: ='2018-2019 B STATEMENT '!B147 -> 200 | AE19: =AD19*0.89% -> 1.78 | AF19: 0 | AG19: ='2018-2019 B STATEMENT '!B175 -> 200 | AH19: =AG19*0.89% -> 1.78 | AI19: 0 | AJ19: ='2018-2019 B STATEMENT '!B189 -> 200 | AK19: =AJ19*0.89% -> 1.78 | AL19: 0 | AM19: ='2018-2019 B STATEMENT '!B213 -> 200 | AN19: =AM19*0.99% -> 1.98 | AO19: 0 | AP19: ='2018-2019 B STATEMENT '!B247 -> 200 | AQ19: =AP19*0.99% -> 1.98 | AR19: 0 | AS19: ='2018-2019 B STATEMENT '!B275 -> 200 | AT19: =AS19*0.99% -> 1.98 | AU19: 0 | AV19: ='2018-2019 B STATEMENT '!B301 -> 200 | AW19: =AV19*0.99% -> 1.98 | AX19: 0 | AY19: =O19+R19+U19+X19+AA19+AD19+AJ19+AG19+AM19+AP19+AS19+AV19 -> 2300
A20: Member 19 | B20: 16/7/2019 | C20: 0 | D20: =200*12 -> 2400 | E20: 0 | F20: ='Catch up Fee'!D20 -> 2400 | G20: =C20+D20 -> 2400 | H20: =AY20 -> 0 | I20: =G20-H20 -> 2400 | J20: =I20+M20 -> 2400 | K20: =P20+S20+V20+Y20+AB20+AE20+AH20+AK20+AN20+AQ20+AT20+AW20 -> 0 | L20: =(H20-K20-C20)*5.5% -> 0 | M20: 0 | N20: =H20-K20-M20+L20 -> 0 | O20: 0 | P20: =O20*0.89% -> 0 | Q20: 0 | R20: 0 | S20: =R20*0.89% -> 0 | T20: 0 | U20: 0 | V20: =U20*0.89% -> 0 | W20: 0 | X20: 0 | Y20: =X20*0.89% -> 0 | Z20: 0 | AA20: 0 | AB20: =AA20*0.89% -> 0 | AC20: 0 | AD20: 0 | AE20: =AD20*0.89% -> 0 | AF20: 0 | AG20: 0 | AH20: =AG20*0.89% -> 0 | AI20: 0 | AJ20: 0 | AK20: =AJ20*0.89% -> 0 | AL20: 0 | AM20: 0 | AN20: =AM20*0.99% -> 0 | AO20: 0 | AP20: 0 | AQ20: =AP20*0.99% -> 0 | AR20: 0 | AS20: 0 | AT20: =AS20*0.99% -> 0 | AU20: 0 | AV20: 0 | AW20: =AV20*0.99% -> 0 | AX20: 0 | AY20: =O20+R20+U20+X20+AA20+AD20+AJ20+AG20+AM20+AP20+AS20+AV20 -> 0
A21: Member 20 | B21: 25/07/2018 | C21: 100 | D21: =200*12 -> 2400 | E21: 0 | F21: ='Catch up Fee'!D21 -> 0 | G21: =C21+D21 -> 2500 | H21: =AY21 -> 900 | I21: =G21-H21-C21 -> 1500 | J21: =I21+M21 -> 1500 | K21: =P21+S21+V21+Y21+AB21+AE21+AH21+AK21+AN21+AQ21+AT21+AW21 -> 8.01 | L21: =(H21-K21-C21)*5.5% -> 43.55945 | M21: 0 | N21: =H21-K21-M21+L21 -> 935.54945 | O21: 0 | P21: =O21*0.89% -> 0 | Q21: 0 | R21: ='2018-2019 B STATEMENT '!B28 -> 300 | S21: =R21*0.89% -> 2.67 | T21: 0 | U21: 0 | V21: =U21*0.89% -> 0 | W21: 0 | X21: ='2018-2019 B STATEMENT '!B76 -> 200 | Y21: =X21*0.89% -> 1.78 | Z21: 0 | AA21: 0 | AB21: =AA21*0.89% -> 0 | AC21: 0 | AD21: 0 | AE21: =AD21*0.89% -> 0 | AF21: 0 | AG21: ='2018-2019 B STATEMENT '!B176 -> 400 | AH21: =AG21*0.89% -> 3.56 | AI21: 0 | AJ21: 0 | AK21: =AJ21*0.89% -> 0 | AL21: 0 | AM21: 0 | AN21: =AM21*0.99% -> 0 | AO21: 0 | AP21: 0 | AQ21: =AP21*0.99% -> 0 | AR21: 0 | AS21: 0 | AT21: =AS21*0.99% -> 0 | AU21: 0 | AV21: 0 | AW21: =AV21*0.99% -> 0 | AX21: 0 | AY21: =O21+R21+U21+X21+AA21+AD21+AJ21+AG21+AM21+AP21+AS21+AV21 -> 900
A22: Member 21 | B22: 20/08/2018 | C22: 100 | D22: =200*12 -> 2400 | E22: 0 | F22: ='Catch up Fee'!D22 -> 200 | G22: =C22+D22 -> 2500 | H22: =AY22 -> 1300 | I22: =G22-H22 -> 1200 | J22: =I22+M22 -> 1200 | K22: =P22+S22+V22+Y22+AB22+AE22+AH22+AK22+AN22+AQ22+AT22+AW22 -> 11.97 | L22: =(H22-K22-C22)*5.5% -> 65.34165 | M22: 0 | N22: =H22-K22-M22+L22 -> 1353.3717 | O22: 0 | P22: =O22*0.89% -> 0 | Q22: 0 | R22: 0 | S22: =R22*0.89% -> 0 | T22: 0 | U22: ='2018-2019 B STATEMENT '!B71 -> 300 | V22: =U22*0.89% -> 2.67 | W22: 0 | X22: ='2018-2019 B STATEMENT '!B87 -> 400 | Y22: =X22*0.89% -> 3.56 | Z22: 0 | AA22: ='2018-2019 B STATEMENT '!B133 -> 200 | AB22: =AA22*0.89% -> 1.78 | AC22: 0 | AD22: 0 | AE22: =AD22*0.89% -> 0 | AF22: 0 | AG22: 0 | AH22: =AG22*0.89% -> 0 | AI22: 0 | AJ22: 0 | AK22: =AJ22*0.89% -> 0 | AL22: 0 | AM22: 0 | AN22: =AM22*0.99% -> 0 | AO22: 0 | AP22: ='2018-2019 B STATEMENT '!B259+'2018-2019 B STATEMENT '!B268 -> 400 | AQ22: =AP22*0.99% -> 3.96 | AR22: 0 | AS22: 0 | AT22: =AS22*0.99% -> 0 | AU22: 0 | AV22: 0 | AW22: =AV22*0.99% -> 0 | AX22: 0 | AY22: =O22+R22+U22+X22+AA22+AD22+AJ22+AG22+AM22+AP22+AS22+AV22 -> 1300
A23: Member 22 | B23: 26/08/2018 | C23: 100 | D23: =200*12 -> 2400 | E23: 0 | F23: ='Catch up Fee'!D23 -> 200 | G23: =C23+D23 -> 2500 | H23: =AY23 -> 2800 | I23: =G23-H23 -> -300 | J23: =I23+M23 -> -300 | K23: =P23+S23+V23+Y23+AB23+AE23+AH23+AK23+AN23+AQ23+AT23+AW23 -> 26.12 | L23: =(H23-K23-C23)*5.5% -> 147.0634 | M23: 0 | N23: =H23-K23-M23+L23 -> 2920.9434 | O23: 0 | P23: =O23*0.89% -> 0 | Q23: 0 | R23: 0 | S23: =R23*0.89% -> 0 | T23: 0 | U23: 0 | V23: =U23*0.89% -> 0 | W23: 0 | X23: ='2018-2019 B STATEMENT '!B85 -> 500 | Y23: =X23*0.89% -> 4.45 | Z23: 0 | AA23: ='2018-2019 B STATEMENT '!B113+'2018-2019 B STATEMENT '!B128 -> 500 | AB23: =AA23*0.89% -> 4.45 | AC23: 0 | AD23: 0 | AE23: =AD23*0.89% -> 0 | AF23: 0 | AG23: ='2018-2019 B STATEMENT '!B177 -> 200 | AH23: =AG23*0.89% -> 1.78 | AI23: 0 | AJ23: ='2018-2019 B STATEMENT '!B205 -> 400 | AK23: =AJ23*0.89% -> 3.56 | AL23: 0 | AM23: 0 | AN23: =AM23*0.99% -> 0 | AO23: 0 | AP23: ='2018-2019 B STATEMENT '!B262 -> 400 | AQ23: =AP23*0.99% -> 3.96 | AR23: 0 | AS23: ='2018-2019 B STATEMENT '!B295 -> 400 | AT23: =AS23*0.99% -> 3.96 | AU23: 0 | AV23: ='2018-2019 B STATEMENT '!B316 -> 400 | AW23: =AV23*0.99% -> 3.96 | AX23: 0 | AY23: =O23+R23+U23+X23+AA23+AD23+AJ23+AG23+AM23+AP23+AS23+AV23 -> 2800
A24: Member 23 | B24: 3/7/2018 | C24: 100 | D24: =200*12 -> 2400 | E24: 0 | F24: ='Catch up Fee'!D24 -> 0 | G24: =C24+D24 -> 2500 | H24: =AY24 -> 500 | I24: =G24-H24-C24 -> 1900 | J24: =I24+M24 -> 1900 | K24: =P24+S24+V24+Y24+AB24+AE24+AH24+AK24+AN24+AQ24+AT24+AW24 -> 4.45 | L24: =(H24-K24-C24)*5.5% -> 21.75525 | M24: 0 | N24: =H24-K24-M24+L24 -> 517.30525 | O24: 0 | P24: =O24*0.89% -> 0 | Q24: 0 | R24: ='2018-2019 B STATEMENT '!B23 -> 300 | S24: =R24*0.89% -> 2.67 | T24: 0 | U24: 0 | V24: =U24*0.89% -> 0 | W24: 0 | X24: ='2018-2019 B STATEMENT '!B77 -> 200 | Y24: =X24*0.89% -> 1.78 | Z24: 0 | AA24: 0 | AB24: =AA24*0.89% -> 0 | AC24: 0 | AD24: 0 | AE24: =AD24*0.89% -> 0 | AF24: 0 | AG24: 0 | AH24: =AG24*0.89% -> 0 | AI24: 0 | AJ24: 0 | AK24: =AJ24*0.89% -> 0 | AL24: 0 | AM24: 0 | AN24: =AM24*0.99% -> 0 | AO24: 0 | AP24: 0 | AQ24: =AP24*0.99% -> 0 | AR24: 0 | AS24: 0 | AT24: =AS24*0.99% -> 0 | AU24: 0 | AV24: 0 | AW24: =AV24*0.99% -> 0 | AX24: 0 | AY24: =O24+R24+U24+X24+AA24+AD24+AJ24+AG24+AM24+AP24+AS24+AV24 -> 500
A25: Member 24 | B25: 27/08/2018 | C25: 100 | D25: =200*12 -> 2400 | E25: 0 | F25: ='Catch up Fee'!D25 -> 200 | G25: =C25+D25 -> 2500 | H25: =AY25 -> 0 | I25: =G25-H25 -> 2500 | J25: =I25+M25 -> 2500 | K25: =P25+S25+V25+Y25+AB25+AE25+AH25+AK25+AN25+AQ25+AT25+AW25 -> 0 | L25: =(H25-K25-C25)*5.5% -> -5.5 | M25: 0 | N25: =H25-K25-M25+L25 -> -5.5 | O25: 0 | P25: =O25*0.89% -> 0 | Q25: 0 | R25: 0 | S25: =R25*0.89% -> 0 | T25: 0 | U25: 0 | V25: =U25*0.89% -> 0 | W25: 0 | X25: 0 | Y25: =X25*0.89% -> 0 | Z25: 0 | AA25: 0 | AB25: =AA25*0.89% -> 0 | AC25: 0 | AD25: 0 | AE25: =AD25*0.89% -> 0 | AF25: 0 | AG25: 0 | AH25: =AG25*0.89% -> 0 | AI25: 0 | AJ25: 0 | AK25: =AJ25*0.89% -> 0 | AL25: 0 | AM25: 0 | AN25: =AM25*0.99% -> 0 | AO25: 0 | AP25: 0 | AQ25: =AP25*0.99% -> 0 | AR25: 0 | AS25: 0 | AT25: =AS25*0.99% -> 0 | AU25: 0 | AV25: 0 | AW25: =AV25*0.99% -> 0 | AX25: 0 | AY25: =O25+R25+U25+X25+AA25+AD25+AJ25+AG25+AM25+AP25+AS25+AV25 -> 0
A26: Member 25 | B26: 29/06/2018 | C26: 100 | D26: =200*12 -> 2400 | E26: 0 | F26: ='Catch up Fee'!D26 -> 0 | G26: =C26+D26 -> 2500 | H26: =AY26 -> 1950 | I26: =G26-H26-C26 -> 450 | J26: =I26+M26 -> 450 | K26: =P26+S26+V26+Y26+AB26+AE26+AH26+AK26+AN26+AQ26+AT26+AW26 -> 17.755 | L26: =(H26-K26-C26)*5.5% -> 100.77347 | M26: 0 | N26: =H26-K26-M26+L26 -> 2033.0185 | O26: ='2018-2019 B STATEMENT '!B2 -> 150 | P26: =O26*0.89% -> 1.335 | Q26: 0 | R26: ='2018-2019 B STATEMENT '!B11 -> 200 | S26: =R26*0.89% -> 1.78 | T26: 0 | V26: =U26*0.89% -> 0 | W26: 0 | X26: ='2018-2019 B STATEMENT '!B73+'2018-2019 B STATEMENT '!B78 -> 1200 | Y26: =X26*0.89% -> 10.68 | Z26: 0 | AA26: 0 | AB26: =AA26*0.89% -> 0 | AC26: 0 | AD26: 0 | AE26: =AD26*0.89% -> 0 | AF26: 0 | AG26: 0 | AH26: =AG26*0.89% -> 0 | AI26: 0 | AJ26: 0 | AK26: =AJ26*0.89% -> 0 | AL26: 0 | AM26: 0 | AN26: =AM26*0.99% -> 0 | AO26: 0 | AP26: 0 | AQ26: =AP26*0.99% -> 0 | AR26: 0 | AS26: ='2018-2019 B STATEMENT '!B290 -> 400 | AT26: =AS26*0.99% -> 3.96 | AU26: 0 | AV26: 0 | AW26: =AV26*0.99% -> 0 | AX26: 0 | AY26: =O26+R26+U26+X26+AA26+AD26+AJ26+AG26+AM26+AP26+AS26+AV26 -> 1950
A27: Member 26 | B27: 4/7/2018 | C27: 100 | D27: =200*12 -> 2400 | E27: 0 | F27: ='Catch up Fee'!D27 -> 0 | G27: =C27+D27 -> 2500 | H27: =AY27 -> 700 | I27: =G27-H27-C27 -> 1700 | J27: =I27+M27 -> 1700 | K27: =P27+S27+V27+Y27+AB27+AE27+AH27+AK27+AN27+AQ27+AT27+AW27 -> 6.23 | L27: =(H27-K27-C27)*5.5% -> 32.65735 | M27: 0 | N27: =H27-K27-M27+L27 -> 726.42735 | O27: 0 | P27: =O27*0.89% -> 0 | Q27: 0 | R27: ='2018-2019 B STATEMENT '!B5+'2018-2019 B STATEMENT '!B30 -> 500 | S27: =R27*0.89% -> 4.45 | T27: 0 | U27: 0 | V27: =U27*0.89% -> 0 | W27: 0 | X27: 0 | Y27: =X27*0.89% -> 0 | Z27: 0 | AA27: ='2018-2019 B STATEMENT '!B134 -> 200 | AB27: =AA27*0.89% -> 1.78 | AC27: 0 | AD27: 0 | AE27: =AD27*0.89% -> 0 | AF27: 0 | AG27: 0 | AH27: =AG27*0.89% -> 0 | AI27: 0 | AJ27: 0 | AK27: =AJ27*0.89% -> 0 | AL27: 0 | AM27: 0 | AN27: =AM27*0.99% -> 0 | AO27: 0 | AP27: 0 | AQ27: =AP27*0.99% -> 0 | AR27: 0 | AS27: 0 | AT27: =AS27*0.99% -> 0 | AU27: 0 | AV27: 0 | AW27: =AV27*0.99% -> 0 | AX27: 0 | AY27: =O27+R27+U27+X27+AA27+AD27+AJ27+AG27+AM27+AP27+AS27+AV27 -> 700
A28: Member 27 | B28: 3/7/2018 | C28: 100 | D28: =200*12 -> 2400 | E28: 0 | F28: ='Catch up Fee'!D28 -> 0 | G28: =C28+D28 -> 2500 | H28: =AY28 -> 0 | I28: =G28-H28-C28 -> 2400 | J28: =I28+M28 -> 2400 | K28: =P28+S28+V28+Y28+AB28+AE28+AH28+AK28+AN28+AQ28+AT28+AW28 -> 0 | L28: =(H28-K28-C28)*5.5% -> -5.5 | M28: 0 | N28: =H28-K28-M28+L28 -> -5.5 | O28: 0 | P28: =O28*0.89% -> 0 | Q28: 0 | R28: 0 | S28: =R28*0.89% -> 0 | T28: 0 | U28: 0 | V28: =U28*0.89% -> 0 | W28: 0 | X28: 0 | Y28: =X28*0.89% -> 0 | Z28: 0 | AA28: 0 | AB28: =AA28*0.89% -> 0 | AC28: 0 | AD28: 0 | AE28: =AD28*0.89% -> 0 | AF28: 0 | AG28: 0 | AH28: =AG28*0.89% -> 0 | AI28: 0 | AJ28: 0 | AK28: =AJ28*0.89% -> 0 | AL28: 0 | AM28: 0 | AN28: =AM28*0.99% -> 0 | AO28: 0 | AP28: 0 | AQ28: =AP28*0.99% -> 0 | AR28: 0 | AS28: 0 | AT28: =AS28*0.99% -> 0 | AU28: 0 | AV28: 0 | AW28: =AV28*0.99% -> 0 | AX28: 0 | AY28: =O28+R28+U28+X28+AA28+AD28+AJ28+AG28+AM28+AP28+AS28+AV28 -> 0
A29: Member 28 | B29: 25/10/2019 | C29: 0 | D29: =200*12 -> 2400 | E29: 0 | F29: ='Catch up Fee'!D29 -> 3000 | G29: =C29+D29 -> 2400 | H29: =AY29 -> 500 | I29: =G29-H29 -> 1900 | J29: =I29+M29 -> 1900 | K29: =P29+S29+V29+Y29+AB29+AE29+AH29+AK29+AN29+AQ29+AT29+AW29 -> 4.45 | L29: =(H29-K29-C29)*5.5% -> 27.25525 | M29: 0 | N29: =H29-K29-M29+L29 -> 522.80525 | O29: 0 | P29: =O29*0.89% -> 0 | Q29: 0 | R29: 0 | S29: =R29*0.89% -> 0 | T29: 0 | U29: 0 | V29: =U29*0.89% -> 0 | W29: 0 | X29: 0 | Y29: =X29*0.89% -> 0 | Z29: 0 | AA29: 0 | AB29: =AA29*0.89% -> 0 | AC29: 0 | AD29: 500 | AE29: =AD29*0.89% -> 4.45 | AF29: 0 | AG29: 0 | AH29: =AG29*0.89% -> 0 | AI29: 0 | AJ29: 0 | AK29: =AJ29*0.89% -> 0 | AL29: 0 | AM29: 0 | AN29: =AM29*0.99% -> 0 | AO29: 0 | AP29: 0 | AQ29: =AP29*0.99% -> 0 | AR29: 0 | AS29: 0 | AT29: =AS29*0.99% -> 0 | AU29: 0 | AV29: 0 | AW29: =AV29*0.99% -> 0 | AX29: 0 | AY29: =O29+R29+U29+X29+AA29+AD29+AJ29+AG29+AM29+AP29+AS29+AV29 -> 500
A30: Member 29 | B30: 31/08/2018 | C30: 100 | D30: =200*12 -> 2400 | E30: 0 | F30: ='Catch up Fee'!D30 -> 200 | G30: =C30+D30 -> 2500 | H30: =AY30 -> 2100 | I30: =G30-H30 -> 400 | J30: =I30+M30 -> 400 | K30: =P30+S30+V30+Y30+AB30+AE30+AH30+AK30+AN30+AQ30+AT30+AW30 -> 20.19 | L30: =(H30-K30-C30)*5.5% -> 108.88955 | M30: 0 | N30: =H30-K30-M30+L30 -> 2188.6995 | O30: 0 | P30: =O30*0.89% -> 0 | Q30: 0 | R30: 0 | S30: =R30*0.89% -> 0 | T30: 0 | U30: 0 | V30: =U30*0.89% -> 0 | W30: 0 | X30: 0 | Y30: =X30*0.89% -> 0 | Z30: 0 | AA30: ='2018-2019 B STATEMENT '!B108+'2018-2019 B STATEMENT '!B109+'2018-2019 B STATEMENT '!B110 -> 600 | AB30: =AA30*0.89% -> 5.34 | AC30: 0 | AD30: 0 | AE30: =AD30*0.89% -> 0 | AF30: 0 | AG30: 0 | AH30: =AG30*0.89% -> 0 | AI30: 0 | AJ30: 0 | AK30: =AJ30*0.89% -> 0 | AL30: 0 | AM30: 0 | AN30: =AM30*0.99% -> 0 | AO30: 0 | AP30: 0 | AQ30: =AP30*0.99% -> 0 | AR30: 0 | AS30: ='2018-2019 B STATEMENT '!B269+'2018-2019 B STATEMENT '!B270 -> 1500 | AT30: =AS30*0.99% -> 14.85 | AU30: 0 | AV30: 0 | AW30: =AV30*0.99% -> 0 | AX30: 0 | AY30: =O30+R30+U30+X30+AA30+AD30+AJ30+AG30+AM30+AP30+AS30+AV30 -> 2100
A31: Member 30 | B31: 3/7/2018 | C31: 100 | D31: =200*12 -> 2400 | E31: 0 | F31: ='Catch up Fee'!D31 -> 0 | G31: =C31+D31 -> 2500 | H31: =AY31 -> 1700 | I31: =G31-H31-C31 -> 700 | J31: =I31+M31 -> 700 | K31: =P31+S31+V31+Y31+AB31+AE31+AH31+AK31+AN31+AQ31+AT31+AW31 -> 15.93 | L31: =(H31-K31-C31)*5.5% -> 87.12385 | M31: 0 | N31: =H31-K31-M31+L31 -> 1771.1938 | O31: 0 | P31: =O31*0.89% -> 0 | Q31: 0 | R31: ='2018-2019 B STATEMENT '!B8 -> 300 | S31: =R31*0.89% -> 2.67 | T31: 0 | U31: 0 | V31: =U31*0.89% -> 0 | W31: 0 | X31: ='2018-2019 B STATEMENT '!B83 -> 400 | Y31: =X31*0.89% -> 3.56 | Z31: 0 | AA31: 0 | AB31: =AA31*0.89% -> 0 | AC31: 0 | AD31: 0 | AE31: =AD31*0.89% -> 0 | AF31: 0 | AG31: ='2018-2019 B STATEMENT '!B178 -> 200 | AH31: =AG31*0.89% -> 1.78 | AI31: 0 | AJ31: 0 | AK31: =AJ31*0.89% -> 0 | AL31: 0 | AM31: ='2018-2019 B STATEMENT '!B218 -> 400 | AN31: =AM31*0.99% -> 3.96 | AO31: 0 | AP31: 0 | AQ31: =AP31*0.99% -> 0 | AR31: 0 | AS31: 0 | AT31: =AS31*0.99% -> 0 | AU31: 0 | AV31: ='2018-2019 B STATEMENT '!B312 -> 400 | AW31: =AV31*0.99% -> 3.96 | AX31: 0 | AY31: =O31+R31+U31+X31+AA31+AD31+AJ31+AG31+AM31+AP31+AS31+AV31 -> 1700
A32: Member 31 | B32: 28/07/2018 | C32: 100 | D32: =200*12 -> 2400 | E32: 0 | F32: ='Catch up Fee'!D32 -> 0 | G32: =C32+D32 -> 2500 | H32: =AY32 -> 500 | I32: =G32-H32-C32 -> 1900 | J32: =I32+M32 -> 1900 | K32: =P32+S32+V32+Y32+AB32+AE32+AH32+AK32+AN32+AQ32+AT32+AW32 -> 4.45 | L32: =(H32-K32-C32)*5.5% -> 21.75525 | M32: 0 | N32: =H32-K32-M32+L32 -> 517.30525 | O32: 0 | P32: =O32*0.89% -> 0 | Q32: 0 | R32: ='2018-2019 B STATEMENT '!B24 -> 300 | S32: =R32*0.89% -> 2.67 | T32: 0 | U32: ='2018-2019 B STATEMENT '!B37 -> 200 | V32: =U32*0.89% -> 1.78 | W32: 0 | X32: 0 | Y32: =X32*0.89% -> 0 | Z32: 0 | AA32: 0 | AB32: =AA32*0.89% -> 0 | AC32: 0 | AD32: 0 | AE32: =AD32*0.89% -> 0 | AF32: 0 | AG32: 0 | AH32: =AG32*0.89% -> 0 | AI32: 0 | AJ32: 0 | AK32: =AJ32*0.89% -> 0 | AL32: 0 | AM32: 0 | AN32: =AM32*0.99% -> 0 | AO32: 0 | AP32: 0 | AQ32: =AP32*0.99% -> 0 | AR32: 0 | AS32: 0 | AT32: =AS32*0.99% -> 0 | AU32: 0 | AV32: 0 | AW32: =AV32*0.99% -> 0 | AX32: 0 | AY32: =O32+R32+U32+X32+AA32+AD32+AJ32+AG32+AM32+AP32+AS32+AV32 -> 500
A33: Member 32 | B33: 22/08/2018 | C33: 100 | D33: =200*12 -> 2400 | E33: 0 | F33: ='Catch up Fee'!D33 -> 200 | G33: =C33+D33 -> 2500 | H33: =AY33 -> 1300 | I33: =G33-H33 -> 1200 | J33: =I33+M33 -> 1200 | K33: =P33+S33+V33+Y33+AB33+AE33+AH33+AK33+AN33+AQ33+AT33+AW33 -> 11.57 | L33: =(H33-K33-C33)*5.5% -> 65.36365 | M33: 0 | N33: =H33-K33-M33+L33 -> 1353.7937 | O33: 0 | P33: =O33*0.89% -> 0 | Q33: 0 | R33: 0 | S33: =R33*0.89% -> 0 | T33: 0 | U33: ='2018-2019 B STATEMENT '!B70 -> 500 | V33: =U33*0.89% -> 4.45 | W33: 0 | X33: ='2018-2019 B STATEMENT '!B104 -> 200 | Y33: =X33*0.89% -> 1.78 | Z33: 0 | AA33: ='2018-2019 B STATEMENT '!B136 -> 200 | AB33: =AA33*0.89% -> 1.78 | AC33: 0 | AD33: ='2018-2019 B STATEMENT '!B159 -> 400 | AE33: =AD33*0.89% -> 3.56 | AF33: 0 | AG33: 0 | AH33: =AG33*0.89% -> 0 | AI33: 0 | AJ33: 0 | AK33: =AJ33*0.89% -> 0 | AL33: 0 | AM33: 0 | AN33: =AM33*0.99% -> 0 | AO33: 0 | AP33: 0 | AQ33: =AP33*0.99% -> 0 | AR33: 0 | AS33: 0 | AT33: =AS33*0.99% -> 0 | AU33: 0 | AV33: 0 | AW33: =AV33*0.99% -> 0 | AX33: 0 | AY33: =O33+R33+U33+X33+AA33+AD33+AJ33+AG33+AM33+AP33+AS33+AV33 -> 1300
A34: Member 33 | C34: 100 | D34: =200*12 -> 2400 | E34: 0 | F34: ='Catch up Fee'!D34 -> 0 | G34: =C34+D34 -> 2500 | H34: =AY34 -> 0 | I34: =G34-H34-C34 -> 2400 | J34: =I34+M34 -> 2400 | K34: =P34+S34+V34+Y34+AB34+AE34+AH34+AK34+AN34+AQ34+AT34+AW34 -> 0 | L34: =(H34-K34-C34)*5.5% -> -5.5 | M34: 0 | N34: =H34-K34-M34+L34 -> -5.5 | O34: 0 | P34: =O34*0.89% -> 0 | Q34: 0 | R34: 0 | S34: =R34*0.89% -> 0 | T34: 0 | U34: 0 | V34: =U34*0.89% -> 0 | W34: 0 | X34: 0 | Y34: =X34*0.89% -> 0 | Z34: 0 | AA34: 0 | AB34: =AA34*0.89% -> 0 | AC34: 0 | AD34: 0 | AE34: =AD34*0.89% -> 0 | AF34: 0 | AG34: 0 | AH34: =AG34*0.89% -> 0 | AI34: 0 | AJ34: 0 | AK34: =AJ34*0.89% -> 0 | AL34: 0 | AM34: 0 | AN34: =AM34*0.99% -> 0 | AO34: 0 | AP34: 0 | AQ34: =AP34*0.99% -> 0 | AR34: 0 | AS34: 0 | AT34: =AS34*0.99% -> 0 | AU34: 0 | AV34: 0 | AW34: =AV34*0.99% -> 0 | AX34: 0 | AY34: =O34+R34+U34+X34+AA34+AD34+AJ34+AG34+AM34+AP34+AS34+AV34 -> 0
A35: Member 34 | B35: 15/08/2018 | C35: 100 | D35: =200*12 -> 2400 | E35: 0 | F35: ='Catch up Fee'!D35 -> 200 | G35: =C35+D35 -> 2500 | H35: =AY35 -> 500 | I35: =G35-H35 -> 2000 | J35: =I35+M35 -> 2000 | K35: =P35+S35+V35+Y35+AB35+AE35+AH35+AK35+AN35+AQ35+AT35+AW35 -> 4.45 | L35: =(H35-K35-C35)*5.5% -> 21.75525 | M35: 0 | N35: =H35-K35-M35+L35 -> 517.30525 | O35: 0 | P35: =O35*0.89% -> 0 | Q35: 0 | R35: 0 | S35: =R35*0.89% -> 0 | T35: 0 | U35: ='2018-2019 B STATEMENT '!B56 -> 300 | V35: =U35*0.89% -> 2.67 | W35: 0 | X35: 0 | Y35: =X35*0.89% -> 0 | Z35: 0 | AA35: ='2018-2019 B STATEMENT '!B129 -> 200 | AB35: =AA35*0.89% -> 1.78 | AC35: 0 | AD35: 0 | AE35: =AD35*0.89% -> 0 | AF35: 0 | AG35: 0 | AH35: =AG35*0.89% -> 0 | AI35: 0 | AJ35: 0 | AK35: =AJ35*0.89% -> 0 | AL35: 0 | AM35: 0 | AN35: =AM35*0.99% -> 0 | AO35: 0 | AP35: 0 | AQ35: =AP35*0.99% -> 0 | AR35: 0 | AS35: 0 | AT35: =AS35*0.99% -> 0 | AU35: 0 | AV35: 0 | AW35: =AV35*0.99% -> 0 | AX35: 0 | AY35: =O35+R35+U35+X35+AA35+AD35+AJ35+AG35+AM35+AP35+AS35+AV35 -> 500
A36: Member 35 | C36: 100 | D36: =200*12 -> 2400 | E36: 0 | F36: ='Catch up Fee'!D36 -> 0 | G36: =C36+D36 -> 2500 | H36: =AY36 -> 0 | I36: =G36-H36-C36 -> 2400 | J36: =I36+M36 -> 2400 | K36: =P36+S36+V36+Y36+AB36+AE36+AH36+AK36+AN36+AQ36+AT36+AW36 -> 0 | L36: =(H36-K36-C36)*5.5% -> -5.5 | M36: 0 | N36: =H36-K36-M36+L36 -> -5.5 | O36: 0 | P36: =O36*0.89% -> 0 | Q36: 0 | R36: 0 | S36: =R36*0.89% -> 0 | T36: 0 | U36: 0 | V36: =U36*0.89% -> 0 | W36: 0 | X36: 0 | Y36: =X36*0.89% -> 0 | Z36: 0 | AA36: 0 | AB36: =AA36*0.89% -> 0 | AC36: 0 | AD36: 0 | AE36: =AD36*0.89% -> 0 | AF36: 0 | AG36: 0 | AH36: =AG36*0.89% -> 0 | AI36: 0 | AJ36: 0 | AK36: =AJ36*0.89% -> 0 | AL36: 0 | AM36: 0 | AN36: =AM36*0.99% -> 0 | AO36: 0 | AP36: 0 | AQ36: =AP36*0.99% -> 0 | AR36: 0 | AS36: 0 | AT36: =AS36*0.99% -> 0 | AU36: 0 | AV36: 0 | AW36: =AV36*0.99% -> 0 | AX36: 0 | AY36: =O36+R36+U36+X36+AA36+AD36+AJ36+AG36+AM36+AP36+AS36+AV36 -> 0
A37: Member 36 | B37: 20/08/2019 | C37: 0 | D37: =200*12 -> 2400 | E37: 0 | F37: ='Catch up Fee'!D37 -> 2600 | G37: =C37+D37 -> 2400 | H37: =AY37 -> 0 | I37: =G37-H37 -> 2400 | J37: =I37+M37 -> 2400 | K37: =P37+S37+V37+Y37+AB37+AE37+AH37+AK37+AN37+AQ37+AT37+AW37 -> 0 | L37: =(H37-K37-C37)*5.5% -> 0 | M37: 0 | N37: =H37-K37-M37+L37 -> 0 | O37: 0 | P37: =O37*0.89% -> 0 | Q37: 0 | R37: 0 | S37: =R37*0.89% -> 0 | T37: 0 | U37: 0 | V37: =U37*0.89% -> 0 | W37: 0 | X37: 0 | Y37: =X37*0.89% -> 0 | Z37: 0 | AA37: 0 | AB37: =AA37*0.89% -> 0 | AC37: 0 | AD37: 0 | AE37: =AD37*0.89% -> 0 | AF37: 0 | AG37: 0 | AH37: =AG37*0.89% -> 0 | AI37: 0 | AJ37: 0 | AK37: =AJ37*0.89% -> 0 | AL37: 0 | AM37: 0 | AN37: =AM37*0.99% -> 0 | AO37: 0 | AP37: 0 | AQ37: =AP37*0.99% -> 0 | AR37: 0 | AS37: 0 | AT37: =AS37*0.99% -> 0 | AU37: 0 | AV37: 0 | AW37: =AV37*0.99% -> 0 | AX37: 0 | AY37: =O37+R37+U37+X37+AA37+AD37+AJ37+AG37+AM37+AP37+AS37+AV37 -> 0
A38: Member 37 | B38: 12/7/2018 | C38: 100 | D38: =200*12 -> 2400 | E38: 0 | F38: ='Catch up Fee'!D38 -> 0 | G38: =C38+D38 -> 2500 | H38: =AY38 -> 2300 | I38: =G38-H38-C38 -> 100 | J38: =I38+M38 -> 100 | K38: =P38+S38+V38+Y38+AB38+AE38+AH38+AK38+AN38+AQ38+AT38+AW38 -> 21.27 | L38: =(H38-K38-C38)*5.5% -> 119.83015 | M38: 0 | N38: =H38-K38-M38+L38 -> 2398.5602 | O38: 0 | P38: =O38*0.89% -> 0 | Q38: 0 | R38: ='2018-2019 B STATEMENT '!B12 -> 300 | S38: =R38*0.89% -> 2.67 | T38: 0 | U38: ='2018-2019 B STATEMENT '!B47 -> 200 | V38: =U38*0.89% -> 1.78 | W38: 0 | X38: ='2018-2019 B STATEMENT '!B89 -> 200 | Y38: =X38*0.89% -> 1.78 | Z38: 0 | AA38: ='2018-2019 B STATEMENT '!B118 -> 200 | AB38: =AA38*0.89% -> 1.78 | AC38: 0 | AD38: ='2018-2019 B STATEMENT '!B148 -> 400 | AE38: =AD38*0.89% -> 3.56 | AF38: 0 | AG38: 0 | AH38: =AG38*0.89% -> 0 | AI38: 0 | AJ38: ='2018-2019 B STATEMENT '!B193 -> 200 | AK38: =AJ38*0.89% -> 1.78 | AL38: 0 | AM38: ='2018-2019 B STATEMENT '!B214 -> 200 | AN38: =AM38*0.99% -> 1.98 | AO38: 0 | AP38: ='2018-2019 B STATEMENT '!B263 -> 400 | AQ38: =AP38*0.99% -> 3.96 | AR38: 0 | AS38: 0 | AT38: =AS38*0.99% -> 0 | AU38: 0 | AV38: ='2018-2019 B STATEMENT '!B313 -> 200 | AW38: =AV38*0.99% -> 1.98 | AX38: 0 | AY38: =O38+R38+U38+X38+AA38+AD38+AJ38+AG38+AM38+AP38+AS38+AV38 -> 2300
A39: Member 38 | B39: 16/7/2019 | C39: 0 | D39: =200*12 -> 2400 | E39: 0 | F39: ='Catch up Fee'!D39 -> 2400 | G39: =C39+D39 -> 2400 | H39: =AY39 -> 0 | I39: =G39-H39 -> 2400 | J39: =I39+M39 -> 2400 | K39: =P39+S39+V39+Y39+AB39+AE39+AH39+AK39+AN39+AQ39+AT39+AW39 -> 0 | L39: =(H39-K39-C39)*5.5% -> 0 | M39: 0 | N39: =H39-K39-M39+L39 -> 0 | O39: 0 | P39: =O39*0.89% -> 0 | Q39: 0 | R39: 0 | S39: =R39*0.89% -> 0 | T39: 0 | U39: 0 | V39: =U39*0.89% -> 0 | W39: 0 | X39: 0 | Y39: =X39*0.89% -> 0 | Z39: 0 | AA39: 0 | AB39: =AA39*0.89% -> 0 | AC39: 0 | AD39: 0 | AE39: =AD39*0.89% -> 0 | AF39: 0 | AG39: 0 | AH39: =AG39*0.89% -> 0 | AI39: 0 | AJ39: 0 | AK39: =AJ39*0.89% -> 0 | AL39: 0 | AM39: 0 | AN39: =AM39*0.99% -> 0 | AO39: 0 | AP39: 0 | AQ39: =AP39*0.99% -> 0 | AR39: 0 | AS39: 0 | AT39: =AS39*0.99% -> 0 | AU39: 0 | AV39: 0 | AW39: =AV39*0.99% -> 0 | AX39: 0 | AY39: =O39+R39+U39+X39+AA39+AD39+AJ39+AG39+AM39+AP39+AS39+AV39 -> 0
A40: Member 39 | B40: 25/08/2018 | C40: 100 | D40: =200*12 -> 2400 | E40: 0 | F40: ='Catch up Fee'!D40 -> 200 | G40: =C40+D40 -> 2500 | H40: =AY40 -> 2310 | I40: =G40-H40 -> 190 | J40: =I40+M40 -> 190 | K40: =P40+S40+V40+Y40+AB40+AE40+AH40+AK40+AN40+AQ40+AT40+AW40 -> 20.559 | L40: =(H40-K40-C40)*5.5% -> 120.41925 | M40: 0 | N40: =H40-K40-M40+L40 -> 2409.8603 | O40: 0 | P40: =O40*0.89% -> 0 | Q40: 0 | R40: ='2018-2019 B STATEMENT '!B18 -> 310 | S40: =R40*0.89% -> 2.759 | T40: 0 | U40: ='2018-2019 B STATEMENT '!B48 -> 1000 | V40: =U40*0.89% -> 8.9 | W40: 0 | X40: 0 | Y40: =X40*0.89% -> 0 | Z40: 0 | AA40: 0 | AB40: =AA40*0.89% -> 0 | AC40: 0 | AD40: ='2018-2019 B STATEMENT '!B155 -> 1000 | AE40: =AD40*0.89% -> 8.9 | AF40: 0 | AG40: 0 | AH40: =AG40*0.89% -> 0 | AI40: 0 | AJ40: 0 | AK40: =AJ40*0.89% -> 0 | AL40: 0 | AM40: 0 | AN40: =AM40*0.99% -> 0 | AO40: 0 | AP40: 0 | AQ40: =AP40*0.99% -> 0 | AR40: 0 | AS40: 0 | AT40: =AS40*0.99% -> 0 | AU40: 0 | AV40: 0 | AW40: =AV40*0.99% -> 0 | AX40: 0 | AY40: =O40+R40+U40+X40+AA40+AD40+AJ40+AG40+AM40+AP40+AS40+AV40 -> 2310
A41: Member 40 | B41: 29/11/2018 | C41: 100 | D41: =200*12 -> 2400 | E41: 0 | F41: ='Catch up Fee'!D41 -> 1000 | G41: =C41+D41 -> 2500 | H41: =AY41 -> 500 | I41: =G41-H41 -> 2000 | J41: =I41+M41 -> 2000 | K41: =P41+S41+V41+Y41+AB41+AE41+AH41+AK41+AN41+AQ41+AT41+AW41 -> 4.45 | L41: =(H41-K41-C41)*5.5% -> 21.75525 | M41: 0 | N41: =H41-K41-M41+L41 -> 517.30525 | O41: 0 | P41: =O41*0.89% -> 0 | Q41: 0 | R41: 0 | S41: =R41*0.89% -> 0 | T41: 0 | U41: ='2018-2019 B STATEMENT '!B40 -> 500 | V41: =U41*0.89% -> 4.45 | W41: 0 | X41: 0 | Y41: =X41*0.89% -> 0 | Z41: 0 | AA41: 0 | AB41: =AA41*0.89% -> 0 | AC41: 0 | AD41: 0 | AE41: =AD41*0.89% -> 0 | AF41: 0 | AG41: 0 | AH41: =AG41*0.89% -> 0 | AI41: 0 | AJ41: 0 | AK41: =AJ41*0.89% -> 0 | AL41: 0 | AM41: 0 | AN41: =AM41*0.99% -> 0 | AO41: 0 | AP41: 0 | AQ41: =AP41*0.99% -> 0 | AR41: 0 | AS41: 0 | AT41: =AS41*0.99% -> 0 | AU41: 0 | AV41: 0 | AW41: =AV41*0.99% -> 0 | AX41: 0 | AY41: =O41+R41+U41+X41+AA41+AD41+AJ41+AG41+AM41+AP41+AS41+AV41 -> 500
A42: Member 41 | B42: 22/07/2019 | C42: 0 | D42: =200*12 -> 2400 | E42: 0 | F42: ='Catch up Fee'!D42 -> 2400 | G42: =C42+D42 -> 2400 | H42: =AY42 -> 0 | I42: =G42-H42 -> 2400 | J42: =I42+M42 -> 2400 | K42: =P42+S42+V42+Y42+AB42+AE42+AH42+AK42+AN42+AQ42+AT42+AW42 -> 0 | L42: =(H42-K42-C42)*5.5% -> 0 | M42: 0 | N42: =H42-K42-M42+L42 -> 0 | O42: 0 | P42: =O42*0.89% -> 0 | Q42: 0 | R42: 0 | S42: =R42*0.89% -> 0 | T42: 0 | U42: 0 | V42: =U42*0.89% -> 0 | W42: 0 | X42: 0 | Y42: =X42*0.89% -> 0 | Z42: 0 | AA42: 0 | AB42: =AA42*0.89% -> 0 | AC42: 0 | AD42: 0 | AE42: =AD42*0.89% -> 0 | AF42: 0 | AG42: 0 | AH42: =AG42*0.89% -> 0 | AI42: 0 | AJ42: 0 | AK42: =AJ42*0.89% -> 0 | AL42: 0 | AM42: 0 | AN42: =AM42*0.99% -> 0 | AO42: 0 | AP42: 0 | AQ42: =AP42*0.99% -> 0 | AR42: 0 | AS42: 0 | AT42: =AS42*0.99% -> 0 | AU42: 0 | AV42: 0 | AW42: =AV42*0.99% -> 0 | AX42: 0 | AY42: =O42+R42+U42+X42+AA42+AD42+AJ42+AG42+AM42+AP42+AS42+AV42 -> 0
A43: Member 42 | B43: 16/9/2018 | C43: 100 | D43: =200*12 -> 2400 | E43: 0 | F43: ='Catch up Fee'!D43 -> 400 | G43: =C43+D43 -> 2500 | H43: =AY43 -> 900 | I43: =G43-H43 -> 1600 | J43: =I43+M43 -> 1600 | K43: =P43+S43+V43+Y43+AB43+AE43+AH43+AK43+AN43+AQ43+AT43+AW43 -> 8.51 | L43: =(H43-K43-C43)*5.5% -> 43.53195 | M43: 0 | N43: =H43-K43-M43+L43 -> 935.02195 | O43: 0 | P43: =O43*0.89% -> 0 | Q43: 0 | R43: 0 | S43: =R43*0.89% -> 0 | T43: 0 | U43: 0 | V43: =U43*0.89% -> 0 | W43: 0 | X43: ='2018-2019 B STATEMENT '!B90 -> 100 | Y43: =X43*0.89% -> 0.89 | Z43: 0 | AA43: 0 | AB43: =AA43*0.89% -> 0 | AC43: 0 | AD43: ='2018-2019 B STATEMENT '!B144 -> 100 | AE43: =AD43*0.89% -> 0.89 | AF43: 0 | AG43: 0 | AH43: =AG43*0.89% -> 0 | AI43: 0 | AJ43: ='2018-2019 B STATEMENT '!B200 -> 200 | AK43: =AJ43*0.89% -> 1.78 | AL43: 0 | AM43: 0 | AN43: =AM43*0.99% -> 0 | AO43: 0 | AP43: ='2018-2019 B STATEMENT '!B248 -> 300 | AQ43: =AP43*0.99% -> 2.97 | AR43: 0 | AS43: ='2018-2019 B STATEMENT '!B292 -> 200 | AT43: =AS43*0.99% -> 1.98 | AU43: 0 | AV43: 0 | AW43: =AV43*0.99% -> 0 | AX43: 0 | AY43: =O43+R43+U43+X43+AA43+AD43+AJ43+AG43+AM43+AP43+AS43+AV43 -> 900
A44: Member 43 | B44: 29/9/2018 | C44: 100 | D44: =200*12 -> 2400 | E44: 0 | F44: ='Catch up Fee'!D44 -> 400 | G44: =C44+D44 -> 2500 | H44: =AY44 -> 2630 | I44: =G44-H44 -> -130 | J44: =I44+M44 -> -130 | K44: =P44+S44+V44+Y44+AB44+AE44+AH44+AK44+AN44+AQ44+AT44+AW44 -> 24.907 | L44: =(H44-K44-C44)*5.5% -> 137.78011 | M44: 0 | N44: =H44-K44-M44+L44 -> 2742.8731 | O44: 0 | P44: =O44*0.89% -> 0 | Q44: 0 | R44: 0 | S44: =R44*0.89% -> 0 | T44: 0 | U44: 0 | V44: =U44*0.89% -> 0 | W44: 0 | X44: ='2018-2019 B STATEMENT '!B103 -> 250 | Y44: =X44*0.89% -> 2.225 | Z44: 0 | AA44: ='2018-2019 B STATEMENT '!B119 -> 250 | AB44: =AA44*0.89% -> 2.225 | AC44: 0 | AD44: ='2018-2019 B STATEMENT '!B151 -> 210 | AE44: =AD44*0.89% -> 1.869 | AF44: 0 | AG44: ='2018-2019 B STATEMENT '!B163 -> 210 | AH44: =AG44*0.89% -> 1.869 | AI44: 0 | AJ44: ='2018-2019 B STATEMENT '!B183 -> 210 | AK44: =AJ44*0.89% -> 1.869 | AL44: 0 | AM44: ='2018-2019 B STATEMENT '!B208+'2018-2019 B STATEMENT '!B239 -> 600 | AN44: =AM44*0.99% -> 5.94 | AO44: 0 | AP44: ='2018-2019 B STATEMENT '!B249 -> 300 | AQ44: =AP44*0.99% -> 2.97 | AR44: 0 | AS44: ='2018-2019 B STATEMENT '!B281 -> 300 | AT44: =AS44*0.99% -> 2.97 | AU44: 0 | AV44: ='2018-2019 B STATEMENT '!B302 -> 300 | AW44: =AV44*0.99% -> 2.97 | AX44: 0 | AY44: =O44+R44+U44+X44+AA44+AD44+AJ44+AG44+AM44+AP44+AS44+AV44 -> 2630
A45: Member 44 | B45: 1/8/2018 | C45: 100 | D45: =200*12 -> 2400 | E45: 0 | F45: ='Catch up Fee'!D45 -> 200 | G45: =C45+D45 -> 2500 | H45: =AY45 -> 300 | I45: =G45-H45 -> 2200 | J45: =I45+M45 -> 2200 | K45: =P45+S45+V45+Y45+AB45+AE45+AH45+AK45+AN45+AQ45+AT45+AW45 -> 2.67 | L45: =(H45-K45-C45)*5.5% -> 10.85315 | M45: 0 | N45: =H45-K45-M45+L45 -> 308.18315 | O45: 0 | P45: =O45*0.89% -> 0 | Q45: 0 | R45: 0 | S45: =R45*0.89% -> 0 | T45: 0 | U45: ='2018-2019 B STATEMENT '!B41 -> 300 | V45: =U45*0.89% -> 2.67 | W45: 0 | X45: 0 | Y45: =X45*0.89% -> 0 | Z45: 0 | AA45: 0 | AB45: =AA45*0.89% -> 0 | AC45: 0 | AD45: 0 | AE45: =AD45*0.89% -> 0 | AF45: 0 | AG45: 0 | AH45: =AG45*0.89% -> 0 | AI45: 0 | AJ45: 0 | AK45: =AJ45*0.89% -> 0 | AL45: 0 | AM45: 0 | AN45: =AM45*0.99% -> 0 | AO45: 0 | AP45: 0 | AQ45: =AP45*0.99% -> 0 | AR45: 0 | AS45: 0 | AT45: =AS45*0.99% -> 0 | AU45: 0 | AV45: 0 | AW45: =AV45*0.99% -> 0 | AX45: 0 | AY45: =O45+R45+U45+X45+AA45+AD45+AJ45+AG45+AM45+AP45+AS45+AV45 -> 300
A46: Member 45 | B46: 13/3/2019 | C46: 100 | D46: =200*12 -> 2400 | E46: 0 | F46: ='Catch up Fee'!D46 -> 1600 | G46: =C46+D46 -> 2500 | H46: =AY46 -> 1000 | I46: =G46-H46 -> 1500 | J46: =I46+M46 -> 1500 | K46: =P46+S46+V46+Y46+AB46+AE46+AH46+AK46+AN46+AQ46+AT46+AW46 -> 9.9 | L46: =(H46-K46-C46)*5.5% -> 48.9555 | M46: 0 | N46: =H46-K46-M46+L46 -> 1039.0555 | O46: 0 | P46: =O46*0.89% -> 0 | Q46: 0 | R46: 0 | S46: =R46*0.89% -> 0 | T46: 0 | U46: 0 | V46: =U46*0.89% -> 0 | W46: 0 | X46: 0 | Y46: =X46*0.89% -> 0 | Z46: 0 | AA46: 0 | AB46: =AA46*0.89% -> 0 | AC46: 0 | AD46: 0 | AE46: =AD46*0.89% -> 0 | AF46: 0 | AG46: 0 | AH46: =AG46*0.89% -> 0 | AI46: 0 | AJ46: 0 | AK46: =AJ46*0.89% -> 0 | AL46: 0 | AM46: 0 | AN46: =AM46*0.99% -> 0 | AO46: 0 | AP46: ='2018-2019 B STATEMENT '!B244 -> 1000 | AQ46: =AP46*0.99% -> 9.9 | AR46: 0 | AS46: 0 | AT46: =AS46*0.99% -> 0 | AU46: 0 | AV46: 0 | AW46: =AV46*0.99% -> 0 | AX46: 0 | AY46: =O46+R46+U46+X46+AA46+AD46+AJ46+AG46+AM46+AP46+AS46+AV46 -> 1000
A47: Member 46 | B47: 3/7/2018 | C47: 100 | D47: =200*12 -> 2400 | E47: 0 | F47: ='Catch up Fee'!D47 -> 0 | G47: =C47+D47 -> 2500 | H47: =AY47 -> 2500 | I47: =G47-H47-C47 -> -100 | J47: =I47+M47 -> -100 | K47: =P47+S47+V47+Y47+AB47+AE47+AH47+AK47+AN47+AQ47+AT47+AW47 -> 24.05 | L47: =(H47-K47-C47)*5.5% -> 130.67725 | M47: 0 | N47: =H47-K47-M47+L47 -> 2606.6273 | O47: 0 | P47: =O47*0.89% -> 0 | Q47: 0 | R47: ='2018-2019 B STATEMENT '!B4+'2018-2019 B STATEMENT '!B19 -> 300 | S47: =R47*0.89% -> 2.67 | T47: 0 | U47: ='2018-2019 B STATEMENT '!B57 -> 400 | V47: =U47*0.89% -> 3.56 | W47: 0 | X47: 0 | Y47: =X47*0.89% -> 0 | Z47: 0 | AA47: 0 | AB47: =AA47*0.89% -> 0 | AC47: 0 | AD47: 0 | AE47: =AD47*0.89% -> 0 | AF47: 0 | AG47: 0 | AH47: =AG47*0.89% -> 0 | AI47: 0 | AJ47: 0 | AK47: =AJ47*0.89% -> 0 | AL47: 0 | AM47: 0 | AN47: =AM47*0.99% -> 0 | AO47: 0 | AP47: ='2018-2019 B STATEMENT '!B264 -> 1800 | AQ47: =AP47*0.99% -> 17.82 | AR47: 0 | AS47: 0 | AT47: =AS47*0.99% -> 0 | AU47: 0 | AV47: 0 | AW47: =AV47*0.99% -> 0 | AX47: 0 | AY47: =O47+R47+U47+X47+AA47+AD47+AJ47+AG47+AM47+AP47+AS47+AV47 -> 2500
A48: Member 47 | B48: 25/9/2018 | C48: 100 | D48: =200*12 -> 2400 | E48: 0 | F48: ='Catch up Fee'!D48 -> 400 | G48: =C48+D48 -> 2500 | H48: =AY48 -> 2510 | I48: =G48-H48 -> -10 | J48: =I48+M48 -> -10 | K48: =P48+S48+V48+Y48+AB48+AE48+AH48+AK48+AN48+AQ48+AT48+AW48 -> 23.539 | L48: =(H48-K48-C48)*5.5% -> 131.25535 | M48: 0 | N48: =H48-K48-M48+L48 -> 2617.7164 | O48: 0 | P48: =O48*0.89% -> 0 | Q48: 0 | R48: 0 | S48: =R48*0.89% -> 0 | T48: 0 | U48: 0 | V48: =U48*0.89% -> 0 | W48: 0 | X48: ='2018-2019 B STATEMENT '!B97 -> 310 | Y48: =X48*0.89% -> 2.759 | Z48: 0 | AA48: ='2018-2019 B STATEMENT '!B117 -> 600 | AB48: =AA48*0.89% -> 5.34 | AC48: 0 | AD48: ='2018-2019 B STATEMENT '!B149 -> 200 | AE48: =AD48*0.89% -> 1.78 | AF48: 0 | AG48: ='2018-2019 B STATEMENT '!B172 -> 200 | AH48: =AG48*0.89% -> 1.78 | AI48: 0 | AJ48: 0 | AK48: =AJ48*0.89% -> 0 | AL48: 0 | AM48: ='2018-2019 B STATEMENT '!B215 -> 400 | AN48: =AM48*0.99% -> 3.96 | AO48: 0 | AP48: ='2018-2019 B STATEMENT '!B250 -> 200 | AQ48: =AP48*0.99% -> 1.98 | AR48: 0 | AS48: ='2018-2019 B STATEMENT '!B276 -> 200 | AT48: =AS48*0.99% -> 1.98 | AU48: 0 | AV48: ='2018-2019 B STATEMENT '!B298 -> 400 | AW48: =AV48*0.99% -> 3.96 | AX48: 0 | AY48: =O48+R48+U48+X48+AA48+AD48+AJ48+AG48+AM48+AP48+AS48+AV48 -> 2510
A49: Member 48 | B49: 28/07/2018 | C49: 100 | D49: =200*12 -> 2400 | E49: 0 | F49: ='Catch up Fee'!D49 -> 0 | G49: =C49+D49 -> 2500 | H49: =AY49 -> 2750 | I49: =G49-H49-C49 -> -350 | J49: =I49+M49 -> -350 | K49: =P49+S49+V49+Y49+AB49+AE49+AH49+AK49+AN49+AQ49+AT49+AW49 -> 25.895 | L49: =(H49-K49-C49)*5.5% -> 144.32577 | M49: 0 | N49: =H49-K49-M49+L49 -> 2868.4308 | O49: 0 | P49: =O49*0.89% -> 0 | Q49: 0 | R49: ='2018-2019 B STATEMENT '!B16 -> 300 | S49: =R49*0.89% -> 2.67 | T49: 0 | U49: ='2018-2019 B STATEMENT '!B59 -> 210 | V49: =U49*0.89% -> 1.869 | W49: 0 | X49: ='2018-2019 B STATEMENT '!B101 -> 210 | Y49: =X49*0.89% -> 1.869 | Z49: 0 | AA49: ='2018-2019 B STATEMENT '!B120 -> 200 | AB49: =AA49*0.89% -> 1.78 | AC49: 0 | AD49: ='2018-2019 B STATEMENT '!B146 -> 210 | AE49: =AD49*0.89% -> 1.869 | AF49: 0 | AG49: 0 | AH49: =AG49*0.89% -> 0 | AI49: 0 | AJ49: ='2018-2019 B STATEMENT '!B204 -> 200 | AK49: =AJ49*0.89% -> 1.78 | AL49: 0 | AM49: ='2018-2019 B STATEMENT '!B227 -> 600 | AN49: =AM49*0.99% -> 5.94 | AO49: 0 | AP49: ='2018-2019 B STATEMENT '!B246 -> 400 | AQ49: =AP49*0.99% -> 3.96 | AR49: 0 | AS49: ='2018-2019 B STATEMENT '!B284 -> 210 | AT49: =AS49*0.99% -> 2.079 | AU49: 0 | AV49: ='2018-2019 B STATEMENT '!B310 -> 210 | AW49: =AV49*0.99% -> 2.079 | AX49: 0 | AY49: =O49+R49+U49+X49+AA49+AD49+AJ49+AG49+AM49+AP49+AS49+AV49 -> 2750
A50: Member 49 | B50: 1/8/2018 | C50: 100 | D50: =200*12 -> 2400 | E50: 0 | F50: ='Catch up Fee'!D50 -> 200 | G50: =C50+D50 -> 2500 | H50: =AY50 -> 500 | I50: =G50-H50 -> 2000 | J50: =I50+M50 -> 2000 | K50: =P50+S50+V50+Y50+AB50+AE50+AH50+AK50+AN50+AQ50+AT50+AW50 -> 4.45 | L50: =(H50-K50-C50)*5.5% -> 21.75525 | M50: 0 | N50: =H50-K50-M50+L50 -> 517.30525 | O50: 0 | P50: =O50*0.89% -> 0 | Q50: 0 | R50: 0 | S50: =R50*0.89% -> 0 | T50: 0 | U50: ='2018-2019 B STATEMENT '!B42+'2018-2019 B STATEMENT '!B66 -> 500 | V50: =U50*0.89% -> 4.45 | W50: 0 | X50: 0 | Y50: =X50*0.89% -> 0 | Z50: 0 | AA50: 0 | AB50: =AA50*0.89% -> 0 | AC50: 0 | AD50: 0 | AE50: =AD50*0.89% -> 0 | AF50: 0 | AG50: 0 | AH50: =AG50*0.89% -> 0 | AI50: 0 | AJ50: 0 | AK50: =AJ50*0.89% -> 0 | AL50: 0 | AM50: 0 | AN50: =AM50*0.99% -> 0 | AO50: 0 | AP50: 0 | AQ50: =AP50*0.99% -> 0 | AR50: 0 | AS50: 0 | AT50: =AS50*0.99% -> 0 | AU50: 0 | AV50: 0 | AW50: =AV50*0.99% -> 0 | AX50: 0 | AY50: =O50+R50+U50+X50+AA50+AD50+AJ50+AG50+AM50+AP50+AS50+AV50 -> 500
A51: Member 50 | B51: 25/07/2018 | C51: 100 | D51: =200*12 -> 2400 | E51: 0 | F51: ='Catch up Fee'!D51 -> 0 | G51: =C51+D51 -> 2500 | H51: =AY51 -> 900 | I51: =G51-H51-C51 -> 1500 | J51: =I51+M51 -> 1500 | K51: =P51+S51+V51+Y51+AB51+AE51+AH51+AK51+AN51+AQ51+AT51+AW51 -> 8.01 | L51: =(H51-K51-C51)*5.5% -> 43.55945 | M51: 0 | N51: =H51-K51-M51+L51 -> 935.54945 | O51: 0 | P51: =O51*0.89% -> 0 | Q51: 0 | R51: 0 | S51: =R51*0.89% -> 0 | T51: 0 | U51: ='2018-2019 B STATEMENT '!B43+'2018-2019 B STATEMENT '!B58 -> 500 | V51: =U51*0.89% -> 4.45 | W51: 0 | X51: 0 | Y51: =X51*0.89% -> 0 | Z51: 0 | AA51: ='2018-2019 B STATEMENT '!B137 -> 400 | AB51: =AA51*0.89% -> 3.56 | AC51: 0 | AD51: 0 | AE51: =AD51*0.89% -> 0 | AF51: 0 | AG51: 0 | AH51: =AG51*0.89% -> 0 | AI51: 0 | AJ51: 0 | AK51: =AJ51*0.89% -> 0 | AL51: 0 | AM51: 0 | AN51: =AM51*0.99% -> 0 | AO51: 0 | AP51: 0 | AQ51: =AP51*0.99% -> 0 | AR51: 0 | AS51: 0 | AT51: =AS51*0.99% -> 0 | AU51: 0 | AV51: 0 | AW51: =AV51*0.99% -> 0 | AX51: 0 | AY51: =O51+R51+U51+X51+AA51+AD51+AJ51+AG51+AM51+AP51+AS51+AV51 -> 900
A52: Member 51 | B52: 21/07/2018 | C52: 100 | D52: =200*12 -> 2400 | E52: 0 | F52: ='Catch up Fee'!D52 -> 0 | G52: =C52+D52 -> 2500 | H52: =AY52 -> 50 | I52: =G52-H52-C52 -> 2350 | J52: =I52+M52 -> 2350 | K52: =P52+S52+V52+Y52+AB52+AE52+AH52+AK52+AN52+AQ52+AT52+AW52 -> 0.495 | L52: =(H52-K52-C52)*5.5% -> -2.777225 | M52: 0 | N52: =H52-K52-M52+L52 -> 46.727775 | O52: 0 | P52: =O52*0.89% -> 0 | Q52: 0 | R52: 0 | S52: =R52*0.89% -> 0 | T52: 0 | U52: 0 | V52: =U52*0.89% -> 0 | W52: 0 | X52: 0 | Y52: =X52*0.89% -> 0 | Z52: 0 | AA52: 0 | AB52: =AA52*0.89% -> 0 | AC52: 0 | AD52: 0 | AE52: =AD52*0.89% -> 0 | AF52: 0 | AG52: 0 | AH52: =AG52*0.89% -> 0 | AI52: 0 | AJ52: 0 | AK52: =AJ52*0.89% -> 0 | AL52: 0 | AM52: 0 | AN52: =AM52*0.99% -> 0 | AO52: 0 | AP52: 0 | AQ52: =AP52*0.99% -> 0 | AR52: 0 | AS52: 0 | AT52: =AS52*0.99% -> 0 | AU52: 0 | AV52: ='2018-2019 B STATEMENT '!B299 -> 50 | AW52: =AV52*0.99% -> 0.495 | AX52: 0 | AY52: =O52+R52+U52+X52+AA52+AD52+AJ52+AG52+AM52+AP52+AS52+AV52 -> 50
A53: Member 52 | B53: 25/07/2018 | C53: 100 | D53: =200*12 -> 2400 | E53: 0 | F53: ='Catch up Fee'!D53 -> 0 | G53: =C53+D53 -> 2500 | H53: =AY53 -> 0 | I53: =G53-H53-C53 -> 2400 | J53: =I53+M53 -> 2400 | K53: =P53+S53+V53+Y53+AB53+AE53+AH53+AK53+AN53+AQ53+AT53+AW53 -> 0 | L53: =(H53-K53-C53)*5.5% -> -5.5 | M53: 0 | N53: =H53-K53-M53+L53 -> -5.5 | O53: 0 | P53: =O53*0.89% -> 0 | Q53: 0 | R53: 0 | S53: =R53*0.89% -> 0 | T53: 0 | U53: 0 | V53: =U53*0.89% -> 0 | W53: 0 | X53: 0 | Y53: =X53*0.89% -> 0 | Z53: 0 | AA53: 0 | AB53: =AA53*0.89% -> 0 | AC53: 0 | AD53: 0 | AE53: =AD53*0.89% -> 0 | AF53: 0 | AG53: 0 | AH53: =AG53*0.89% -> 0 | AI53: 0 | AJ53: 0 | AK53: =AJ53*0.89% -> 0 | AL53: 0 | AM53: 0 | AN53: =AM53*0.99% -> 0 | AO53: 0 | AP53: 0 | AQ53: =AP53*0.99% -> 0 | AR53: 0 | AS53: 0 | AT53: =AS53*0.99% -> 0 | AU53: 0 | AV53: 0 | AW53: =AV53*0.99% -> 0 | AX53: 0 | AY53: =O53+R53+U53+X53+AA53+AD53+AJ53+AG53+AM53+AP53+AS53+AV53 -> 0
A54: Member 53 | B54: 3/7/2018 | C54: 100 | D54: =200*12 -> 2400 | E54: 0 | F54: ='Catch up Fee'!D54 -> 0 | G54: =C54+D54 -> 2500 | H54: =AY54 -> 1800 | I54: =G54-H54-C54 -> 600 | J54: =I54+M54 -> 600 | K54: =P54+S54+V54+Y54+AB54+AE54+AH54+AK54+AN54+AQ54+AT54+AW54 -> 17.82 | L54: =(H54-K54-C54)*5.5% -> 92.5199 | M54: 0 | N54: =H54-K54-M54+L54 -> 1874.6999 | O54: 0 | P54: =O54*0.89% -> 0 | Q54: 0 | R54: 0 | S54: =R54*0.89% -> 0 | T54: 0 | U54: 0 | V54: =U54*0.89% -> 0 | W54: 0 | X54: 0 | Y54: =X54*0.89% -> 0 | Z54: 0 | AA54: 0 | AB54: =AA54*0.89% -> 0 | AC54: 0 | AD54: 0 | AE54: =AD54*0.89% -> 0 | AF54: 0 | AG54: 0 | AH54: =AG54*0.89% -> 0 | AI54: 0 | AJ54: 0 | AK54: =AJ54*0.89% -> 0 | AL54: 0 | AM54: 0 | AN54: =AM54*0.99% -> 0 | AO54: 0 | AP54: 0 | AQ54: =AP54*0.99% -> 0 | AR54: 0 | AS54: ='2018-2019 B STATEMENT '!B285+'2018-2019 B STATEMENT '!B293 -> 1800 | AT54: =AS54*0.99% -> 17.82 | AU54: 0 | AV54: 0 | AW54: =AV54*0.99% -> 0 | AX54: 0 | AY54: =O54+R54+U54+X54+AA54+AD54+AJ54+AG54+AM54+AP54+AS54+AV54 -> 1800
A55: Member 54 | B55: 12/7/2018 | C55: 100 | D55: =200*12 -> 2400 | E55: 0 | F55: ='Catch up Fee'!D55 -> 0 | G55: =C55+D55 -> 2500 | H55: =AY55 -> 700 | I55: =G55-H55-C55 -> 1700 | J55: =I55+M55 -> 1700 | K55: =P55+S55+V55+Y55+AB55+AE55+AH55+AK55+AN55+AQ55+AT55+AW55 -> 6.23 | L55: =(H55-K55-C55)*5.5% -> 32.65735 | M55: 0 | N55: =H55-K55-M55+L55 -> 726.42735 | O55: 0 | P55: =O55*0.89% -> 0 | Q55: 0 | R55: 0 | S55: =R55*0.89% -> 0 | T55: 0 | U55: 0 | V55: =U55*0.89% -> 0 | W55: 0 | X55: ='2018-2019 B STATEMENT '!B701 -> 700 | Y55: =X55*0.89% -> 6.23 | Z55: 0 | AA55: 0 | AB55: =AA55*0.89% -> 0 | AC55: 0 | AD55: 0 | AE55: =AD55*0.89% -> 0 | AF55: 0 | AG55: 0 | AH55: =AG55*0.89% -> 0 | AI55: 0 | AJ55: 0 | AK55: =AJ55*0.89% -> 0 | AL55: 0 | AM55: 0 | AN55: =AM55*0.99% -> 0 | AO55: 0 | AP55: 0 | AQ55: =AP55*0.99% -> 0 | AR55: 0 | AS55: 0 | AT55: =AS55*0.99% -> 0 | AU55: 0 | AV55: 0 | AW55: =AV55*0.99% -> 0 | AX55: 0 | AY55: =O55+R55+U55+X55+AA55+AD55+AJ55+AG55+AM55+AP55+AS55+AV55 -> 700
A56: Member 55 | B56: 12/7/2018 | C56: 100 | D56: =200*12 -> 2400 | E56: 0 | F56: ='Catch up Fee'!D56 -> 0 | G56: =C56+D56 -> 2500 | H56: =AY56 -> 2450 | I56: =G56-H56-C56 -> -50 | J56: =I56+M56 -> -50 | K56: =P56+S56+V56+Y56+AB56+AE56+AH56+AK56+AN56+AQ56+AT56+AW56 -> 22.155 | L56: =(H56-K56-C56)*5.5% -> 128.03148 | M56: 0 | N56: =H56-K56-M56+L56 -> 2555.8765 | O56: 0 | P56: =O56*0.89% -> 0 | Q56: 0 | R56: ='2018-2019 B STATEMENT '!B25 -> 300 | S56: =R56*0.89% -> 2.67 | T56: 0 | U56: 0 | V56: =U56*0.89% -> 0 | W56: 0 | X56: ='2018-2019 B STATEMENT '!B79 -> 500 | Y56: =X56*0.89% -> 4.45 | Z56: 0 | AA56: ='2018-2019 B STATEMENT '!B106 -> 1000 | AB56: =AA56*0.89% -> 8.9 | AC56: 0 | AD56: ='2018-2019 B STATEMENT '!B156 -> 300 | AE56: =AD56*0.89% -> 2.67 | AF56: 0 | AG56: 0 | AH56: =AG56*0.89% -> 0 | AI56: 0 | AJ56: 0 | AK56: =AJ56*0.89% -> 0 | AL56: 0 | AM56: ='2018-2019 B STATEMENT '!B229 -> 350 | AN56: =AM56*0.99% -> 3.465 | AO56: 0 | AP56: 0 | AQ56: =AP56*0.99% -> 0 | AR56: 0 | AS56: 0 | AT56: =AS56*0.99% -> 0 | AU56: 0 | AV56: 0 | AW56: =AV56*0.99% -> 0 | AX56: 0 | AY56: =O56+R56+U56+X56+AA56+AD56+AJ56+AG56+AM56+AP56+AS56+AV56 -> 2450
A57: Member 56 | B57: 26/11/2019 | C57: 0 | D57: =200*12 -> 2400 | E57: 0 | F57: ='Catch up Fee'!D57 -> 3200 | G57: =C57+D57 -> 2400 | H57: =AY57 -> 0 | I57: =G57-H57 -> 2400 | J57: =I57+M57 -> 2400 | K57: =P57+S57+V57+Y57+AB57+AE57+AH57+AK57+AN57+AQ57+AT57+AW57 -> 0 | L57: =(H57-K57-C57)*5.5% -> 0 | M57: 0 | N57: =H57-K57-M57+L57 -> 0 | O57: 0 | P57: =O57*0.89% -> 0 | Q57: 0 | R57: 0 | S57: =R57*0.89% -> 0 | T57: 0 | U57: 0 | V57: =U57*0.89% -> 0 | W57: 0 | X57: 0 | Y57: =X57*0.89% -> 0 | Z57: 0 | AA57: 0 | AB57: =AA57*0.89% -> 0 | AC57: 0 | AD57: 0 | AE57: =AD57*0.89% -> 0 | AF57: 0 | AG57: 0 | AH57: =AG57*0.89% -> 0 | AI57: 0 | AJ57: 0 | AK57: =AJ57*0.89% -> 0 | AL57: 0 | AM57: 0 | AN57: =AM57*0.99% -> 0 | AO57: 0 | AP57: 0 | AQ57: =AP57*0.99% -> 0 | AR57: 0 | AS57: 0 | AT57: =AS57*0.99% -> 0 | AU57: 0 | AV57: 0 | AW57: =AV57*0.99% -> 0 | AX57: 0 | AY57: =O57+R57+U57+X57+AA57+AD57+AJ57+AG57+AM57+AP57+AS57+AV57 -> 0
A58: Member 57 | B58: 07/8/2019 | C58: 0 | D58: =200*12 -> 2400 | E58: 0 | F58: ='Catch up Fee'!D58 -> 2600 | G58: =C58+D58 -> 2400 | H58: =AY58 -> 0 | I58: =G58-H58 -> 2400 | J58: =I58+M58 -> 2400 | K58: =P58+S58+V58+Y58+AB58+AE58+AH58+AK58+AN58+AQ58+AT58+AW58 -> 0 | L58: =(H58-K58-C58)*5.5% -> 0 | M58: 0 | N58: =H58-K58-M58+L58 -> 0 | O58: 0 | P58: =O58*0.89% -> 0 | Q58: 0 | R58: 0 | S58: =R58*0.89% -> 0 | T58: 0 | U58: 0 | V58: =U58*0.89% -> 0 | W58: 0 | X58: 0 | Y58: =X58*0.89% -> 0 | Z58: 0 | AA58: 0 | AB58: =AA58*0.89% -> 0 | AC58: 0 | AD58: 0 | AE58: =AD58*0.89% -> 0 | AF58: 0 | AG58: 0 | AH58: =AG58*0.89% -> 0 | AI58: 0 | AJ58: 0 | AK58: =AJ58*0.89% -> 0 | AL58: 0 | AM58: 0 | AN58: =AM58*0.99% -> 0 | AO58: 0 | AP58: 0 | AQ58: =AP58*0.99% -> 0 | AR58: 0 | AS58: 0 | AT58: =AS58*0.99% -> 0 | AU58: 0 | AV58: 0 | AW58: =AV58*0.99% -> 0 | AX58: 0 | AY58: =O58+R58+U58+X58+AA58+AD58+AJ58+AG58+AM58+AP58+AS58+AV58 -> 0
A59: Member 58 | B59: 25/2/2020 | C59: 0 | D59: =200*12 -> 2400 | E59: 0 | F59: ='Catch up Fee'!D59 -> 3800 | G59: =C59+D59 -> 2400 | H59: =AY59 -> 0 | I59: =G59-H59 -> 2400 | J59: =I59+M59 -> 2400 | K59: =P59+S59+V59+Y59+AB59+AE59+AH59+AK59+AN59+AQ59+AT59+AW59 -> 0 | L59: =(H59-K59-C59)*5.5% -> 0 | M59: 0 | N59: =H59-K59-M59+L59 -> 0 | O59: 0 | P59: =O59*0.89% -> 0 | Q59: 0 | R59: 0 | S59: =R59*0.89% -> 0 | T59: 0 | U59: 0 | V59: =U59*0.89% -> 0 | W59: 0 | X59: 0 | Y59: =X59*0.89% -> 0 | Z59: 0 | AA59: 0 | AB59: =AA59*0.89% -> 0 | AC59: 0 | AD59: 0 | AE59: =AD59*0.89% -> 0 | AF59: 0 | AG59: 0 | AH59: =AG59*0.89% -> 0 | AI59: 0 | AJ59: 0 | AK59: =AJ59*0.89% -> 0 | AL59: 0 | AM59: 0 | AN59: =AM59*0.99% -> 0 | AO59: 0 | AP59: 0 | AQ59: =AP59*0.99% -> 0 | AR59: 0 | AS59: 0 | AT59: =AS59*0.99% -> 0 | AU59: 0 | AV59: 0 | AW59: =AV59*0.99% -> 0 | AX59: 0 | AY59: =O59+R59+U59+X59+AA59+AD59+AJ59+AG59+AM59+AP59+AS59+AV59 -> 0
A60: Member 59 | B60: 20/08/2018 | C60: 100 | D60: =200*12 -> 2400 | E60: 0 | F60: ='Catch up Fee'!D60 -> 200 | G60: =C60+D60 -> 2500 | H60: =AY60 -> 1200 | I60: =G60-H60 -> 1300 | J60: =I60+M60 -> 1300 | K60: =P60+S60+V60+Y60+AB60+AE60+AH60+AK60+AN60+AQ60+AT60+AW60 -> 11.68 | L60: =(H60-K60-C60)*5.5% -> 59.8576 | M60: 0 | N60: =H60-K60-M60+L60 -> 1248.1776 | O60: 0 | P60: =O60*0.89% -> 0 | Q60: 0 | R60: 0 | S60: =R60*0.89% -> 0 | T60: 0 | U60: 0 | V60: =U60*0.89% -> 0 | W60: 0 | X60: ='2018-2019 B STATEMENT '!B80 -> 200 | Y60: =X60*0.89% -> 1.78 | Z60: 0 | AA60: 0 | AB60: =AA60*0.89% -> 0 | AC60: 0 | AD60: 0 | AE60: =AD60*0.89% -> 0 | AF60: 0 | AG60: 0 | AH60: =AG60*0.89% -> 0 | AI60: 0 | AJ60: 0 | AK60: =AJ60*0.89% -> 0 | AL60: 0 | AM60: ='2018-2019 B STATEMENT '!B230 -> 1000 | AN60: =AM60*0.99% -> 9.9 | AO60: 0 | AP60: 0 | AQ60: =AP60*0.99% -> 0 | AR60: 0 | AS60: 0 | AT60: =AS60*0.99% -> 0 | AU60: 0 | AV60: 0 | AW60: =AV60*0.99% -> 0 | AX60: 0 | AY60: =O60+R60+U60+X60+AA60+AD60+AJ60+AG60+AM60+AP60+AS60+AV60 -> 1200
A61: Member 60 | B61: 13/8/2019 | C61: 0 | D61: =200*12 -> 2400 | E61: 0 | F61: ='Catch up Fee'!D61 -> 2600 | G61: =C61+D61 -> 2400 | H61: =AY61 -> 0 | I61: =G61-H61 -> 2400 | J61: =I61+M61 -> 2400 | K61: =P61+S61+V61+Y61+AB61+AE61+AH61+AK61+AN61+AQ61+AT61+AW61 -> 0 | L61: =(H61-K61-C61)*5.5% -> 0 | M61: 0 | N61: =H61-K61-M61+L61 -> 0 | O61: 0 | P61: =O61*0.89% -> 0 | Q61: 0 | R61: 0 | S61: =R61*0.89% -> 0 | T61: 0 | U61: 0 | V61: =U61*0.89% -> 0 | W61: 0 | X61: 0 | Y61: =X61*0.89% -> 0 | Z61: 0 | AA61: 0 | AB61: =AA61*0.89% -> 0 | AC61: 0 | AD61: 0 | AE61: =AD61*0.89% -> 0 | AF61: 0 | AG61: 0 | AH61: =AG61*0.89% -> 0 | AI61: 0 | AJ61: 0 | AK61: =AJ61*0.89% -> 0 | AL61: 0 | AM61: 0 | AN61: =AM61*0.99% -> 0 | AO61: 0 | AP61: 0 | AQ61: =AP61*0.99% -> 0 | AR61: 0 | AS61: 0 | AT61: =AS61*0.99% -> 0 | AU61: 0 | AV61: 0 | AW61: =AV61*0.99% -> 0 | AX61: 0 | AY61: =O61+R61+U61+X61+AA61+AD61+AJ61+AG61+AM61+AP61+AS61+AV61 -> 0
A62: Member 61 | B62: 21/08/2018 | C62: 100 | D62: =200*12 -> 2400 | E62: 0 | F62: ='Catch up Fee'!D62 -> 200 | G62: =C62+D62 -> 2500 | H62: =AY62 -> 2500 | I62: =G62-H62 -> 0 | J62: =I62+M62 -> 0 | K62: =P62+S62+V62+Y62+AB62+AE62+AH62+AK62+AN62+AQ62+AT62+AW62 -> 22.25 | L62: =(H62-K62-C62)*5.5% -> 130.77625 | M62: 0 | N62: =H62-K62-M62+L62 -> 2608.5262 | O62: 0 | P62: =O62*0.89% -> 0 | Q62: 0 | R62: 0 | S62: =R62*0.89% -> 0 | T62: 0 | U62: ='2018-2019 B STATEMENT '!B50 -> 2500 | V62: =U62*0.89% -> 22.25 | W62: 0 | X62: 0 | Y62: =X62*0.89% -> 0 | Z62: 0 | AA62: 0 | AB62: =AA62*0.89% -> 0 | AC62: 0 | AD62: 0 | AE62: =AD62*0.89% -> 0 | AF62: 0 | AG62: 0 | AH62: =AG62*0.89% -> 0 | AI62: 0 | AJ62: 0 | AK62: =AJ62*0.89% -> 0 | AL62: 0 | AM62: 0 | AN62: =AM62*0.99% -> 0 | AO62: 0 | AP62: 0 | AQ62: =AP62*0.99% -> 0 | AR62: 0 | AS62: 0 | AT62: =AS62*0.99% -> 0 | AU62: 0 | AV62: 0 | AW62: =AV62*0.99% -> 0 | AX62: 0 | AY62: =O62+R62+U62+X62+AA62+AD62+AJ62+AG62+AM62+AP62+AS62+AV62 -> 2500
A63: Member 62 | B63: 21/08/2018 | C63: 100 | D63: =200*12 -> 2400 | E63: 0 | F63: ='Catch up Fee'!D63 -> 200 | G63: =C63+D63 -> 2500 | H63: =AY63 -> 700 | I63: =G63-H63 -> 1800 | J63: =I63+M63 -> 1800 | K63: =P63+S63+V63+Y63+AB63+AE63+AH63+AK63+AN63+AQ63+AT63+AW63 -> 6.23 | L63: =(H63-K63-C63)*5.5% -> 32.65735 | M63: 0 | N63: =H63-K63-M63+L63 -> 726.42735 | O63: 0 | P63: =O63*0.89% -> 0 | Q63: 0 | R63: 0 | S63: =R63*0.89% -> 0 | T63: 0 | U63: 0 | V63: =U63*0.89% -> 0 | W63: 0 | X63: ='2018-2019 B STATEMENT '!B93 -> 400 | Y63: =X63*0.89% -> 3.56 | Z63: 0 | AA63: 0 | AB63: =AA63*0.89% -> 0 | AC63: 0 | AD63: ='2018-2019 B STATEMENT '!B160 -> 300 | AE63: =AD63*0.89% -> 2.67 | AF63: 0 | AG63: 0 | AH63: =AG63*0.89% -> 0 | AI63: 0 | AJ63: 0 | AK63: =AJ63*0.89% -> 0 | AL63: 0 | AM63: 0 | AN63: =AM63*0.99% -> 0 | AO63: 0 | AP63: 0 | AQ63: =AP63*0.99% -> 0 | AR63: 0 | AS63: 0 | AT63: =AS63*0.99% -> 0 | AU63: 0 | AV63: 0 | AW63: =AV63*0.99% -> 0 | AX63: 0 | AY63: =O63+R63+U63+X63+AA63+AD63+AJ63+AG63+AM63+AP63+AS63+AV63 -> 700
A64: Member 63 | B64: 31/07/2018 | C64: 100 | D64: =200*12 -> 2400 | E64: 0 | F64: ='Catch up Fee'!D64 -> 0 | G64: =C64+D64 -> 2500 | H64: =AY64 -> 710 | I64: =G64-H64-C64 -> 1690 | J64: =I64+M64 -> 1690 | K64: =P64+S64+V64+Y64+AB64+AE64+AH64+AK64+AN64+AQ64+AT64+AW64 -> 6.319 | L64: =(H64-K64-C64)*5.5% -> 33.202455 | M64: 0 | N64: =H64-K64-M64+L64 -> 736.88346 | O64: 0 | P64: =O64*0.89% -> 0 | Q64: 0 | R64: ='2018-2019 B STATEMENT '!B31 -> 400 | S64: =R64*0.89% -> 3.56 | T64: 0 | U64: ='2018-2019 B STATEMENT '!B55 -> 310 | V64: =U64*0.89% -> 2.759 | W64: 0 | X64: 0 | Y64: =X64*0.89% -> 0 | Z64: 0 | AA64: 0 | AB64: =AA64*0.89% -> 0 | AC64: 0 | AD64: 0 | AE64: =AD64*0.89% -> 0 | AF64: 0 | AG64: 0 | AH64: =AG64*0.89% -> 0 | AI64: 0 | AJ64: 0 | AK64: =AJ64*0.89% -> 0 | AL64: 0 | AM64: 0 | AN64: =AM64*0.99% -> 0 | AO64: 0 | AP64: 0 | AQ64: =AP64*0.99% -> 0 | AR64: 0 | AS64: 0 | AT64: =AS64*0.99% -> 0 | AU64: 0 | AV64: 0 | AW64: =AV64*0.99% -> 0 | AX64: 0 | AY64: =O64+R64+U64+X64+AA64+AD64+AJ64+AG64+AM64+AP64+AS64+AV64 -> 710
A65: Member 64 | B65: 31/07/2018 | C65: 100 | D65: =200*12 -> 2400 | E65: 0 | F65: ='Catch up Fee'!D65 -> 0 | G65: =C65+D65 -> 2500 | H65: =AY65 -> 300 | I65: =G65-H65-C65 -> 2100 | J65: =I65+M65 -> 2100 | K65: =P65+S65+V65+Y65+AB65+AE65+AH65+AK65+AN65+AQ65+AT65+AW65 -> 2.67 | L65: =(H65-K65-C65)*5.5% -> 10.85315 | M65: 0 | N65: =H65-K65-M65+L65 -> 308.18315 | O65: 0 | P65: =O65*0.89% -> 0 | Q65: 0 | R65: 0 | S65: =R65*0.89% -> 0 | T65: 0 | U65: ='2018-2019 B STATEMENT '!B68 -> 300 | V65: =U65*0.89% -> 2.67 | W65: 0 | X65: 0 | Y65: =X65*0.89% -> 0 | Z65: 0 | AA65: 0 | AB65: =AA65*0.89% -> 0 | AC65: 0 | AD65: 0 | AE65: =AD65*0.89% -> 0 | AF65: 0 | AG65: 0 | AH65: =AG65*0.89% -> 0 | AI65: 0 | AJ65: 0 | AK65: =AJ65*0.89% -> 0 | AL65: 0 | AM65: 0 | AN65: =AM65*0.99% -> 0 | AO65: 0 | AP65: 0 | AQ65: =AP65*0.99% -> 0 | AR65: 0 | AS65: 0 | AT65: =AS65*0.99% -> 0 | AU65: 0 | AV65: 0 | AW65: =AV65*0.99% -> 0 | AX65: 0 | AY65: =O65+R65+U65+X65+AA65+AD65+AJ65+AG65+AM65+AP65+AS65+AV65 -> 300
A66: Member 65 | B66: 25/10/2018 | C66: 100 | D66: =200*12 -> 2400 | E66: 0 | F66: ='Catch up Fee'!D66 -> 600 | G66: =C66+D66 -> 2500 | H66: =AY66 -> 1000 | I66: =G66-H66 -> 1500 | J66: =I66+M66 -> 1500 | K66: =P66+S66+V66+Y66+AB66+AE66+AH66+AK66+AN66+AQ66+AT66+AW66 -> 9.5 | L66: =(H66-K66-C66)*5.5% -> 48.9775 | M66: 0 | N66: =H66-K66-M66+L66 -> 1039.4775 | O66: 0 | P66: =O66*0.89% -> 0 | Q66: 0 | R66: 0 | S66: =R66*0.89% -> 0 | T66: 0 | U66: 0 | V66: =U66*0.89% -> 0 | W66: 0 | X66: 0 | Y66: =X66*0.89% -> 0 | Z66: 0 | AA66: ='2018-2019 B STATEMENT '!B122 -> 400 | AB66: =AA66*0.89% -> 3.56 | AC66: 0 | AD66: 0 | AE66: =AD66*0.89% -> 0 | AF66: 0 | AG66: 0 | AH66: =AG66*0.89% -> 0 | AI66: 0 | AJ66: 0 | AK66: =AJ66*0.89% -> 0 | AL66: 0 | AM66: ='2018-2019 B STATEMENT '!B231 -> 400 | AN66: =AM66*0.99% -> 3.96 | AO66: 0 | AP66: ='2018-2019 B STATEMENT '!B241 -> 200 | AQ66: =AP66*0.99% -> 1.98 | AR66: 0 | AS66: 0 | AT66: =AS66*0.99% -> 0 | AU66: 0 | AV66: 0 | AW66: =AV66*0.99% -> 0 | AX66: 0 | AY66: =O66+R66+U66+X66+AA66+AD66+AJ66+AG66+AM66+AP66+AS66+AV66 -> 1000
A67: Member 66 | B67: 1/8/2018 | C67: 100 | D67: =200*12 -> 2400 | E67: 0 | F67: ='Catch up Fee'!D67 -> 200 | G67: =C67+D67 -> 2500 | H67: =AY67 -> 1300 | I67: =G67-H67 -> 1200 | J67: =I67+M67 -> 1200 | K67: =P67+S67+V67+Y67+AB67+AE67+AH67+AK67+AN67+AQ67+AT67+AW67 -> 11.57 | L67: =(H67-K67-C67)*5.5% -> 65.36365 | M67: 0 | N67: =H67-K67-M67+L67 -> 1353.7937 | O67: 0 | P67: =O67*0.89% -> 0 | Q67: 0 | R67: ='2018-2019 B STATEMENT '!B32 -> 300 | S67: =R67*0.89% -> 2.67 | T67: 0 | U67: ='2018-2019 B STATEMENT '!B60 -> 1000 | V67: =U67*0.89% -> 8.9 | W67: 0 | X67: 0 | Y67: =X67*0.89% -> 0 | Z67: 0 | AA67: 0 | AB67: =AA67*0.89% -> 0 | AC67: 0 | AD67: 0 | AE67: =AD67*0.89% -> 0 | AF67: 0 | AG67: 0 | AH67: =AG67*0.89% -> 0 | AI67: 0 | AJ67: 0 | AK67: =AJ67*0.89% -> 0 | AL67: 0 | AM67: 0 | AN67: =AM67*0.99% -> 0 | AO67: 0 | AP67: 0 | AQ67: =AP67*0.99% -> 0 | AR67: 0 | AS67: 0 | AT67: =AS67*0.99% -> 0 | AU67: 0 | AV67: 0 | AW67: =AV67*0.99% -> 0 | AX67: 0 | AY67: =O67+R67+U67+X67+AA67+AD67+AJ67+AG67+AM67+AP67+AS67+AV67 -> 1300
A68: Member 67 | B68: 3/7/2018 | C68: 100 | D68: =200*12 -> 2400 | E68: 0 | F68: ='Catch up Fee'!D68 -> 0 | G68: =C68+D68 -> 2500 | H68: =AY68 -> 2100 | I68: =G68-H68-C68 -> 300 | J68: =I68+M68 -> 300 | K68: =P68+S68+V68+Y68+AB68+AE68+AH68+AK68+AN68+AQ68+AT68+AW68 -> 19.69 | L68: =(H68-K68-C68)*5.5% -> 108.91705 | M68: 0 | N68: =H68-K68-M68+L68 -> 2189.227 | O68: 0 | P68: =O68*0.89% -> 0 | Q68: 0 | R68: 0 | S68: =R68*0.89% -> 0 | T68: 0 | U68: ='2018-2019 B STATEMENT '!B44 -> 300 | V68: =U68*0.89% -> 2.67 | W68: 0 | X68: ='2018-2019 B STATEMENT '!B81 -> 800 | Y68: =X68*0.89% -> 7.12 | Z68: 0 | AA68: 0 | AB68: =AA68*0.89% -> 0 | AC68: 0 | AD68: 0 | AE68: =AD68*0.89% -> 0 | AF68: 0 | AG68: 0 | AH68: =AG68*0.89% -> 0 | AI68: 0 | AJ68: 0 | AK68: =AJ68*0.89% -> 0 | AL68: 0 | AM68: 0 | AN68: =AM68*0.99% -> 0 | AO68: 0 | AP68: 0 | AQ68: =AP68*0.99% -> 0 | AR68: 0 | AS68: ='2018-2019 B STATEMENT '!B294 -> 600 | AT68: =AS68*0.99% -> 5.94 | AU68: 0 | AV68: ='2018-2019 B STATEMENT '!B314 -> 400 | AW68: =AV68*0.99% -> 3.96 | AX68: 0 | AY68: =O68+R68+U68+X68+AA68+AD68+AJ68+AG68+AM68+AP68+AS68+AV68 -> 2100
A69: Member 68 | B69: 26/04/2019 | C69: 100 | D69: =200*12 -> 2400 | E69: 0 | F69: ='Catch up Fee'!D69 -> 1800 | G69: =C69+D69 -> 2500 | H69: =AY69 -> 500 | I69: =G69-H69 -> 2000 | J69: =I69+M69 -> 2000 | K69: =P69+S69+V69+Y69+AB69+AE69+AH69+AK69+AN69+AQ69+AT69+AW69 -> 4.95 | L69: =(H69-K69-C69)*5.5% -> 21.72775 | M69: 0 | N69: =H69-K69-M69+L69 -> 516.77775 | O69: 0 | P69: =O69*0.89% -> 0 | Q69: 0 | R69: 0 | S69: =R69*0.89% -> 0 | T69: 0 | U69: 0 | V69: =U69*0.89% -> 0 | W69: 0 | X69: 0 | Y69: =X69*0.89% -> 0 | Z69: 0 | AA69: 0 | AB69: =AA69*0.89% -> 0 | AC69: 0 | AD69: 0 | AE69: =AD69*0.89% -> 0 | AF69: 0 | AG69: 0 | AH69: =AG69*0.89% -> 0 | AI69: 0 | AJ69: 0 | AK69: =AJ69*0.89% -> 0 | AL69: 0 | AM69: 0 | AN69: =AM69*0.99% -> 0 | AO69: 0 | AP69: 0 | AQ69: =AP69*0.99% -> 0 | AR69: 0 | AS69: ='2018-2019 B STATEMENT '!B279 -> 300 | AT69: =AS69*0.99% -> 2.97 | AU69: 0 | AV69: ='2018-2019 B STATEMENT '!B311 -> 200 | AW69: =AV69*0.99% -> 1.98 | AX69: 0 | AY69: =O69+R69+U69+X69+AA69+AD69+AJ69+AG69+AM69+AP69+AS69+AV69 -> 500
A70: Member 69 | B70: 28/07/2018 | C70: 100 | D70: =200*12 -> 2400 | E70: 0 | F70: ='Catch up Fee'!D70 -> 0 | G70: =C70+D70 -> 2500 | H70: =AY70 -> 2450 | I70: =G70-H70-C70 -> -50 | J70: =I70+M70 -> -50 | K70: =P70+S70+V70+Y70+AB70+AE70+AH70+AK70+AN70+AQ70+AT70+AW70 -> 22.155 | L70: =(H70-K70-C70)*5.5% -> 128.03148 | M70: 0 | N70: =H70-K70-M70+L70 -> 2555.8765 | O70: 0 | P70: =O70*0.89% -> 0 | Q70: 0 | R70: ='2018-2019 B STATEMENT '!B26 -> 300 | S70: =R70*0.89% -> 2.67 | T70: 0 | U70: 0 | V70: =U70*0.89% -> 0 | W70: 0 | X70: ='2018-2019 B STATEMENT '!B74 -> 500 | Y70: =X70*0.89% -> 4.45 | Z70: 0 | AA70: ='2018-2019 B STATEMENT '!B107 -> 1000 | AB70: =AA70*0.89% -> 8.9 | AC70: 0 | AD70: ='2018-2019 B STATEMENT '!B157 -> 300 | AE70: =AD70*0.89% -> 2.67 | AF70: 0 | AG70: 0 | AH70: =AG70*0.89% -> 0 | AI70: 0 | AJ70: 0 | AK70: =AJ70*0.89% -> 0 | AL70: 0 | AM70: ='2018-2019 B STATEMENT '!B234 -> 350 | AN70: =AM70*0.99% -> 3.465 | AO70: 0 | AP70: 0 | AQ70: =AP70*0.99% -> 0 | AR70: 0 | AS70: 0 | AT70: =AS70*0.99% -> 0 | AU70: 0 | AV70: 0 | AW70: =AV70*0.99% -> 0 | AX70: 0 | AY70: =O70+R70+U70+X70+AA70+AD70+AJ70+AG70+AM70+AP70+AS70+AV70 -> 2450
A71: Member 70 | B71: 18/10/2018 | C71: 100 | D71: =200*12 -> 2400 | E71: 0 | F71: ='Catch up Fee'!D71 -> 600 | G71: =C71+D71 -> 2500 | H71: =AY71 -> 1200 | I71: =G71-H71 -> 1300 | J71: =I71+M71 -> 1300 | K71: =P71+S71+V71+Y71+AB71+AE71+AH71+AK71+AN71+AQ71+AT71+AW71 -> 11.88 | L71: =(H71-K71-C71)*5.5% -> 59.8466 | M71: 0 | N71: =H71-K71-M71+L71 -> 1247.9666 | O71: 0 | P71: =O71*0.89% -> 0 | Q71: 0 | R71: 0 | S71: =R71*0.89% -> 0 | T71: 0 | U71: 0 | V71: =U71*0.89% -> 0 | W71: 0 | X71: 0 | Y71: =X71*0.89% -> 0 | Z71: 0 | AA71: 0 | AB71: =AA71*0.89% -> 0 | AC71: 0 | AD71: 0 | AE71: =AD71*0.89% -> 0 | AF71: 0 | AG71: 0 | AH71: =AG71*0.89% -> 0 | AI71: 0 | AJ71: 0 | AK71: =AJ71*0.89% -> 0 | AL71: 0 | AM71: ='2018-2019 B STATEMENT '!B222 -> 300 | AN71: =AM71*0.99% -> 2.97 | AO71: 0 | AP71: ='2018-2019 B STATEMENT '!B254 -> 300 | AQ71: =AP71*0.99% -> 2.97 | AR71: 0 | AS71: ='2018-2019 B STATEMENT '!B282 -> 300 | AT71: =AS71*0.99% -> 2.97 | AU71: 0 | AV71: ='2018-2019 B STATEMENT '!B305 -> 300 | AW71: =AV71*0.99% -> 2.97 | AX71: 0 | AY71: =O71+R71+U71+X71+AA71+AD71+AJ71+AG71+AM71+AP71+AS71+AV71 -> 1200
A72: Member 71 | B72: 31/08/2018 | C72: 100 | D72: =200*12 -> 2400 | E72: 0 | F72: ='Catch up Fee'!D72 -> 200 | G72: =C72+D72 -> 2500 | H72: =AY72 -> 0 | I72: =G72-H72 -> 2500 | J72: =I72+M72 -> 2500 | K72: =P72+S72+V72+Y72+AB72+AE72+AH72+AK72+AN72+AQ72+AT72+AW72 -> 0 | L72: =(H72-K72-C72)*5.5% -> -5.5 | M72: 0 | N72: =H72-K72-M72+L72 -> -5.5 | O72: 0 | P72: =O72*0.89% -> 0 | Q72: 0 | R72: 0 | S72: =R72*0.89% -> 0 | T72: 0 | U72: 0 | V72: =U72*0.89% -> 0 | W72: 0 | X72: 0 | Y72: =X72*0.89% -> 0 | Z72: 0 | AA72: 0 | AB72: =AA72*0.89% -> 0 | AC72: 0 | AD72: 0 | AE72: =AD72*0.89% -> 0 | AF72: 0 | AG72: 0 | AH72: =AG72*0.89% -> 0 | AI72: 0 | AJ72: 0 | AK72: =AJ72*0.89% -> 0 | AL72: 0 | AM72: 0 | AN72: =AM72*0.99% -> 0 | AO72: 0 | AP72: 0 | AQ72: =AP72*0.99% -> 0 | AR72: 0 | AS72: 0 | AT72: =AS72*0.99% -> 0 | AU72: 0 | AV72: 0 | AW72: =AV72*0.99% -> 0 | AX72: 0 | AY72: =O72+R72+U72+X72+AA72+AD72+AJ72+AG72+AM72+AP72+AS72+AV72 -> 0
A73: Member 72 | B73: 2/8/2018 | C73: 100 | D73: =200*12 -> 2400 | E73: 0 | F73: ='Catch up Fee'!D73 -> 200 | G73: =C73+D73 -> 2500 | H73: =AY73 -> 2300 | I73: =G73-H73 -> 200 | J73: =I73+M73 -> 200 | K73: =P73+S73+V73+Y73+AB73+AE73+AH73+AK73+AN73+AQ73+AT73+AW73 -> 21.27 | L73: =(H73-K73-C73)*5.5% -> 119.83015 | M73: 0 | N73: =H73-K73-M73+L73 -> 2398.5602 | O73: 0 | P73: =O73*0.89% -> 0 | Q73: 0 | R73: 0 | S73: =R73*0.89% -> 0 | T73: 0 | U73: ='2018-2019 B STATEMENT '!B51 -> 300 | V73: =U73*0.89% -> 2.67 | W73: 0 | X73: ='2018-2019 B STATEMENT '!B91 -> 400 | Y73: =X73*0.89% -> 3.56 | Z73: 0 | AA73: ='2018-2019 B STATEMENT '!B123 -> 200 | AB73: =AA73*0.89% -> 1.78 | AC73: 0 | AD73: ='2018-2019 B STATEMENT '!B152 -> 200 | AE73: =AD73*0.89% -> 1.78 | AF73: 0 | AG73: ='2018-2019 B STATEMENT '!B179 -> 200 | AH73: =AG73*0.89% -> 1.78 | AI73: 0 | AJ73: ='2018-2019 B STATEMENT '!B194 -> 200 | AK73: =AJ73*0.89% -> 1.78 | AL73: 0 | AM73: ='2018-2019 B STATEMENT '!B223 -> 200 | AN73: =AM73*0.99% -> 1.98 | AO73: 0 | AP73: ='2018-2019 B STATEMENT '!B251 -> 200 | AQ73: =AP73*0.99% -> 1.98 | AR73: 0 | AS73: ='2018-2019 B STATEMENT '!B277 -> 200 | AT73: =AS73*0.99% -> 1.98 | AU73: 0 | AV73: ='2018-2019 B STATEMENT '!B306 -> 200 | AW73: =AV73*0.99% -> 1.98 | AX73: 0 | AY73: =O73+R73+U73+X73+AA73+AD73+AJ73+AG73+AM73+AP73+AS73+AV73 -> 2300
A74: Member 73 | B74: 5/9/2018 | C74: 100 | D74: =200*12 -> 2400 | E74: 0 | F74: ='Catch up Fee'!D74 -> 400 | G74: =C74+D74 -> 2500 | H74: =AY74 -> 2500 | I74: =G74-H74 -> 0 | J74: =I74+M74 -> 0 | K74: =P74+S74+V74+Y74+AB74+AE74+AH74+AK74+AN74+AQ74+AT74+AW74 -> 23.05 | L74: =(H74-K74-C74)*5.5% -> 130.73225 | M74: 0 | N74: =H74-K74-M74+L74 -> 2607.6822 | O74: 0 | P74: =O74*0.89% -> 0 | Q74: 0 | R74: 0 | S74: =R74*0.89% -> 0 | T74: 0 | U74: 0 | V74: =U74*0.89% -> 0 | W74: 0 | X74: ='2018-2019 B STATEMENT '!B114 -> 900 | Y74: =X74*0.89% -> 8.01 | Z74: 0 | AA74: 0 | AB74: =AA74*0.89% -> 0 | AC74: 0 | AD74: ='2018-2019 B STATEMENT '!B158 -> 200 | AE74: =AD74*0.89% -> 1.78 | AF74: 0 | AG74: ='2018-2019 B STATEMENT '!B167+'2018-2019 B STATEMENT '!B168 -> 400 | AH74: =AG74*0.89% -> 3.56 | AI74: 0 | AJ74: ='2018-2019 B STATEMENT '!B195 -> 200 | AK74: =AJ74*0.89% -> 1.78 | AL74: 0 | AM74: ='2018-2019 B STATEMENT '!B219 -> 200 | AN74: =AM74*0.99% -> 1.98 | AO74: 0 | AP74: ='2018-2019 B STATEMENT '!B265 -> 200 | AQ74: =AP74*0.99% -> 1.98 | AR74: 0 | AS74: ='2018-2019 B STATEMENT '!B278 -> 200 | AT74: =AS74*0.99% -> 1.98 | AU74: 0 | AV74: ='2018-2019 B STATEMENT '!B303 -> 200 | AW74: =AV74*0.99% -> 1.98 | AX74: 0 | AY74: =O74+R74+U74+X74+AA74+AD74+AJ74+AG74+AM74+AP74+AS74+AV74 -> 2500
A75: Member 74 | B75: 25/08/2018 | C75: 100 | D75: =200*12 -> 2400 | E75: 0 | F75: ='Catch up Fee'!D75 -> 200 | G75: =C75+D75 -> 2500 | H75: =AY75 -> 1800 | I75: =G75-H75 -> 700 | J75: =I75+M75 -> 700 | K75: =P75+S75+V75+Y75+AB75+AE75+AH75+AK75+AN75+AQ75+AT75+AW75 -> 16.72 | L75: =(H75-K75-C75)*5.5% -> 92.5804 | M75: 0 | N75: =H75-K75-M75+L75 -> 1875.8604 | O75: 0 | P75: =O75*0.89% -> 0 | Q75: 0 | R75: 0 | S75: =R75*0.89% -> 0 | T75: 0 | U75: 0 | V75: =U75*0.89% -> 0 | W75: 0 | X75: ='2018-2019 B STATEMENT '!B82 -> 300 | Y75: =X75*0.89% -> 2.67 | Z75: 0 | AA75: 0 | AB75: =AA75*0.89% -> 0 | AC75: 0 | AD75: 0 | AE75: =AD75*0.89% -> 0 | AF75: 0 | AG75: 0 | AH75: =AG75*0.89% -> 0 | AI75: 0 | AJ75: ='2018-2019 B STATEMENT '!B196 -> 800 | AK75: =AJ75*0.89% -> 7.12 | AL75: 0 | AM75: 0 | AN75: =AM75*0.99% -> 0 | AO75: 0 | AP75: ='2018-2019 B STATEMENT '!B240+'2018-2019 B STATEMENT '!B256 -> 700 | AQ75: =AP75*0.99% -> 6.93 | AR75: 0 | AT75: =AS75*0.99% -> 0 | AU75: 0 | AV75: 0 | AW75: =AV75*0.99% -> 0 | AX75: 0 | AY75: =O75+R75+U75+X75+AA75+AD75+AJ75+AG75+AM75+AP75+AS75+AV75 -> 1800
A76: Member 75 | B76: 18/08/2018 | C76: 100 | D76: =200*12 -> 2400 | E76: 0 | F76: ='Catch up Fee'!D76 -> 200 | G76: =C76+D76 -> 2500 | H76: =AY76 -> 1900 | I76: =G76-H76 -> 600 | J76: =I76+M76 -> 600 | K76: =P76+S76+V76+Y76+AB76+AE76+AH76+AK76+AN76+AQ76+AT76+AW76 -> 17.11 | L76: =(H76-K76-C76)*5.5% -> 98.05895 | M76: 0 | N76: =H76-K76-M76+L76 -> 1980.949 | O76: 0 | P76: =O76*0.89% -> 0 | Q76: 0 | R76: 0 | S76: =R76*0.89% -> 0 | T76: 0 | U76: ='2018-2019 B STATEMENT '!B45 -> 500 | V76: =U76*0.89% -> 4.45 | W76: 0 | X76: ='2018-2019 B STATEMENT '!B86 -> 200 | Y76: =X76*0.89% -> 1.78 | Z76: 0 | AA76: ='2018-2019 B STATEMENT '!B130 -> 200 | AB76: =AA76*0.89% -> 1.78 | AC76: 0 | AD76: ='2018-2019 B STATEMENT '!B145 -> 200 | AE76: =AD76*0.89% -> 1.78 | AF76: 0 | AG76: ='2018-2019 B STATEMENT '!B169+'2018-2019 B STATEMENT '!B170 -> 400 | AH76: =AG76*0.89% -> 3.56 | AI76: 0 | AJ76: ='2018-2019 B STATEMENT '!B185 -> 200 | AK76: =AJ76*0.89% -> 1.78 | AL76: 0 | AM76: ='2018-2019 B STATEMENT '!B224 -> 200 | AN76: =AM76*0.99% -> 1.98 | AO76: 0 | AP76: 0 | AQ76: =AP76*0.99% -> 0 | AR76: 0 | AS76: 0 | AT76: =AS76*0.99% -> 0 | AU76: 0 | AV76: 0 | AW76: =AV76*0.99% -> 0 | AX76: 0 | AY76: =O76+R76+U76+X76+AA76+AD76+AJ76+AG76+AM76+AP76+AS76+AV76 -> 1900
A77: Member 76 | B77: 3/7/2018 | C77: 100 | D77: =200*12 -> 2400 | E77: 0 | F77: ='Catch up Fee'!D77 -> 0 | G77: =C77+D77 -> 2500 | H77: =AY77 -> 300 | I77: =G77-H77-C77 -> 2100 | J77: =I77+M77 -> 2100 | K77: =P77+S77+V77+Y77+AB77+AE77+AH77+AK77+AN77+AQ77+AT77+AW77 -> 2.67 | L77: =(H77-K77-C77)*5.5% -> 10.85315 | M77: 0 | N77: =H77-K77-M77+L77 -> 308.18315 | O77: 0 | P77: =O77*0.89% -> 0 | Q77: 0 | R77: ='2018-2019 B STATEMENT '!B9 -> 300 | S77: =R77*0.89% -> 2.67 | T77: 0 | U77: 0 | V77: =U77*0.89% -> 0 | W77: 0 | X77: 0 | Y77: =X77*0.89% -> 0 | Z77: 0 | AA77: 0 | AB77: =AA77*0.89% -> 0 | AC77: 0 | AD77: 0 | AE77: =AD77*0.89% -> 0 | AF77: 0 | AG77: 0 | AH77: =AG77*0.89% -> 0 | AI77: 0 | AJ77: 0 | AK77: =AJ77*0.89% -> 0 | AL77: 0 | AM77: 0 | AN77: =AM77*0.99% -> 0 | AO77: 0 | AP77: 0 | AQ77: =AP77*0.99% -> 0 | AR77: 0 | AS77: 0 | AT77: =AS77*0.99% -> 0 | AU77: 0 | AV77: 0 | AW77: =AV77*0.99% -> 0 | AX77: 0 | AY77: =O77+R77+U77+X77+AA77+AD77+AJ77+AG77+AM77+AP77+AS77+AV77 -> 300
A78: Member 77 | B78: 29/07/2018 | C78: 100 | D78: =200*12 -> 2400 | E78: 0 | F78: ='Catch up Fee'!D78 -> 0 | G78: =C78+D78 -> 2500 | H78: =AY78 -> 2100 | I78: =G78-H78-C78 -> 300 | J78: =I78+M78 -> 300 | K78: =P78+S78+V78+Y78+AB78+AE78+AH78+AK78+AN78+AQ78+AT78+AW78 -> 19.49 | L78: =(H78-K78-C78)*5.5% -> 108.92805 | M78: 0 | N78: =H78-K78-M78+L78 -> 2189.4381 | O78: 0 | P78: =O78*0.89% -> 0 | Q78: 0 | R78: ='2018-2019 B STATEMENT '!B29 -> 300 | S78: =R78*0.89% -> 2.67 | T78: 0 | U78: ='2018-2019 B STATEMENT '!B52 -> 200 | V78: =U78*0.89% -> 1.78 | W78: 0 | X78: ='2018-2019 B STATEMENT '!B99 -> 200 | Y78: =X78*0.89% -> 1.78 | Z78: 0 | AA78: ='2018-2019 B STATEMENT '!B124 -> 200 | AB78: =AA78*0.89% -> 1.78 | AC78: 0 | AD78: ='2018-2019 B STATEMENT '!B153 -> 200 | AE78: =AD78*0.89% -> 1.78 | AF78: 0 | AG78: 0 | AH78: =AG78*0.89% -> 0 | AI78: 0 | AJ78: ='2018-2019 B STATEMENT '!B197 -> 200 | AK78: =AJ78*0.89% -> 1.78 | AL78: 0 | AM78: ='2018-2019 B STATEMENT '!B225 -> 200 | AN78: =AM78*0.99% -> 1.98 | AO78: 0 | AP78: ='2018-2019 B STATEMENT '!B255 -> 200 | AQ78: =AP78*0.99% -> 1.98 | AR78: 0 | AS78: ='2018-2019 B STATEMENT '!B283 -> 200 | AT78: =AS78*0.99% -> 1.98 | AU78: 0 | AV78: ='2018-2019 B STATEMENT '!B307 -> 200 | AW78: =AV78*0.99% -> 1.98 | AX78: 0 | AY78: =O78+R78+U78+X78+AA78+AD78+AJ78+AG78+AM78+AP78+AS78+AV78 -> 2100
A79: Member 78 | B79: 15/08/2018 | C79: 100 | D79: =200*12 -> 2400 | E79: 0 | F79: ='Catch up Fee'!D79 -> 200 | G79: =C79+D79 -> 2500 | H79: =AY79 -> 800 | I79: =G79-H79 -> 1700 | J79: =I79+M79 -> 1700 | K79: =P79+S79+V79+Y79+AB79+AE79+AH79+AK79+AN79+AQ79+AT79+AW79 -> 7.12 | L79: =(H79-K79-C79)*5.5% -> 38.1084 | M79: 0 | N79: =H79-K79-M79+L79 -> 830.9884 | O79: 0 | P79: =O79*0.89% -> 0 | Q79: 0 | R79: 0 | S79: =R79*0.89% -> 0 | T79: 0 | U79: 0 | V79: =U79*0.89% -> 0 | W79: 0 | X79: ='2018-2019 B STATEMENT '!B75 -> 200 | Y79: =X79*0.89% -> 1.78 | Z79: 0 | AA79: ='2018-2019 B STATEMENT '!B131 -> 200 | AB79: =AA79*0.89% -> 1.78 | AC79: 0 | AD79: 0 | AE79: =AD79*0.89% -> 0 | AF79: 0 | AG79: ='2018-2019 B STATEMENT '!B180 -> 400 | AH79: =AG79*0.89% -> 3.56 | AI79: 0 | AJ79: 0 | AK79: =AJ79*0.89% -> 0 | AL79: 0 | AM79: 0 | AN79: =AM79*0.99% -> 0 | AO79: 0 | AP79: 0 | AQ79: =AP79*0.99% -> 0 | AR79: 0 | AS79: 0 | AT79: =AS79*0.99% -> 0 | AU79: 0 | AV79: 0 | AW79: =AV79*0.99% -> 0 | AX79: 0 | AY79: =O79+R79+U79+X79+AA79+AD79+AJ79+AG79+AM79+AP79+AS79+AV79 -> 800
A80: Member 79 | B80: 12/7/2018 | C80: 100 | D80: =200*12 -> 2400 | E80: 0 | F80: ='Catch up Fee'!D80 -> 0 | G80: =C80+D80 -> 2500 | H80: =AY80 -> 1900 | I80: =G80-H80-C80 -> 500 | J80: =I80+M80 -> 500 | K80: =P80+S80+V80+Y80+AB80+AE80+AH80+AK80+AN80+AQ80+AT80+AW80 -> 17.61 | L80: =(H80-K80-C80)*5.5% -> 98.03145 | M80: 0 | N80: =H80-K80-M80+L80 -> 1980.4215 | O80: 0 | P80: =O80*0.89% -> 0 | Q80: 0 | R80: 0 | S80: =R80*0.89% -> 0 | T80: 0 | U80: ='2018-2019 B STATEMENT '!B35 -> 300 | V80: =U80*0.89% -> 2.67 | W80: 0 | X80: ='2018-2019 B STATEMENT '!B84 -> 200 | Y80: =X80*0.89% -> 1.78 | Z80: 0 | AA80: 0 | AB80: =AA80*0.89% -> 0 | AC80: 0 | AD80: 0 | AE80: =AD80*0.89% -> 0 | AF80: 0 | AG80: ='2018-2019 B STATEMENT '!B161 -> 400 | AH80: =AG80*0.89% -> 3.56 | AI80: 0 | AJ80: ='2018-2019 B STATEMENT '!B187 -> 300 | AK80: =AJ80*0.89% -> 2.67 | AL80: 0 | AM80: 0 | AN80: =AM80*0.99% -> 0 | AO80: 0 | AP80: 0 | AQ80: =AP80*0.99% -> 0 | AR80: 0 | AS80: ='2018-2019 B STATEMENT '!B272 -> 200 | AT80: =AS80*0.99% -> 1.98 | AU80: 0 | AV80: ='2018-2019 B STATEMENT '!B317 -> 500 | AW80: =AV80*0.99% -> 4.95 | AX80: 0 | AY80: =O80+R80+U80+X80+AA80+AD80+AJ80+AG80+AM80+AP80+AS80+AV80 -> 1900
A81: Member 80 | B81: 13/10/2018 | C81: 100 | D81: =200*12 -> 2400 | E81: 0 | F81: ='Catch up Fee'!D81 -> 600 | G81: =C81+D81 -> 2500 | H81: =AY81 -> 2500 | I81: =G81-H81 -> 0 | J81: =I81+M81 -> 0 | K81: =P81+S81+V81+Y81+AB81+AE81+AH81+AK81+AN81+AQ81+AT81+AW81 -> 23.25 | L81: =(H81-K81-C81)*5.5% -> 130.72125 | M81: 0 | N81: =H81-K81-M81+L81 -> 2607.4713 | O81: 0 | P81: =O81*0.89% -> 0 | Q81: 0 | R81: 0 | S81: =R81*0.89% -> 0 | T81: 0 | U81: 0 | V81: =U81*0.89% -> 0 | W81: 0 | X81: 0 | Y81: =X81*0.89% -> 0 | Z81: 0 | AA81: 0 | AB81: =AA81*0.89% -> 0 | AC81: 0 | AD81: ='2018-2019 B STATEMENT '!B138+'2018-2019 B STATEMENT '!B139 -> 1100 | AE81: =AD81*0.89% -> 9.79 | AF81: 0 | AG81: ='2018-2019 B STATEMENT '!B181 -> 200 | AH81: =AG81*0.89% -> 1.78 | AI81: 0 | AJ81: ='2018-2019 B STATEMENT '!B203 -> 200 | AK81: =AJ81*0.89% -> 1.78 | AL81: 0 | AM81: ='2018-2019 B STATEMENT '!B237 -> 200 | AN81: =AM81*0.99% -> 1.98 | AO81: 0 | AP81: ='2018-2019 B STATEMENT '!B266 -> 200 | AQ81: =AP81*0.99% -> 1.98 | AR81: 0 | AS81: ='2018-2019 B STATEMENT '!B287 -> 200 | AT81: =AS81*0.99% -> 1.98 | AU81: 0 | AV81: ='2018-2019 B STATEMENT '!B308+'2018-2019 B STATEMENT '!B309 -> 400 | AW81: =AV81*0.99% -> 3.96 | AX81: 0 | AY81: =O81+R81+U81+X81+AA81+AD81+AJ81+AG81+AM81+AP81+AS81+AV81 -> 2500
A82: Member 81 | B82: 30/07/2019 | C82: 100 | D82: =200*12 -> 2400 | E82: 0 | F82: ='Catch up Fee'!D82 -> 2400 | G82: =C82+D82 -> 2500 | H82: =AY82 -> 2500 | I82: =G82-H82 -> 0 | J82: =I82+M82 -> 0 | K82: =P82+S82+V82+Y82+AB82+AE82+AH82+AK82+AN82+AQ82+AT82+AW82 -> 24.75 | L82: =(H82-K82-C82)*5.5% -> 130.63875 | M82: 0 | N82: =H82-K82-M82+L82 -> 2605.8888 | O82: 0 | P82: =O82*0.89% -> 0 | Q82: 0 | R82: 0 | S82: =R82*0.89% -> 0 | T82: 0 | U82: 0 | V82: =U82*0.89% -> 0 | W82: 0 | X82: 0 | Y82: =X82*0.89% -> 0 | Z82: 0 | AA82: 0 | AB82: =AA82*0.89% -> 0 | AC82: 0 | AD82: 0 | AE82: =AD82*0.89% -> 0 | AF82: 0 | AG82: 0 | AH82: =AG82*0.89% -> 0 | AI82: 0 | AJ82: 0 | AK82: =AJ82*0.89% -> 0 | AL82: 0 | AM82: ='2018-2019 B STATEMENT '!B207+'2018-2019 B STATEMENT '!B238 -> 2500 | AN82: =AM82*0.99% -> 24.75 | AO82: 0 | AP82: 0 | AQ82: =AP82*0.99% -> 0 | AR82: 0 | AS82: 0 | AT82: =AS82*0.99% -> 0 | AU82: 0 | AV82: 0 | AW82: =AV82*0.99% -> 0 | AX82: 0 | AY82: =O82+R82+U82+X82+AA82+AD82+AJ82+AG82+AM82+AP82+AS82+AV82 -> 2500
A83: Member 82 | B83: 21/08/2018 | C83: 100 | D83: =200*12 -> 2400 | E83: 0 | F83: ='Catch up Fee'!D83 -> 200 | G83: =C83+D83 -> 2500 | H83: =AY83 -> 2500 | I83: =G83-H83 -> 0 | J83: =I83+M83 -> 0 | K83: =P83+S83+V83+Y83+AB83+AE83+AH83+AK83+AN83+AQ83+AT83+AW83 -> 23.25 | L83: =(H83-K83-C83)*5.5% -> 130.72125 | M83: 0 | N83: =H83-K83-M83+L83 -> 2607.4713 | O83: 0 | P83: =O83*0.89% -> 0 | Q83: 0 | R83: 0 | S83: =R83*0.89% -> 0 | T83: 0 | U83: 0 | V83: =U83*0.89% -> 0 | W83: 0 | X83: ='2018-2019 B STATEMENT '!B94 -> 700 | Y83: =X83*0.89% -> 6.23 | Z83: 0 | AA83: ='2018-2019 B STATEMENT '!B125 -> 400 | AB83: =AA83*0.89% -> 3.56 | AC83: 0 | AD83: 0 | AE83: =AD83*0.89% -> 0 | AF83: 0 | AG83: 0 | AH83: =AG83*0.89% -> 0 | AI83: 0 | AJ83: ='2018-2019 B STATEMENT '!B198 -> 400 | AK83: =AJ83*0.89% -> 3.56 | AL83: 0 | AM83: ='2018-2019 B STATEMENT '!B226 -> 200 | AN83: =AM83*0.99% -> 1.98 | AO83: 0 | AP83: ='2018-2019 B STATEMENT '!B245+'2018-2019 B STATEMENT '!B257 -> 800 | AQ83: =AP83*0.99% -> 7.92 | AR83: 0 | AS83: 0 | AT83: =AS83*0.99% -> 0 | AU83: 0 | AV83: 0 | AW83: =AV83*0.99% -> 0 | AX83: 0 | AY83: =O83+R83+U83+X83+AA83+AD83+AJ83+AG83+AM83+AP83+AS83+AV83 -> 2500
A84: Member 83 | B84: 17/09/2018 | C84: 100 | D84: =200*12 -> 2400 | E84: 0 | F84: ='Catch up Fee'!D84 -> 400 | G84: =C84+D84 -> 2500 | H84: =AY84 -> 2500 | I84: =G84-H84 -> 0 | J84: =I84+M84 -> 0 | K84: =P84+S84+V84+Y84+AB84+AE84+AH84+AK84+AN84+AQ84+AT84+AW84 -> 22.25 | L84: =(H84-K84-C84)*5.5% -> 130.77625 | M84: 0 | N84: =H84-K84-M84+L84 -> 2608.5262 | O84: 0 | P84: =O84*0.89% -> 0 | Q84: 0 | R84: 0 | S84: =R84*0.89% -> 0 | T84: 0 | U84: ='2018-2019 B STATEMENT '!B53+'2018-2019 B STATEMENT '!B54 -> 2500 | V84: =U84*0.89% -> 22.25 | W84: 0 | X84: 0 | Y84: =X84*0.89% -> 0 | Z84: 0 | AA84: 0 | AB84: =AA84*0.89% -> 0 | AC84: 0 | AD84: 0 | AE84: =AD84*0.89% -> 0 | AF84: 0 | AG84: 0 | AH84: =AG84*0.89% -> 0 | AI84: 0 | AJ84: 0 | AK84: =AJ84*0.89% -> 0 | AL84: 0 | AM84: 0 | AN84: =AM84*0.99% -> 0 | AO84: 0 | AP84: 0 | AQ84: =AP84*0.99% -> 0 | AR84: 0 | AS84: 0 | AT84: =AS84*0.99% -> 0 | AU84: 0 | AV84: 0 | AW84: =AV84*0.99% -> 0 | AX84: 0 | AY84: =O84+R84+U84+X84+AA84+AD84+AJ84+AG84+AM84+AP84+AS84+AV84 -> 2500
A85: Member 84 | B85: 29/06/2018 | C85: 100 | D85: =200*12 -> 2400 | E85: 0 | F85: ='Catch up Fee'!D85 -> 0 | G85: =C85+D85 -> 2500 | H85: =AY85 -> 1350 | I85: =G85-H85-C85 -> 1050 | J85: =I85+M85 -> 1050 | K85: =P85+S85+V85+Y85+AB85+AE85+AH85+AK85+AN85+AQ85+AT85+AW85 -> 12.465 | L85: =(H85-K85-C85)*5.5% -> 68.064425 | M85: 0 | N85: =H85-K85-M85+L85 -> 1405.5994 | O85: ='2018-2019 B STATEMENT '!B6 -> 150 | P85: =O85*0.89% -> 1.335 | Q85: 0 | R85: ='2018-2019 B STATEMENT '!B27 -> 200 | S85: =R85*0.89% -> 1.78 | T85: 0 | U85: ='2018-2019 B STATEMENT '!B61 -> 150 | V85: =U85*0.89% -> 1.335 | W85: 0 | X85: ='2018-2019 B STATEMENT '!B100 -> 150 | Y85: =X85*0.89% -> 1.335 | Z85: 0 | AA85: ='2018-2019 B STATEMENT '!B132 -> 100 | AB85: =AA85*0.89% -> 0.89 | AC85: 0 | AD85: 0 | AE85: =AD85*0.89% -> 0 | AF85: 0 | AG85: ='2018-2019 B STATEMENT '!B173 -> 150 | AH85: =AG85*0.89% -> 1.335 | AI85: 0 | AJ85: 0 | AK85: =AJ85*0.89% -> 0 | AL85: 0 | AM85: ='2018-2019 B STATEMENT '!B235 -> 150 | AN85: =AM85*0.99% -> 1.485 | AO85: 0 | AP85: ='2018-2019 B STATEMENT '!B258 -> 150 | AQ85: =AP85*0.99% -> 1.485 | AR85: 0 | AS85: ='2018-2019 B STATEMENT '!B288 -> 150 | AT85: =AS85*0.99% -> 1.485 | AU85: 0 | AV85: 0 | AW85: =AV85*0.99% -> 0 | AX85: 0 | AY85: =O85+R85+U85+X85+AA85+AD85+AJ85+AG85+AM85+AP85+AS85+AV85 -> 1350
A86: Member 85 | B86: 15/10/2018 | C86: 100 | D86: =200*12 -> 2400 | E86: 0 | F86: ='Catch up Fee'!D86 -> 600 | G86: =C86+D86 -> 2500 | H86: =AY86 -> 1500 | I86: =G86-H86 -> 1000 | J86: =I86+M86 -> 1000 | K86: =P86+S86+V86+Y86+AB86+AE86+AH86+AK86+AN86+AQ86+AT86+AW86 -> 13.95 | L86: =(H86-K86-C86)*5.5% -> 76.23275 | M86: 0 | N86: =H86-K86-M86+L86 -> 1562.2827 | O86: 0 | P86: =O86*0.89% -> 0 | Q86: 0 | R86: 0 | S86: =R86*0.89% -> 0 | T86: 0 | U86: 0 | V86: =U86*0.89% -> 0 | W86: 0 | X86: 0 | Y86: =X86*0.89% -> 0 | Z86: 0 | AA86: ='2018-2019 B STATEMENT '!B126 -> 300 | AB86: =AA86*0.89% -> 2.67 | AC86: 0 | AD86: 0 | AE86: =AD86*0.89% -> 0 | AF86: 0 | AG86: ='2018-2019 B STATEMENT '!B162+'2018-2019 B STATEMENT '!B182 -> 400 | AH86: =AG86*0.89% -> 3.56 | AI86: 0 | AJ86: ='2018-2019 B STATEMENT '!B220 -> 200 | AK86: =AJ86*0.89% -> 1.78 | AL86: 0 | AM86: ='2018-2019 B STATEMENT '!B220 -> 200 | AN86: =AM86*0.99% -> 1.98 | AO86: 0 | AP86: 0 | AQ86: =AP86*0.99% -> 0 | AR86: 0 | AS86: ='2018-2019 B STATEMENT '!B289 -> 400 | AT86: =AS86*0.99% -> 3.96 | AU86: 0 | AV86: 0 | AW86: =AV86*0.99% -> 0 | AX86: 0 | AY86: =O86+R86+U86+X86+AA86+AD86+AJ86+AG86+AM86+AP86+AS86+AV86 -> 1500
A87: Member 86 | B87: 04/12/2019 | C87: 0 | D87: =200*12 -> 2400 | E87: 0 | F87: ='Catch up Fee'!D87 -> 3400 | G87: =C87+D87 -> 2400 | H87: =AY87 -> 0 | I87: =G87-H87 -> 2400 | J87: =I87+M87 -> 2400 | K87: =P87+S87+V87+Y87+AB87+AE87+AH87+AK87+AN87+AQ87+AT87+AW87 -> 0 | L87: =(H87-K87-C87)*5.5% -> 0 | M87: 0 | N87: =H87-K87-M87+L87 -> 0 | O87: 0 | P87: =O87*0.89% -> 0 | Q87: 0 | R87: 0 | S87: =R87*0.89% -> 0 | T87: 0 | U87: 0 | V87: =U87*0.89% -> 0 | W87: 0 | X87: 0 | Y87: =X87*0.89% -> 0 | Z87: 0 | AA87: 0 | AB87: =AA87*0.89% -> 0 | AC87: 0 | AD87: 0 | AE87: =AD87*0.89% -> 0 | AF87: 0 | AG87: 0 | AH87: =AG87*0.89% -> 0 | AI87: 0 | AJ87: 0 | AK87: =AJ87*0.89% -> 0 | AL87: 0 | AM87: 0 | AN87: =AM87*0.99% -> 0 | AO87: 0 | AP87: 0 | AQ87: =AP87*0.99% -> 0 | AR87: 0 | AS87: 0 | AT87: =AS87*0.99% -> 0 | AU87: 0 | AV87: 0 | AW87: =AV87*0.99% -> 0 | AX87: 0 | AY87: =O87+R87+U87+X87+AA87+AD87+AJ87+AG87+AM87+AP87+AS87+AV87 -> 0
A88: Member 87 | B88: 24/07/2018 | C88: 100 | D88: =200*12 -> 2400 | E88: 0 | F88: ='Catch up Fee'!D88 -> 0 | G88: =C88+D88 -> 2500 | H88: =AY88 -> 1100 | I88: =G88-H88-C88 -> 1300 | J88: =I88+M88 -> 1300 | K88: =P88+S88+V88+Y88+AB88+AE88+AH88+AK88+AN88+AQ88+AT88+AW88 -> 10.19 | L88: =(H88-K88-C88)*5.5% -> 54.43955 | M88: 0 | N88: =H88-K88-M88+L88 -> 1144.2495 | O88: 0 | P88: =O88*0.89% -> 0 | Q88: 0 | R88: ='2018-2019 B STATEMENT '!B33 -> 300 | S88: =R88*0.89% -> 2.67 | T88: 0 | U88: ='2018-2019 B STATEMENT '!B67 -> 200 | V88: =U88*0.89% -> 1.78 | W88: 0 | X88: 0 | Y88: =X88*0.89% -> 0 | Z88: 0 | AA88: ='2018-2019 B STATEMENT '!B127 -> 200 | AB88: =AA88*0.89% -> 1.78 | AC88: 0 | AD88: 0 | AE88: =AD88*0.89% -> 0 | AF88: 0 | AG88: 0 | AH88: =AG88*0.89% -> 0 | AI88: 0 | AJ88: 0 | AK88: =AJ88*0.89% -> 0 | AL88: 0 | AM88: ='2018-2019 B STATEMENT '!B212 -> 400 | AN88: =AM88*0.99% -> 3.96 | AO88: 0 | AP88: 0 | AQ88: =AP88*0.99% -> 0 | AR88: 0 | AS88: 0 | AT88: =AS88*0.99% -> 0 | AU88: 0 | AV88: 0 | AW88: =AV88*0.99% -> 0 | AX88: 0 | AY88: =O88+R88+U88+X88+AA88+AD88+AJ88+AG88+AM88+AP88+AS88+AV88 -> 1100
A89: Member 88 | B89: 11/8/2018 | C89: 100 | D89: =200*12 -> 2400 | E89: 0 | F89: ='Catch up Fee'!D89 -> 200 | G89: =C89+D89 -> 2500 | H89: =AY89 -> 700 | I89: =G89-H89 -> 1800 | J89: =I89+M89 -> 1800 | K89: =P89+S89+V89+Y89+AB89+AE89+AH89+AK89+AN89+AQ89+AT89+AW89 -> 6.23 | L89: =(H89-K89-C89)*5.5% -> 32.65735 | M89: 0 | N89: =H89-K89-M89+L89 -> 726.42735 | O89: 0 | P89: =O89*0.89% -> 0 | Q89: 0 | R89: 0 | S89: =R89*0.89% -> 0 | T89: 0 | U89: ='2018-2019 B STATEMENT '!B69 -> 500 | V89: =U89*0.89% -> 4.45 | W89: 0 | X89: 0 | Y89: =X89*0.89% -> 0 | Z89: 0 | AA89: ='2018-2019 B STATEMENT '!B105 -> 200 | AB89: =AA89*0.89% -> 1.78 | AC89: 0 | AD89: 0 | AE89: =AD89*0.89% -> 0 | AF89: 0 | AG89: 0 | AH89: =AG89*0.89% -> 0 | AI89: 0 | AJ89: 0 | AK89: =AJ89*0.89% -> 0 | AL89: 0 | AM89: 0 | AN89: =AM89*0.99% -> 0 | AO89: 0 | AP89: 0 | AQ89: =AP89*0.99% -> 0 | AR89: 0 | AS89: 0 | AT89: =AS89*0.99% -> 0 | AU89: 0 | AV89: 0 | AW89: =AV89*0.99% -> 0 | AX89: 0 | AY89: =O89+R89+U89+X89+AA89+AD89+AJ89+AG89+AM89+AP89+AS89+AV89 -> 700
A90: Member 89 | B90: 3/7/2018 | C90: 100 | D90: =200*12 -> 2400 | E90: 0 | F90: ='Catch up Fee'!D90 -> 0 | G90: =C90+D90 -> 2500 | H90: =AY90 -> 2700 | I90: =G90-H90-C90 -> -300 | J90: =I90+M90 -> -300 | K90: =P90+S90+V90+Y90+AB90+AE90+AH90+AK90+AN90+AQ90+AT90+AW90 -> 24.43 | L90: =(H90-K90-C90)*5.5% -> 141.65635 | M90: 0 | N90: =H90-K90-M90+L90 -> 2817.2264 | O90: 0 | P90: =O90*0.89% -> 0 | Q90: 0 | R90: 300 | S90: =R90*0.89% -> 2.67 | T90: 0 | U90: 0 | V90: =U90*0.89% -> 0 | W90: 0 | X90: ='2018-2019 B STATEMENT '!B95 -> 1000 | Y90: =X90*0.89% -> 8.9 | Z90: 0 | AA90: 0 | AB90: =AA90*0.89% -> 0 | AC90: 0 | AD90: 0 | AE90: =AD90*0.89% -> 0 | AF90: 0 | AG90: 0 | AH90: =AG90*0.89% -> 0 | AI90: 0 | AJ90: ='2018-2019 B STATEMENT '!B202 -> 1000 | AK90: =AJ90*0.89% -> 8.9 | AL90: 0 | AM90: 0 | AN90: =AM90*0.99% -> 0 | AO90: 0 | AP90: ='2018-2019 B STATEMENT '!B267 -> 400 | AQ90: =AP90*0.99% -> 3.96 | AR90: 0 | AS90: 0 | AT90: =AS90*0.99% -> 0 | AU90: 0 | AV90: 0 | AW90: =AV90*0.99% -> 0 | AX90: 0 | AY90: =O90+R90+U90+X90+AA90+AD90+AJ90+AG90+AM90+AP90+AS90+AV90 -> 2700
C91: =SUM(C2:C90) -> 7700 | D91: =SUM(D2:D90) -> 213600 | E91: =SUM(E2:E90) -> 0 | F91: =SUM(F2:F90) -> 57600 | G91: =SUM(G2:G90) -> 221300 | H91: =SUM(H2:H90) -> 110110 | I91: =SUM(I2:I90) -> 107290 | J91: =SUM(J2:J90) -> 107290 | ... AY91: =SUM(AY2:AY90) -> 110110
H93: Contributed less than R1 199,99 | O93: =AVERAGE(O91,R91,U91,X91,AA91,AD91,AG91,AJ91,AM91,AP91,AS91,AV91) -> 9175.8333
H94: Contributed between R2400 and more
H95: Contributed betweem R1 200 and R2 399,99

Sheet 2019-2020 New
A1: Member | B1: Date Join | C1: Membership Fee | D1: Expected Contribution | E1: Balance Brought Forward (*Incl. Catch up Fee) | F1: Catch-Up Fee | G1: Estimated 12 Months Contribution (Jul 2018-June 2019) | H1: Total Contribution for 12 Months | I1: Total outstanding contribution for 12 Months | J1: Closing Balance | K1: Total Bank Charges @ 1,1% | L1: Total Interest Earned @ 5,5% | M1: Penalty July 2019- June 2020 | N1: Capped Penalties Current Financial Year | O1: Share Value | P1: 43647 | Q1: Bank Charges @ 0,99% | R1: Amount Due | S1: Penalty | T1: 43678 | U1: Bank Charges @ 0,99% | V1: Amount Due | W1: Penalty | X1: 43709 | Y1: Bank Charges @ 0,99% | Z1: Amount Due | AA1: Penalty | AB1: 43739 | AC1: Bank Charges @ 0,99% | AD1: Amount Due | AE1: Penalty | AF1: 43770 | AG1: Bank Charges @ 0,99% | AH1: Amount Due | AI1: Penalty | AJ1: 43800 | AK1: Bank Charges @ 0,99% | AL1: Amount Due | AM1: Penalty | AN1: 43831 | AO1: Bank Charges @ 0,99% | AP1: Amount Due | AQ1: Penalty | AR1: 43862 | AS1: Bank Charges @ 0,99% | AT1: Amount Due | AU1: Penalty | AV1: 43891 | AW1: Bank Charges @ 0,99% | AX1: Amount Due | AY1: Penalty | AZ1: 43922 | BA1: Bank Charges @ 0,99% | BB1: Amount Due | BC1: Penalty | BD1: 43952 | BE1: Bank Charges @ 0,99% | BF1: Amount Due | BG1: Penalty | BH1: 43983 | BI1: Bank Charges @ 0,99% | BJ1: Amount Due | BK1: Penalty | BL1: Total Contribution for Current Year
A2: Member 1 | B2: 14/08/2018 | C2: 0 | D2: =200*12 -> 2400 | E2: =' 2018-2019'!J2 -> 800 | F2: =' 2018-2019'!F2 -> 200 | G2: =C2+D2 -> 2400 | H2: =BL2 -> 0 | I2: =G2-H2-C2 -> 2400 | J2: =I2+M2+E2 -> 4271.7906 | K2: =Q2+U2+Y2+AC2+AG2+AK2+AO2+AS2+AW2+BA2+BE2+BI2 -> 19.8 | L2: =(H2-K2-C2)*5.5% -> -1.089 | M2: =S2+W2+AA2+AE2+AI2+AM2+AQ2+AU2+AY2+BC2+BG2+BK2 -> 1071.7906 | N2: =M2 -> 1071.7906 | O2: =H2-K2-M2+L2 -> -1092.6796 | P2: 600 | Q2: =P2*0.99% -> 5.94 | R2: =E2+'Catch up Fee'!E2 -> 1000 | S2: =(R2-P2)*0.055 -> 22 | T2: 0 | U2: =T2*0.99% -> 0 | V2: =R2-T2+'Catch up Fee'!E2+S2 -> 1222 | W2: =(V2-T2)*0.055 -> 67.21 | X2: 0 | Y2: =X2*0.99% -> 0 | Z2: =V2-X2+'Catch up Fee'!E2+W2 -> 1489.21 | AA2: =(Z2-X2)*0.055 -> 81.90655 | AB2: 400 | AC2: =AB2*0.99% -> 3.96 | AD2: =Z2-AB2+'Catch up Fee'!E2+AA2 -> 1371.1165 | AE2: =(AD2-AB2)*0.055 -> 53.41141 | AF2: 200 | AG2: =AF2*0.99% -> 1.98 | AH2: =AD2-AF2+'Catch up Fee'!E2+AE2 -> 1424.528 | AI2: =(AH2-AF2)*0.055 -> 67.349038 | AJ2: 0 | AK2: =AJ2*0.99% -> 0 | AL2: =AH2-AJ2+'Catch up Fee'!E2+AI2 -> 1691.877 | AM2: =(AL2-AJ2)*0.055 -> 93.053235 | AN2: 0 | AO2: =AN2*0.99% -> 0 | AP2: =AL2-AN2+'Catch up Fee'!E2+AM2 -> 1984.9302 | AQ2: =(AP2-AN2)*0.055 -> 109.17116 | AR2: 0 | AS2: =AR2*0.99% -> 0 | AT2: =AP2-AR2+'Catch up Fee'!E2+AQ2 -> 2294.1014 | AU2: =(AT2-AR2)*0.055 -> 126.17558 | AV2: 800 | AW2: =AV2*0.99% -> 7.92 | AX2: =AT2-AV2+'Catch up Fee'!E2+AU2 -> 1820.277 | AY2: =(AX2-AV2)*0.055 -> 56.115233 | AZ2: 0 | BA2: =AZ2*0.99% -> 0 | BB2: =AX2-AZ2+'Catch up Fee'!E2+AY2 -> 2076.3922 | BC2: =(BB2-AZ2)*0.055 -> 114.20157 | BD2: 0 | BE2: =BD2*0.99% -> 0 | BF2: =BB2-BD2+'Catch up Fee'!E2+BC2 -> 2390.5938 | BG2: =(BF2-BD2)*0.055 -> 131.48266 | BH2: 0 | BI2: =BH2*0.99% -> 0 | BJ2: =BF2-BH2+'Catch up Fee'!E2+BG2 -> 2722.0764 | BK2: =(BJ2-BH2)*0.055 -> 149.7142
A3: Member 2 | B3: 16/02/2019 | C3: 0 | D3: =200*12 -> 2400 | E3: =' 2018-2019'!J3 -> 0 | F3: =' 2018-2019'!F3 -> 1600 | G3: =C3+D3 -> 2400 | H3: =BL3 -> 2000 | I3: =G3-H3-C3 -> 400 | J3: =I3+M3+E3 -> 1115.2596 | K3: =Q3+U3+Y3+AC3+AG3+AK3+AO3+AS3+AW3+BA3+BE3+BI3 -> 19.8 | L3: =(H3-K3-C3)*5.5% -> 108.911 | M3: =S3+W3+AA3+AE3+AI3+AM3+AQ3+AU3+AY3+BC3+BG3+BK3 -> 715.25963 | N3: =M3 -> 715.25963 | O3: =H3-K3-M3+L3 -> 1373.8514 | P3: 0 | Q3: =P3*0.99% -> 0 | R3: =E3+'Catch up Fee'!E3 -> 200 | S3: =(R3-P3)*0.055 -> 11 | T3: 0 | U3: =T3*0.99% -> 0 | V3: =R3-T3+'Catch up Fee'!E3+S3 -> 411 | W3: =(V3-T3)*0.055 -> 22.605 | X3: 0 | Y3: =X3*0.99% -> 0 | Z3: =V3-X3+'Catch up Fee'!E3+W3 -> 633.605 | AA3: =(Z3-X3)*0.055 -> 34.848275 | AB3: 0 | AC3: =AB3*0.99% -> 0 | AD3: =Z3-AB3+'Catch up Fee'!E3+AA3 -> 868.45328 | AE3: =(AD3-AB3)*0.055 -> 47.76493 | AF3: 0 | AG3: =AF3*0.99% -> 0 | AH3: =AD3-AF3+'Catch up Fee'!E3+AE3 -> 1116.2182 | AI3: =(AH3-AF3)*0.055 -> 61.392001 | AJ3: 0 | AK3: =AJ3*0.99% -> 0 | AL3: =AH3-AJ3+'Catch up Fee'!E3+AI3 -> 1377.6102 | AM3: =(AL3-AJ3)*0.055 -> 75.768561 | AN3: 0 | AO3: =AN3*0.99% -> 0 | AP3: =AL3-AN3+'Catch up Fee'!E3+AM3 -> 1653.3788 | AQ3: =(AP3-AN3)*0.055 -> 90.935832 | AR3: 0 | AS3: =AR3*0.99% -> 0 | AT3: =AP3-AR3+'Catch up Fee'!E3+AQ3 -> 1944.3146 | AU3: =(AT3-AR3)*0.055 -> 106.9373 | AV3: 0 | AW3: =AV3*0.99% -> 0 | AX3: =AT3-AV3+'Catch up Fee'!E3+AU3 -> 2251.2519 | AY3: =(AX3-AV3)*0.055 -> 123.81885 | BA3: =AZ3*0.99% -> 0 | BB3: =AX3-AZ3+'Catch up Fee'!E3+AY3 -> 2575.0708 | BC3: =(BB3-AZ3)*0.055 -> 141.62889 | BD3: 2000 | BE3: =BD3*0.99% -> 19.8 | BF3: =BB3-BD3+'Catch up Fee'!E3+BC3 -> 916.69965 | BG3: =(BF3-BD3)*0.055 -> -59.581519 | BH3: 0 | BI3: =BH3*0.99% -> 0 | BJ3: =BF3-BH3+'Catch up Fee'!E3+BG3 -> 1057.1181 | BK3: =(BJ3-BH3)*0.055 -> 58.141497 | BL3: =P3+T3+X3+AB3+AF3+AJ3+AR3+AN3+AV3+AZ3+BD3+BH3 -> 2000
A4: Member 3 | B4: 30/07/2018 | C4: 0 | D4: =200*12 -> 2400 | E4: =' 2018-2019'!J4 -> 900 | F4: =' 2018-2019'!F4 -> 0 | G4: =C4+D4 -> 2400 | H4: =BL4 -> 0 | I4: =G4-H4-C4 -> 2400 | J4: =I4+M4+E4+F4 -> 5168.4464 | K4: =Q4+U4+Y4+AC4+AG4+AK4+AO4+AS4+AW4+BA4+BE4+BI4 -> 0 | L4: =(H4-K4-C4)*5.5% -> 0 | M4: =S4+W4+AA4+AE4+AI4+AM4+AQ4+AU4+AY4+BC4+BG4+BK4 -> 1868.4464 | N4: =M4 -> 1868.4464 | O4: =H4-K4-M4+L4 -> -1868.4464 | P4: 0 | Q4: =P4*0.99% -> 0 | R4: =E4+'Catch up Fee'!E4 -> 1100 | S4: =(R4-P4)*0.055 -> 60.5 | T4: 0 | U4: =T4*0.99% -> 0 | V4: =R4-T4+'Catch up Fee'!E4+S4 -> 1360.5 | W4: =(V4-T4)*0.055 -> 74.8275 | X4: 0 | Y4: =X4*0.99% -> 0 | Z4: =V4-X4+'Catch up Fee'!E4+W4 -> 1635.3275 | AA4: =(Z4-X4)*0.055 -> 89.943013 | AB4: 0 | AC4: =AB4*0.99% -> 0 | AD4: =Z4-AB4+'Catch up Fee'!E4+AA4 -> 1925.2705 | AE4: =(AD4-AB4)*0.055 -> 105.88988 | AF4: 0 | AG4: =AF4*0.99% -> 0 | AH4: =AD4-AF4+'Catch up Fee'!E4+AE4 -> 2231.1604 | AI4: =(AH4-AF4)*0.055 -> 122.71382 | AJ4: 0 | AK4: =AJ4*0.99% -> 0 | AL4: =AH4-AJ4+'Catch up Fee'!E4+AI4 -> 2553.8742 | AM4: =(AL4-AJ4)*0.055 -> 140.46308 | AN4: 0 | AO4: =AN4*0.99% -> 0 | AP4: =AL4-AN4+'Catch up Fee'!E4+AM4 -> 2894.3373 | AQ4: =(AP4-AN4)*0.055 -> 159.18855 | AR4: 0 | AS4: =AR4*0.99% -> 0 | AT4: =AP4-AR4+'Catch up Fee'!E4+AQ4 -> 3253.5258 | AU4: =(AT4-AR4)*0.055 -> 178.94392 | AV4: 0 | AW4: =AV4*0.99% -> 0 | AX4: =AT4-AV4+'Catch up Fee'!E4+AU4 -> 3632.4698 | AY4: =(AX4-AV4)*0.055 -> 199.78584 | AZ4: 0 | BA4: =AZ4*0.99% -> 0 | BB4: =AX4-AZ4+'Catch up Fee'!E4+AY4 -> 4032.2556 | BC4: =(BB4-AZ4)*0.055 -> 221.77406 | BD4: 0 | BE4: =BD4*0.99% -> 0 | BF4: =BB4-BD4+'Catch up Fee'!E4+BC4 -> 4454.0297 | BG4: =(BF4-BD4)*0.055 -> 244.97163 | BH4: 0 | BI4: =BH4*0.99% -> 0 | BJ4: =BF4-BH4+'Catch up Fee'!E4+BG4 -> 4899.0013 | BK4: =(BJ4-BH4)*0.055 -> 269.44507 | BL4: =P4+T4+X4+AB4+AF4+AJ4+AR4+AN4+AV4+AZ4+BD4+BH4 -> 0
A5: Member 4 | B5: 11/7/2018 | C5: 0 | D5: =200*12 -> 2400 | E5: =' 2018-2019'!J5 -> 2200 | F5: =' 2018-2019'!F5 -> 0 | G5: =C5+D5 -> 2400 | H5: =BL5 -> 0 | I5: =G5-H5-C5 -> 2400 | J5: =I5+M5+E5+F5 -> 7640.0161 | K5: =Q5+U5+Y5+AC5+AG5+AK5+AO5+AS5+AW5+BA5+BE5+BI5 -> 0 | L5: =(H5-K5-C5)*5.5% -> 0 | M5: =S5+W5+AA5+AE5+AI5+AM5+AQ5+AU5+AY5+BC5+BG5+BK5 -> 3040.0161 | N5: =M5 -> 3040.0161 | O5: =H5-K5-M5+L5 -> -3040.0161 | P5: 0 | Q5: =P5*0.99% -> 0 | R5: =E5+'Catch up Fee'!E5 -> 2400 | S5: =(R5-P5)*0.055 -> 132 | T5: 0 | U5: =T5*0.99% -> 0 | V5: =R5-T5+'Catch up Fee'!E5+S5 -> 2732 | W5: =(V5-T5)*0.055 -> 150.26 | X5: 0 | Y5: =X5*0.99% -> 0 | Z5: =V5-X5+'Catch up Fee'!E5+W5 -> 3082.26 | AA5: =(Z5-X5)*0.055 -> 169.5243 | AB5: 0 | AC5: =AB5*0.99% -> 0 | AD5: =Z5-AB5+'Catch up Fee'!E5+AA5 -> 3451.7843 | AE5: =(AD5-AB5)*0.055 -> 189.84814 | AF5: 0 | AG5: =AF5*0.99% -> 0 | AH5: =AD5-AF5+'Catch up Fee'!E5+AE5 -> 3841.6324 | AI5: =(AH5-AF5)*0.055 -> 211.28978 | AJ5: 0 | AK5: =AJ5*0.99% -> 0 | AL5: =AH5-AJ5+'Catch up Fee'!E5+AI5 -> 4252.9222 | AM5: =(AL5-AJ5)*0.055 -> 233.91072 | AN5: 0 | AO5: =AN5*0.99% -> 0 | AP5: =AL5-AN5+'Catch up Fee'!E5+AM5 -> 4686.8329 | AQ5: =(AP5-AN5)*0.055 -> 257.77581 | AR5: 0 | AS5: =AR5*0.99% -> 0 | AT5: =AP5-AR5+'Catch up Fee'!E5+AQ5 -> 5144.6088 | AU5: =(AT5-AR5)*0.055 -> 282.95348 | AV5: 0 | AW5: =AV5*0.99% -> 0 | AX5: =AT5-AV5+'Catch up Fee'!E5+AU5 -> 5627.5622 | AY5: =(AX5-AV5)*0.055 -> 309.51592 | AZ5: 0 | BA5: =AZ5*0.99% -> 0 | BB5: =AX5-AZ5+'Catch up Fee'!E5+AY5 -> 6137.0782 | BC5: =(BB5-AZ5)*0.055 -> 337.5393 | BD5: 0 | BE5: =BD5*0.99% -> 0 | BF5: =BB5-BD5+'Catch up Fee'!E5+BC5 -> 6674.6175 | BG5: =(BF5-BD5)*0.055 -> 367.10396 | BH5: 0 | BI5: =BH5*0.99% -> 0 | BJ5: =BF5-BH5+'Catch up Fee'!E5+BG5 -> 7241.7214 | BK5: =(BJ5-BH5)*0.055 -> 398.29468 | BL5: =P5+T5+X5+AB5+AF5+AJ5+AR5+AN5+AV5+AZ5+BD5+BH5 -> 0
A6: Member 5 | B6: 4/7/2018 | C6: 0 | D6: =200*12 -> 2400 | E6: =' 2018-2019'!J6 -> -100 | F6: =' 2018-2019'!F6 -> 0 | G6: =C6+D6 -> 2400 | H6: =BL6 -> 1850 | I6: =G6-H6-C6 -> 550 | J6: =I6+M6+E6+F6 -> 459.8665 | K6: =Q6+U6+Y6+AC6+AG6+AK6+AO6+AS6+AW6+BA6+BE6+BI6 -> 18.315 | L6: =(H6-K6-C6)*5.5% -> 100.74267 | M6: =S6+W6+AA6+AE6+AI6+AM6+AQ6+AU6+AY6+BC6+BG6+BK6 -> 9.8665031 | N6: =M6 -> 9.8665031 | O6: =H6-K6-M6+L6 -> 1922.5612 | P6: 0 | Q6: =P6*0.99% -> 0 | R6: =E6+'Catch up Fee'!E6 -> 100 | S6: =(R6-P6)*0.055 -> 5.5 | T6: 0 | U6: =T6*0.99% -> 0 | V6: =R6-T6+'Catch up Fee'!E6+S6 -> 305.5 | W6: =(V6-T6)*0.055 -> 16.8025 | X6: ='2018-2019 B STATEMENT '!B382 -> 400 | Y6: =X6*0.99% -> 3.96 | Z6: =V6-X6+'Catch up Fee'!E6+W6 -> 122.3025 | AA6: =(Z6-X6)*0.055 -> -15.273362 | AB6: ='2018-2019 B STATEMENT '!B416 -> 200 | AC6: =AB6*0.99% -> 1.98 | AD6: =Z6-AB6+'Catch up Fee'!E6+AA6 -> 107.02914 | AE6: =(AD6-AB6)*0.055 -> -5.1133974 | AF6: ='2018-2019 B STATEMENT '!B429 -> 200 | AG6: =AF6*0.99% -> 1.98 | AH6: =AD6-AF6+'Catch up Fee'!E6+AE6 -> 101.91574 | AI6: =(AH6-AF6)*0.055 -> -5.3946343 | AJ6: 0 | AK6: =AJ6*0.99% -> 0 | AL6: =AH6-AJ6+'Catch up Fee'!E6+AI6 -> 296.52111 | AM6: =(AL6-AJ6)*0.055 -> 16.308661 | AN6: ='2018-2019 B STATEMENT '!B483 -> 400 | AO6: =AN6*0.99% -> 3.96 | AP6: =AL6-AN6+'Catch up Fee'!E6+AM6 -> 112.82977 | AQ6: =(AP6-AN6)*0.055 -> -15.794363 | AR6: ='2018-2019 B STATEMENT '!B501 -> 200 | AS6: =AR6*0.99% -> 1.98 | AT6: =AP6-AR6+'Catch up Fee'!E6+AQ6 -> 97.035404 | AU6: =(AT6-AR6)*0.055 -> -5.6630528 | AV6: ='2018-2019 B STATEMENT '!B518 -> 200 | AW6: =AV6*0.99% -> 1.98 | AX6: =AT6-AV6+'Catch up Fee'!E6+AU6 -> 91.372351 | AY6: =(AX6-AV6)*0.055 -> -5.9745207 | AZ6: ='2018-2019 B STATEMENT '!B536 -> 250 | BA6: =AZ6*0.99% -> 2.475 | BB6: =AX6-AZ6+'Catch up Fee'!E6+AY6 -> 35.39783 | BC6: =(BB6-AZ6)*0.055 -> -11.803119 | BD6: 0 | BE6: =BD6*0.99% -> 0 | BF6: =BB6-BD6+'Catch up Fee'!E6+BC6 -> 223.59471 | BG6: =(BF6-BD6)*0.055 -> 12.297709 | BH6: 0 | BI6: =BH6*0.99% -> 0 | BJ6: =BF6-BH6+'Catch up Fee'!E6+BG6 -> 435.89242 | BK6: =(BJ6-BH6)*0.055 -> 23.974083 | BL6: =P6+T6+X6+AB6+AF6+AJ6+AR6+AN6+AV6+AZ6+BD6+BH6 -> 1850
A7: Member 6 | B7: 14/10/2018 | C7: 0 | D7: =200*12 -> 2400 | E7: =' 2018-2019'!J7 -> 1400 | F7: =' 2018-2019'!F7 -> 600 | G7: =C7+D7 -> 2400 | H7: =BL7 -> 0 | I7: =G7-H7-C7 -> 2400 | J7: =I7+M7+E7 -> 6119.0501 | K7: =Q7+U7+Y7+AC7+AG7+AK7+AO7+AS7+AW7+BA7+BE7+BI7 -> 0 | L7: =(H7-K7-C7)*5.5% -> 0 | M7: =S7+W7+AA7+AE7+AI7+AM7+AQ7+AU7+AY7+BC7+BG7+BK7 -> 2319.0501 | N7: =M7 -> 2319.0501 | O7: =H7-K7-M7+L7 -> -2319.0501 | P7: 0 | Q7: =P7*0.99% -> 0 | R7: =E7+'Catch up Fee'!E7 -> 1600 | S7: =(R7-P7)*0.055 -> 88 | T7: 0 | U7: =T7*0.99% -> 0 | V7: =R7-T7+'Catch up Fee'!E7+S7 -> 1888 | W7: =(V7-T7)*0.055 -> 103.84 | X7: 0 | Y7: =X7*0.99% -> 0 | Z7: =V7-X7+'Catch up Fee'!E7+W7 -> 2191.84 | AA7: =(Z7-X7)*0.055 -> 120.5512 | AB7: 0 | AC7: =AB7*0.99% -> 0 | AD7: =Z7-AB7+'Catch up Fee'!E7+AA7 -> 2512.3912 | AE7: =(AD7-AB7)*0.055 -> 138.18152 | AF7: 0 | AG7: =AF7*0.99% -> 0 | AH7: =AD7-AF7+'Catch up Fee'!E7+AE7 -> 2850.5727 | AI7: =(AH7-AF7)*0.055 -> 156.7815 | AJ7: 0 | AK7: =AJ7*0.99% -> 0 | AL7: =AH7-AJ7+'Catch up Fee'!E7+AI7 -> 3207.3542 | AM7: =(AL7-AJ7)*0.055 -> 176.40448 | AN7: 0 | AO7: =AN7*0.99% -> 0 | AP7: =AL7-AN7+'Catch up Fee'!E7+AM7 -> 3583.7587 | AQ7: =(AP7-AN7)*0.055 -> 197.10673 | AR7: 0 | AS7: =AR7*0.99% -> 0 | AT7: =AP7-AR7+'Catch up Fee'!E7+AQ7 -> 3980.8654 | AU7: =(AT7-AR7)*0.055 -> 218.9476 | AV7: 0 | AW7: =AV7*0.99% -> 0 | AX7: =AT7-AV7+'Catch up Fee'!E7+AU7 -> 4399.813 | AY7: =(AX7-AV7)*0.055 -> 241.98972 | AZ7: 0 | BA7: =AZ7*0.99% -> 0 | BB7: =AX7-AZ7+'Catch up Fee'!E7+AY7 -> 4841.8027 | BC7: =(BB7-AZ7)*0.055 -> 266.29915 | BD7: 0 | BE7: =BD7*0.99% -> 0 | BF7: =BB7-BD7+'Catch up Fee'!E7+BC7 -> 5308.1019 | BG7: =(BF7-BD7)*0.055 -> 291.9456 | BH7: 0 | BI7: =BH7*0.99% -> 0 | BJ7: =BF7-BH7+'Catch up Fee'!E7+BG7 -> 5800.0475 | BK7: =(BJ7-BH7)*0.055 -> 319.00261 | BL7: =P7+T7+X7+AB7+AF7+AJ7+AR7+AN7+AV7+AZ7+BD7+BH7 -> 0
A8: Member 7 | B8: 27/10/2021 | C8: 0 | D8: =200*12 -> 2400 | E8: =' 2018-2019'!J90 -> -300 | F8: =' 2018-2019'!F8 -> 7800 | G8: =C8+D8 -> 2400 | H8: =BL8 -> 0 | I8: =G8-H8-C8 -> 2400 | J8: =I8+M8+E8 -> 2886.9974 | K8: =Q8+U8+Y8+AC8+AG8+AK8+AO8+AS8+AW8+BA8+BE8+BI8 -> 0 | L8: =(H8-K8-C8)*5.5% -> 0 | M8: =S8+W8+AA8+AE8+AI8+AM8+AQ8+AU8+AY8+BC8+BG8+BK8 -> 786.99738 | N8: =M8 -> 786.99738 | O8: =H8-K8-M8+L8 -> -786.99738 | P8: 0 | Q8: =P8*0.99% -> 0 | R8: =E8+'Catch up Fee'!E8 -> -100 | S8: =(R8-P8)*0.055 -> -5.5 | T8: 0 | U8: =T8*0.99% -> 0 | V8: =R8-T8+'Catch up Fee'!E8+S8 -> 94.5 | W8: =(V8-T8)*0.055 -> 5.1975 | X8: 0 | Y8: =X8*0.99% -> 0 | Z8: =V8-X8+'Catch up Fee'!E8+W8 -> 299.6975 | AA8: =(Z8-X8)*0.055 -> 16.483362 | AB8: 0 | AC8: =AB8*0.99% -> 0 | AD8: =Z8-AB8+'Catch up Fee'!E8+AA8 -> 516.18086 | AE8: =(AD8-AB8)*0.055 -> 28.389947 | AF8: 0 | AG8: =AF8*0.99% -> 0 | AH8: =AD8-AF8+'Catch up Fee'!E8+AE8 -> 744.57081 | AI8: =(AH8-AF8)*0.055 -> 40.951395 | AJ8: 0 | AK8: =AJ8*0.99% -> 0 | AL8: =AH8-AJ8+'Catch up Fee'!E8+AI8 -> 985.5222 | AM8: =(AL8-AJ8)*0.055 -> 54.203721 | AN8: 0 | AO8: =AN8*0.99% -> 0 | AP8: =AL8-AN8+'Catch up Fee'!E8+AM8 -> 1239.7259 | AQ8: =(AP8-AN8)*0.055 -> 68.184926 | AR8: 0 | AS8: =AR8*0.99% -> 0 | AT8: =AP8-AR8+'Catch up Fee'!E8+AQ8 -> 1507.9109 | AU8: =(AT8-AR8)*0.055 -> 82.935097 | AV8: 0 | AW8: =AV8*0.99% -> 0 | AX8: =AT8-AV8+'Catch up Fee'!E8+AU8 -> 1790.8459 | AY8: =(AX8-AV8)*0.055 -> 98.496527 | AZ8: 0 | BA8: =AZ8*0.99% -> 0 | BB8: =AX8-AZ8+'Catch up Fee'!E8+AY8 -> 2089.3425 | BC8: =(BB8-AZ8)*0.055 -> 114.91384 | BD8: 0 | BE8: =BD8*0.99% -> 0 | BF8: =BB8-BD8+'Catch up Fee'!E8+BC8 -> 2404.2563 | BG8: =(BF8-BD8)*0.055 -> 132.2341 | BH8: 0 | BI8: =BH8*0.99% -> 0 | BJ8: =BF8-BH8+'Catch up Fee'!E8+BG8 -> 2736.4904 | BK8: =(BJ8-BH8)*0.055 -> 150.50697 | BL8: =P8+T8+X8+AB8+AF8+AJ8+AR8+AN8+AV8+AZ8+BD8+BH8 -> 0
A9: Member 8 | B9: 23/07/2018 | C9: 0 | D9: =200*12 -> 2400 | E9: =' 2018-2019'!J8 -> 2400 | F9: =' 2018-2019'!F9 -> 0 | G9: =C9+D9 -> 2400 | H9: =BL9 -> 500 | I9: =G9-H9-C9 -> 1900 | J9: =I9+M9+E9+F9 -> 7072.2374 | K9: =Q9+U9+Y9+AC9+AG9+AK9+AO9+AS9+AW9+BA9+BE9+BI9 -> 4.95 | L9: =(H9-K9-C9)*5.5% -> 27.22775 | M9: =S9+W9+AA9+AE9+AI9+AM9+AQ9+AU9+AY9+BC9+BG9+BK9 -> 2772.2374 | N9: =M9 -> 2772.2374 | O9: =H9-K9-M9+L9 -> -2249.9597 | P9: 0 | Q9: =P9*0.99% -> 0 | R9: =E9+'Catch up Fee'!E9 -> 2600 | S9: =(R9-P9)*0.055 -> 143 | T9: ='2018-2019 B STATEMENT '!B365 -> 500 | U9: =T9*0.99% -> 4.95 | V9: =R9-T9+'Catch up Fee'!E9+S9 -> 2443 | W9: =(V9-T9)*0.055 -> 106.865 | X9: 0 | Y9: =X9*0.99% -> 0 | Z9: =V9-X9+'Catch up Fee'!E9+W9 -> 2749.865 | AA9: =(Z9-X9)*0.055 -> 151.24257 | AC9: =AB9*0.99% -> 0 | AD9: =Z9-AB9+'Catch up Fee'!E9+AA9 -> 3101.1076 | AE9: =(AD9-AB9)*0.055 -> 170.56092 | AG9: =AF9*0.99% -> 0 | AH9: =AD9-AF9+'Catch up Fee'!E9+AE9 -> 3471.6685 | AI9: =(AH9-AF9)*0.055 -> 190.94177 | AK9: =AJ9*0.99% -> 0 | AL9: =AH9-AJ9+'Catch up Fee'!E9+AI9 -> 3862.6103 | AM9: =(AL9-AJ9)*0.055 -> 212.44356 | AO9: =AN9*0.99% -> 0 | AP9: =AL9-AN9+'Catch up Fee'!E9+AM9 -> 4275.0538 | AQ9: =(AP9-AN9)*0.055 -> 235.12796 | AS9: =AR9*0.99% -> 0 | AT9: =AP9-AR9+'Catch up Fee'!E9+AQ9 -> 4710.1818 | AU9: =(AT9-AR9)*0.055 -> 259.06 | AW9: =AV9*0.99% -> 0 | AX9: =AT9-AV9+'Catch up Fee'!E9+AU9 -> 5169.2418 | AY9: =(AX9-AV9)*0.055 -> 284.3083 | BA9: =AZ9*0.99% -> 0 | BB9: =AX9-AZ9+'Catch up Fee'!E9+AY9 -> 5653.5501 | BC9: =(BB9-AZ9)*0.055 -> 310.94525 | BE9: =BD9*0.99% -> 0 | BF9: =BB9-BD9+'Catch up Fee'!E9+BC9 -> 6164.4953 | BG9: =(BF9-BD9)*0.055 -> 339.04724 | BI9: =BH9*0.99% -> 0 | BJ9: =BF9-BH9+'Catch up Fee'!E9+BG9 -> 6703.5426 | BK9: =(BJ9-BH9)*0.055 -> 368.69484 | BL9: =P9+T9+X9+AB9+AF9+AJ9+AR9+AN9+AV9+AZ9+BD9+BH9 -> 500
A10: Member 9 | B10: 21/07/2018 | C10: 0 | D10: =200*12 -> 2400 | E10: =' 2018-2019'!J9 -> 1100 | F10: =' 2018-2019'!F10 -> 0 | G10: =C10+D10 -> 2400 | H10: =BL10 -> 1800 | I10: =G10-H10-C10 -> 600 | J10: =I10+M10+E10+F10 -> 2898.5232 | K10: =Q10+U10+Y10+AC10+AG10+AK10+AO10+AS10+AW10+BA10+BE10+BI10 -> 17.82 | L10: =(H10-K10-C10)*5.5% -> 98.0199 | M10: =S10+W10+AA10+AE10+AI10+AM10+AQ10+AU10+AY10+BC10+BG10+BK10 -> 1198.5232 | N10: =M10 -> 1198.5232 | O10: =H10-K10-M10+L10 -> 681.67666 | P10: ='2018-2019 B STATEMENT '!B325 -> 200 | Q10: =P10*0.99% -> 1.98 | R10: =E10+'Catch up Fee'!E10 -> 1300 | S10: =(R10-P10)*0.055 -> 60.5 | T10: ='2018-2019 B STATEMENT '!B356 -> 200 | U10: =T10*0.99% -> 1.98 | V10: =R10-T10+'Catch up Fee'!E10+S10 -> 1360.5 | W10: =(V10-T10)*0.055 -> 63.8275 | X10: ='2018-2019 B STATEMENT '!B389 -> 200 | Y10: =X10*0.99% -> 1.98 | Z10: =V10-X10+'Catch up Fee'!E10+W10 -> 1424.3275 | AA10: =(Z10-X10)*0.055 -> 67.338013 | AB10: ='2018-2019 B STATEMENT '!B412 -> 200 | AC10: =AB10*0.99% -> 1.98 | AD10: =Z10-AB10+'Catch up Fee'!E10+AA10 -> 1491.6655 | AE10: =(AD10-AB10)*0.055 -> 71.041603 | AF10: ='2018-2019 B STATEMENT '!B435 -> 200 | AG10: =AF10*0.99% -> 1.98 | AH10: =AD10-AF10+'Catch up Fee'!E10+AE10 -> 1562.7071 | AI10: =(AH10-AF10)*0.055 -> 74.948891 | AJ10: ='2018-2019 B STATEMENT '!B453 -> 200 | AK10: =AJ10*0.99% -> 1.98 | AL10: =AH10-AJ10+'Catch up Fee'!E10+AI10 -> 1637.656 | AM10: =(AL10-AJ10)*0.055 -> 79.07108 | AN10: 0 | AO10: =AN10*0.99% -> 0 | AP10: =AL10-AN10+'Catch up Fee'!E10+AM10 -> 1916.7271 | AQ10: =(AP10-AN10)*0.055 -> 105.41999 | AR10: 0 | AS10: =AR10*0.99% -> 0 | AT10: =AP10-AR10+'Catch up Fee'!E10+AQ10 -> 2222.1471 | AU10: =(AT10-AR10)*0.055 -> 122.21809 | AV10: 0 | AW10: =AV10*0.99% -> 0 | AX10: =AT10-AV10+'Catch up Fee'!E10+AU10 -> 2544.3652 | AY10: =(AX10-AV10)*0.055 -> 139.94008 | AZ10: ='2018-2019 B STATEMENT '!B540 -> 300 | BA10: =AZ10*0.99% -> 2.97 | BB10: =AX10-AZ10+'Catch up Fee'!E10+AY10 -> 2584.3053 | BC10: =(BB10-AZ10)*0.055 -> 125.63679 | BD10: ='2018-2019 B STATEMENT '!B557 -> 300 | BE10: =BD10*0.99% -> 2.97 | BF10: =BB10-BD10+'Catch up Fee'!E10+BC10 -> 2609.942 | BG10: =(BF10-BD10)*0.055 -> 127.04681 | BH10: 0 | BI10: =BH10*0.99% -> 0 | BJ10: =BF10-BH10+'Catch up Fee'!E10+BG10 -> 2936.9889 | BK10: =(BJ10-BH10)*0.055 -> 161.53439 | BL10: =P10+T10+X10+AB10+AF10+AJ10+AR10+AN10+AV10+AZ10+BD10+BH10 -> 1800
A11: Member 10 | B11: 30/06/2020 | C11: 100 | D11: =200*12 -> 2400 | E11: =' 2018-2019'!J10 -> 300 | F11: =' 2018-2019'!F11 -> 2400 | G11: =C11+D11 -> 2500 | H11: =BL11 -> 0 | I11: =G11-H11-C11 -> 2400 | J11: =I11+M11+E11 -> 3847.4804 | K11: =Q11+U11+Y11+AC11+AG11+AK11+AO11+AS11+AW11+BA11+BE11+BI11 -> 0 | L11: =(H11-K11-C11)*5.5% -> -5.5 | M11: =S11+W11+AA11+AE11+AI11+AM11+AQ11+AU11+AY11+BC11+BG11+BK11 -> 1147.4804 | N11: =M11 -> 1147.4804 | O11: =H11-K11-M11+L11 -> -1152.9804 | P11: 0 | Q11: =P11*0.99% -> 0 | R11: =C11+'Catch up Fee'!E11 -> 300 | S11: =(R11-P11)*0.055 -> 16.5 | T11: 0 | U11: =T11*0.99% -> 0 | V11: =R11-T11+'Catch up Fee'!E11+S11 -> 516.5 | W11: =(V11-T11)*0.055 -> 28.4075 | X11: 0 | Y11: =X11*0.99% -> 0 | Z11: =V11-X11+'Catch up Fee'!E11+W11 -> 744.9075 | AA11: =(Z11-X11)*0.055 -> 40.969912 | AB11: 0 | AC11: =AB11*0.99% -> 0 | AD11: =Z11-AB11+'Catch up Fee'!E11+AA11 -> 985.87741 | AE11: =(AD11-AB11)*0.055 -> 54.223258 | AF11: 0 | AG11: =AF11*0.99% -> 0 | AH11: =AD11-AF11+'Catch up Fee'!E11+AE11 -> 1240.1007 | AI11: =(AH11-AF11)*0.055 -> 68.205537 | AJ11: 0 | AK11: =AJ11*0.99% -> 0 | AL11: =AH11-AJ11+'Catch up Fee'!E11+AI11 -> 1508.3062 | AM11: =(AL11-AJ11)*0.055 -> 82.956841 | AN11: 0 | AO11: =AN11*0.99% -> 0 | AP11: =AL11-AN11+'Catch up Fee'!E11+AM11 -> 1791.263 | AQ11: =(AP11-AN11)*0.055 -> 98.519468 | AR11: 0 | AS11: =AR11*0.99% -> 0 | AT11: =AP11-AR11+'Catch up Fee'!E11+AQ11 -> 2089.7825 | AU11: =(AT11-AR11)*0.055 -> 114.93804 | AV11: 0 | AW11: =AV11*0.99% -> 0 | AX11: =AT11-AV11+'Catch up Fee'!E11+AU11 -> 2404.7206 | AY11: =(AX11-AV11)*0.055 -> 132.25963 | AZ11: 0 | BA11: =AZ11*0.99% -> 0 | BB11: =AX11-AZ11+'Catch up Fee'!E11+AY11 -> 2736.9802 | BC11: =(BB11-AZ11)*0.055 -> 150.53391 | BD11: 0 | BE11: =BD11*0.99% -> 0 | BF11: =BB11-BD11+'Catch up Fee'!E11+BC11 -> 3087.5141 | BG11: =(BF11-BD11)*0.055 -> 169.81328 | BH11: 0 | BI11: =BH11*0.99% -> 0 | BJ11: =BF11-BH11+'Catch up Fee'!E11+BG11 -> 3457.3274 | BK11: =(BJ11-BH11)*0.055 -> 190.15301 | BL11: =P11+T11+X11+AB11+AF11+AJ11+AR11+AN11+AV11+AZ11+BD11+BH11 -> 0
A12: Member 11 | B12: 15/08/2018 | C12: 0 | D12: =200*12 -> 2400 | E12: =' 2018-2019'!J11 -> 2400 | F12: =' 2018-2019'!F12 -> 200 | G12: =C12+D12 -> 2400 | H12: =BL12 -> 2400 | I12: =G12-H12-C12 -> 0 | J12: =I12+M12+E12 -> 4328.2906 | K12: =Q12+U12+Y12+AC12+AG12+AK12+AO12+AS12+AW12+BA12+BE12+BI12 -> 23.76 | L12: =(H12-K12-C12)*5.5% -> 130.6932 | M12: =S12+W12+AA12+AE12+AI12+AM12+AQ12+AU12+AY12+BC12+BG12+BK12 -> 1928.2906 | N12: =M12 -> 1928.2906 | O12: =H12-K12-M12+L12 -> 578.64262 | P12: 0 | Q12: =P12*0.99% -> 0 | R12: =E12+'Catch up Fee'!E12 -> 2600 | S12: =(R12-P12)*0.055 -> 143 | T12: 0 | U12: =T12*0.99% -> 0 | V12: =R12-T12+'Catch up Fee'!E12+S12 -> 2943 | W12: =(V12-T12)*0.055 -> 161.865 | X12: ='2018-2019 B STATEMENT '!B372 -> 900 | Y12: =X12*0.99% -> 8.91 | Z12: =V12-X12+'Catch up Fee'!E12+W12 -> 2404.865 | AA12: =(Z12-X12)*0.055 -> 82.767575 | AB12: 0 | AC12: =AB12*0.99% -> 0 | AD12: =Z12-AB12+'Catch up Fee'!E12+AA12 -> 2687.6326 | AE12: =(AD12-AB12)*0.055 -> 147.81979 | AF12: ='2018-2019 B STATEMENT '!B425 -> 300 | AG12: =AF12*0.99% -> 2.97 | AH12: =AD12-AF12+'Catch up Fee'!E12+AE12 -> 2735.4524 | AI12: =(AH12-AF12)*0.055 -> 133.94988 | AJ12: 0 | AK12: =AJ12*0.99% -> 0 | AL12: =AH12-AJ12+'Catch up Fee'!E12+AI12 -> 3069.4022 | AM12: =(AL12-AJ12)*0.055 -> 168.81712 | AN12: ='2018-2019 B STATEMENT '!B478 -> 300 | AO12: =AN12*0.99% -> 2.97 | AP12: =AL12-AN12+'Catch up Fee'!E12+AM12 -> 3138.2194 | AQ12: =(AP12-AN12)*0.055 -> 156.10207 | AR12: ='2018-2019 B STATEMENT '!B499 -> 300 | AS12: =AR12*0.99% -> 2.97 | AT12: =AP12-AR12+'Catch up Fee'!E12+AQ12 -> 3194.3214 | AU12: =(AT12-AR12)*0.055 -> 159.18768 | AV12: ='2018-2019 B STATEMENT '!B515 -> 300 | AW12: =AV12*0.99% -> 2.97 | AX12: =AT12-AV12+'Catch up Fee'!E12+AU12 -> 3253.5091 | AY12: =(AX12-AV12)*0.055 -> 162.443 | BA12: =AZ12*0.99% -> 0 | BB12: =AX12-AZ12+'Catch up Fee'!E12+AY12 -> 3615.9521 | BC12: =(BB12-AZ12)*0.055 -> 198.87737 | BD12: ='2018-2019 B STATEMENT '!B552 -> 300 | BE12: =BD12*0.99% -> 2.97 | BF12: =BB12-BD12+'Catch up Fee'!E12+BC12 -> 3714.8295 | BG12: =(BF12-BD12)*0.055 -> 187.81562 | BH12: 0 | BI12: =BH12*0.99% -> 0 | BJ12: =BF12-BH12+'Catch up Fee'!E12+BG12 -> 4102.6451 | BK12: =(BJ12-BH12)*0.055 -> 225.64548 | BL12: =P12+T12+X12+AB12+AF12+AJ12+AR12+AN12+AV12+AZ12+BD12+BH12 -> 2400
A13: Member 12 | B13: 3/7/2018 | C13: 0 | D13: =200*12 -> 2400 | E13: =' 2018-2019'!J12 -> -500 | F13: =' 2018-2019'!F13 -> 0 | G13: =C13+D13 -> 2400 | H13: =BL13 -> 2300 | I13: =G13-H13-C13 -> 100 | J13: =I13+M13+E13+F13 -> -700.75958 | K13: =Q13+U13+Y13+AC13+AG13+AK13+AO13+AS13+AW13+BA13+BE13+BI13 -> 22.77 | L13: =(H13-K13-C13)*5.5% -> 125.24765 | M13: =S13+W13+AA13+AE13+AI13+AM13+AQ13+AU13+AY13+BC13+BG13+BK13 -> -300.75958 | N13: =M13 -> -300.75958 | O13: =H13-K13-M13+L13 -> 2703.2372 | P13: ='2018-2019 B STATEMENT '!B324 -> 200 | Q13: =P13*0.99% -> 1.98 | R13: =E13+'Catch up Fee'!E13 -> -300 | S13: =(R13-P13)*0.055 -> -27.5 | T13: 0 | U13: =T13*0.99% -> 0 | V13: =R13-T13+'Catch up Fee'!E13+S13 -> -127.5 | W13: =(V13-T13)*0.055 -> -7.0125 | X13: 0 | Y13: =X13*0.99% -> 0 | Z13: =V13-X13+'Catch up Fee'!E13+W13 -> 65.4875 | AA13: =(Z13-X13)*0.055 -> 3.6018125 | AB13: ='2018-2019 B STATEMENT '!B404+'2018-2019 B STATEMENT '!B420 -> 600 | AC13: =AB13*0.99% -> 5.94 | AD13: =Z13-AB13+'Catch up Fee'!E13+AA13 -> -330.91069 | AE13: =(AD13-AB13)*0.055 -> -51.200088 | AF13: 0 | AG13: =AF13*0.99% -> 0 | AH13: =AD13-AF13+'Catch up Fee'!E13+AE13 -> -182.11078 | AI13: =(AH13-AF13)*0.055 -> -10.016093 | AJ13: ='2018-2019 B STATEMENT '!B450 -> 200 | AK13: =AJ13*0.99% -> 1.98 | AL13: =AH13-AJ13+'Catch up Fee'!E13+AI13 -> -192.12687 | AM13: =(AL13-AJ13)*0.055 -> -21.566978 | AN13: ='2018-2019 B STATEMENT '!B491 -> 200 | AO13: =AN13*0.99% -> 1.98 | AP13: =AL13-AN13+'Catch up Fee'!E13+AM13 -> -213.69385 | AQ13: =(AP13-AN13)*0.055 -> -22.753162 | AR13: ='2018-2019 B STATEMENT '!B497 -> 200 | AS13: =AR13*0.99% -> 1.98 | AT13: =AP13-AR13+'Catch up Fee'!E13+AQ13 -> -236.44701 | AU13: =(AT13-AR13)*0.055 -> -24.004585 | AV13: ='2018-2019 B STATEMENT '!B529 -> 300 | AW13: =AV13*0.99% -> 2.97 | AX13: =AT13-AV13+'Catch up Fee'!E13+AU13 -> -360.45159 | AY13: =(AX13-AV13)*0.055 -> -36.324838 | AZ13: ='2018-2019 B STATEMENT '!B546 -> 200 | BA13: =AZ13*0.99% -> 1.98 | BB13: =AX13-AZ13+'Catch up Fee'!E13+AY13 -> -396.77643 | BC13: =(BB13-AZ13)*0.055 -> -32.822704 | BD13: ='2018-2019 B STATEMENT '!B554 -> 200 | BE13: =BD13*0.99% -> 1.98 | BF13: =BB13-BD13+'Catch up Fee'!E13+BC13 -> -429.59913 | BG13: =(BF13-BD13)*0.055 -> -34.627952 | BH13: ='2018-2019 B STATEMENT '!B574 -> 200 | BI13: =BH13*0.99% -> 1.98 | BJ13: =BF13-BH13+'Catch up Fee'!E13+BG13 -> -464.22709 | BK13: =(BJ13-BH13)*0.055 -> -36.53249 | BL13: =P13+T13+X13+AB13+AF13+AJ13+AR13+AN13+AV13+AZ13+BD13+BH13 -> 2300
A14: Member 13 | B14: 28/07/2018 | C14: 0 | D14: =200*12 -> 2400 | E14: =' 2018-2019'!J13 -> 100 | F14: =' 2018-2019'!F14 -> 0 | G14: =C14+D14 -> 2400 | H14: =BL14 -> 2400 | I14: =G14-H14-C14 -> 0 | J14: =I14+M14+E14+F14 -> 175.44375 | K14: =Q14+U14+Y14+AC14+AG14+AK14+AO14+AS14+AW14+BA14+BE14+BI14 -> 23.76 | L14: =(H14-K14-C14)*5.5% -> 130.6932 | M14: =S14+W14+AA14+AE14+AI14+AM14+AQ14+AU14+AY14+BC14+BG14+BK14 -> 75.443754 | N14: =M14 -> 75.443754 | O14: =H14-K14-M14+L14 -> 2431.4894 | P14: 0 | Q14: =P14*0.99% -> 0 | R14: =E14+'Catch up Fee'!E14 -> 300 | S14: =(R14-P14)*0.055 -> 16.5 | T14: ='2018-2019 B STATEMENT '!B367 -> 600 | U14: =T14*0.99% -> 5.94 | V14: =R14-T14+'Catch up Fee'!E14+S14 -> -83.5 | W14: =(V14-T14)*0.055 -> -37.5925 | X14: 0 | Y14: =X14*0.99% -> 0 | Z14: =V14-X14+'Catch up Fee'!E14+W14 -> 78.9075 | AA14: =(Z14-X14)*0.055 -> 4.3399125 | AB14: 0 | AC14: =AB14*0.99% -> 0 | AD14: =Z14-AB14+'Catch up Fee'!E14+AA14 -> 283.24741 | AE14: =(AD14-AB14)*0.055 -> 15.578608 | AF14: 0 | AG14: =AF14*0.99% -> 0 | AH14: =AD14-AF14+'Catch up Fee'!E14+AE14 -> 498.82602 | AI14: =(AH14-AF14)*0.055 -> 27.435431 | AJ14: ='2018-2019 B STATEMENT '!B447 -> 800 | AK14: =AJ14*0.99% -> 7.92 | AL14: =AH14-AJ14+'Catch up Fee'!E14+AI14 -> -73.738549 | AM14: =(AL14-AJ14)*0.055 -> -48.05562 | AN14: 0 | AO14: =AN14*0.99% -> 0 | AP14: =AL14-AN14+'Catch up Fee'!E14+AM14 -> 78.205831 | AQ14: =(AP14-AN14)*0.055 -> 4.3013207 | AR14: 0 | AS14: =AR14*0.99% -> 0 | AT14: =AP14-AR14+'Catch up Fee'!E14+AQ14 -> 282.50715 | AU14: =(AT14-AR14)*0.055 -> 15.537893 | AV14: 0 | AW14: =AV14*0.99% -> 0 | AX14: =AT14-AV14+'Catch up Fee'!E14+AU14 -> 498.04505 | AY14: =(AX14-AV14)*0.055 -> 27.392477 | AZ14: 0 | BA14: =AZ14*0.99% -> 0 | BB14: =AX14-AZ14+'Catch up Fee'!E14+AY14 -> 725.43752 | BC14: =(BB14-AZ14)*0.055 -> 39.899064 | BD14: 0 | BE14: =BD14*0.99% -> 0 | BF14: =BB14-BD14+'Catch up Fee'!E14+BC14 -> 965.33659 | BG14: =(BF14-BD14)*0.055 -> 53.093512 | BH14: ='2018-2019 B STATEMENT '!B575 -> 1000 | BI14: =BH14*0.99% -> 9.9 | BJ14: =BF14-BH14+'Catch up Fee'!E14+BG14 -> 218.4301 | BK14: =(BJ14-BH14)*0.055 -> -42.986345 | BL14: =P14+T14+X14+AB14+AF14+AJ14+AR14+AN14+AV14+AZ14+BD14+BH14 -> 2400
A15: Member 14 | B15: 3/7/2018 | C15: 0 | D15: =200*12 -> 2400 | E15: =' 2018-2019'!J14 -> 300 | F15: =' 2018-2019'!F15 -> 0 | G15: =C15+D15 -> 2400 | H15: =BL15 -> 0 | I15: =G15-H15-C15 -> 2400 | J15: =I15+M15+E15+F15 -> 4027.7219 | K15: =Q15+U15+Y15+AC15+AG15+AK15+AO15+AS15+AW15+BA15+BE15+BI15 -> 0 | L15: =(H15-K15-C15)*5.5% -> 0 | M15: =S15+W15+AA15+AE15+AI15+AM15+AQ15+AU15+AY15+BC15+BG15+BK15 -> 1327.7219 | N15: =M15 -> 1327.7219 | O15: =H15-K15-M15+L15 -> -1327.7219 | P15: 0 | Q15: =P15*0.99% -> 0 | R15: =E15+'Catch up Fee'!E15 -> 500 | S15: =(R15-P15)*0.055 -> 27.5 | T15: 0 | U15: =T15*0.99% -> 0 | V15: =R15-T15+'Catch up Fee'!E15+S15 -> 727.5 | W15: =(V15-T15)*0.055 -> 40.0125 | X15: 0 | Y15: =X15*0.99% -> 0 | Z15: =V15-X15+'Catch up Fee'!E15+W15 -> 967.5125 | AA15: =(Z15-X15)*0.055 -> 53.213188 | AB15: 0 | AC15: =AB15*0.99% -> 0 | AD15: =Z15-AB15+'Catch up Fee'!E15+AA15 -> 1220.7257 | AE15: =(AD15-AB15)*0.055 -> 67.139913 | AF15: 0 | AG15: =AF15*0.99% -> 0 | AH15: =AD15-AF15+'Catch up Fee'!E15+AE15 -> 1487.8656 | AI15: =(AH15-AF15)*0.055 -> 81.832608 | AJ15: 0 | AK15: =AJ15*0.99% -> 0 | AL15: =AH15-AJ15+'Catch up Fee'!E15+AI15 -> 1769.6982 | AM15: =(AL15-AJ15)*0.055 -> 97.333401 | AN15: 0 | AO15: =AN15*0.99% -> 0 | AP15: =AL15-AN15+'Catch up Fee'!E15+AM15 -> 2067.0316 | AQ15: =(AP15-AN15)*0.055 -> 113.68674 | AR15: 0 | AS15: =AR15*0.99% -> 0 | AT15: =AP15-AR15+'Catch up Fee'!E15+AQ15 -> 2380.7183 | AU15: =(AT15-AR15)*0.055 -> 130.93951 | AV15: 0 | AW15: =AV15*0.99% -> 0 | AX15: =AT15-AV15+'Catch up Fee'!E15+AU15 -> 2711.6579 | AY15: =(AX15-AV15)*0.055 -> 149.14118 | AZ15: 0 | BA15: =AZ15*0.99% -> 0 | BB15: =AX15-AZ15+'Catch up Fee'!E15+AY15 -> 3060.799 | BC15: =(BB15-AZ15)*0.055 -> 168.34395 | BD15: 0 | BE15: =BD15*0.99% -> 0 | BF15: =BB15-BD15+'Catch up Fee'!E15+BC15 -> 3429.143 | BG15: =(BF15-BD15)*0.055 -> 188.60286 | BH15: 0 | BI15: =BH15*0.99% -> 0 | BJ15: =BF15-BH15+'Catch up Fee'!E15+BG15 -> 3817.7459 | BK15: =(BJ15-BH15)*0.055 -> 209.97602 | BL15: =P15+T15+X15+AB15+AF15+AJ15+AR15+AN15+AV15+AZ15+BD15+BH15 -> 0
A16: Member 15 | C16: 0 | D16: =200*12 -> 2400 | E16: =' 2018-2019'!J15 -> 2300 | F16: =' 2018-2019'!F16 -> 0 | G16: =C16+D16 -> 2400 | H16: =BL16 -> 2100 | I16: =G16-H16-C16 -> 300 | J16: =I16+M16+E16+F16 -> 4056.0281 | K16: =Q16+U16+Y16+AC16+AG16+AK16+AO16+AS16+AW16+BA16+BE16+BI16 -> 20.79 | L16: =(H16-K16-C16)*5.5% -> 114.35655 | M16: =S16+W16+AA16+AE16+AI16+AM16+AQ16+AU16+AY16+BC16+BG16+BK16 -> 1456.0281 | N16: =M16 -> 1456.0281 | O16: =H16-K16-M16+L16 -> 737.53846 | P16: 0 | Q16: =P16*0.99% -> 0 | R16: =E16+'Catch up Fee'!E16 -> 2500 | S16: =(R16-P16)*0.055 -> 137.5 | T16: 0 | U16: =T16*0.99% -> 0 | V16: =R16-T16+'Catch up Fee'!E16+S16 -> 2837.5 | W16: =(V16-T16)*0.055 -> 156.0625 | X16: ='2018-2019 B STATEMENT '!B378 -> 2100 | Y16: =X16*0.99% -> 20.79 | Z16: =V16-X16+'Catch up Fee'!E16+W16 -> 1093.5625 | AA16: =(Z16-X16)*0.055 -> -55.354062 | AB16: 0 | AC16: =AB16*0.99% -> 0 | AD16: =Z16-AB16+'Catch up Fee'!E16+AA16 -> 1238.2084 | AE16: =(AD16-AB16)*0.055 -> 68.101464 | AF16: 0 | AG16: =AF16*0.99% -> 0 | AH16: =AD16-AF16+'Catch up Fee'!E16+AE16 -> 1506.3099 | AI16: =(AH16-AF16)*0.055 -> 82.847045 | AJ16: 0 | AK16: =AJ16*0.99% -> 0 | AL16: =AH16-AJ16+'Catch up Fee'!E16+AI16 -> 1789.1569 | AM16: =(AL16-AJ16)*0.055 -> 98.403632 | AN16: 0 | AO16: =AN16*0.99% -> 0 | AP16: =AL16-AN16+'Catch up Fee'!E16+AM16 -> 2087.5606 | AQ16: =(AP16-AN16)*0.055 -> 114.81583 | AR16: 0 | AS16: =AR16*0.99% -> 0 | AT16: =AP16-AR16+'Catch up Fee'!E16+AQ16 -> 2402.3764 | AU16: =(AT16-AR16)*0.055 -> 132.1307 | AV16: 0 | AW16: =AV16*0.99% -> 0 | AX16: =AT16-AV16+'Catch up Fee'!E16+AU16 -> 2734.5071 | AY16: =(AX16-AV16)*0.055 -> 150.39789 | AZ16: 0 | BA16: =AZ16*0.99% -> 0 | BB16: =AX16-AZ16+'Catch up Fee'!E16+AY16 -> 3084.905 | BC16: =(BB16-AZ16)*0.055 -> 169.66978 | BD16: 0 | BE16: =BD16*0.99% -> 0 | BF16: =BB16-BD16+'Catch up Fee'!E16+BC16 -> 3454.5748 | BG16: =(BF16-BD16)*0.055 -> 190.00161 | BH16: 0 | BI16: =BH16*0.99% -> 0 | BJ16: =BF16-BH16+'Catch up Fee'!E16+BG16 -> 3844.5764 | BK16: =(BJ16-BH16)*0.055 -> 211.4517 | BL16: =P16+T16+X16+AB16+AF16+AJ16+AR16+AN16+AV16+AZ16+BD16+BH16 -> 2100
A17: Member 16 | B17: 28/07/2018 | C17: 0 | D17: =200*12 -> 2400 | E17: =' 2018-2019'!J16 -> 2400 | F17: =' 2018-2019'!F17 -> 0 | G17: =C17+D17 -> 2400 | H17: =BL17 -> 0 | I17: =G17-H17-C17 -> 2400 | J17: =I17+M17+E17+F17 -> 8020.2576 | K17: =Q17+U17+Y17+AC17+AG17+AK17+AO17+AS17+AW17+BA17+BE17+BI17 -> 0 | L17: =(H17-K17-C17)*5.5% -> 0 | M17: =S17+W17+AA17+AE17+AI17+AM17+AQ17+AU17+AY17+BC17+BG17+BK17 -> 3220.2576 | N17: =M17 -> 3220.2576 | O17: =H17-K17-M17+L17 -> -3220.2576 | P17: 0 | Q17: =P17*0.99% -> 0 | R17: =E17+'Catch up Fee'!E17 -> 2600 | S17: =(R17-P17)*0.055 -> 143 | T17: 0 | U17: =T17*0.99% -> 0 | V17: =R17-T17+'Catch up Fee'!E17+S17 -> 2943 | W17: =(V17-T17)*0.055 -> 161.865 | X17: 0 | Y17: =X17*0.99% -> 0 | Z17: =V17-X17+'Catch up Fee'!E17+W17 -> 3304.865 | AA17: =(Z17-X17)*0.055 -> 181.76757 | AB17: 0 | AC17: =AB17*0.99% -> 0 | AD17: =Z17-AB17+'Catch up Fee'!E17+AA17 -> 3686.6326 | AE17: =(AD17-AB17)*0.055 -> 202.76479 | AF17: 0 | AG17: =AF17*0.99% -> 0 | AH17: =AD17-AF17+'Catch up Fee'!E17+AE17 -> 4089.3974 | AI17: =(AH17-AF17)*0.055 -> 224.91686 | AJ17: 0 | AK17: =AJ17*0.99% -> 0 | AL17: =AH17-AJ17+'Catch up Fee'!E17+AI17 -> 4514.3142 | AM17: =(AL17-AJ17)*0.055 -> 248.28728 | AN17: 0 | AO17: =AN17*0.99% -> 0 | AP17: =AL17-AN17+'Catch up Fee'!E17+AM17 -> 4962.6015 | AQ17: =(AP17-AN17)*0.055 -> 272.94308 | AR17: 0 | AS17: =AR17*0.99% -> 0 | AT17: =AP17-AR17+'Catch up Fee'!E17+AQ17 -> 5435.5446 | AU17: =(AT17-AR17)*0.055 -> 298.95495 | AV17: 0 | AW17: =AV17*0.99% -> 0 | AX17: =AT17-AV17+'Catch up Fee'!E17+AU17 -> 5934.4995 | AY17: =(AX17-AV17)*0.055 -> 326.39747 | AZ17: 0 | BA17: =AZ17*0.99% -> 0 | BB17: =AX17-AZ17+'Catch up Fee'!E17+AY17 -> 6460.897 | BC17: =(BB17-AZ17)*0.055 -> 355.34934 | BD17: 0 | BE17: =BD17*0.99% -> 0 | BF17: =BB17-BD17+'Catch up Fee'!E17+BC17 -> 7016.2463 | BG17: =(BF17-BD17)*0.055 -> 385.89355 | BH17: 0 | BI17: =BH17*0.99% -> 0 | BJ17: =BF17-BH17+'Catch up Fee'!E17+BG17 -> 7602.1399 | BK17: =(BJ17-BH17)*0.055 -> 418.11769 | BL17: =P17+T17+X17+AB17+AF17+AJ17+AR17+AN17+AV17+AZ17+BD17+BH17 -> 0
A18: Member 17 | B18: 25/01/2019 | C18: 0 | D18: =200*12 -> 2400 | E18: =' 2018-2019'!J17 -> 1100 | F18: =' 2018-2019'!F18 -> 1200 | G18: =C18+D18 -> 2400 | H18: =BL18 -> 2450 | I18: =G18-H18-C18 -> -50 | J18: =I18+M18+E18 -> 2031.3908 | K18: =Q18+U18+Y18+AC18+AG18+AK18+AO18+AS18+AW18+BA18+BE18+BI18 -> 24.255 | L18: =(H18-K18-C18)*5.5% -> 133.41598 | M18: =S18+W18+AA18+AE18+AI18+AM18+AQ18+AU18+AY18+BC18+BG18+BK18 -> 981.39079 | N18: =M18 -> 981.39079 | O18: =H18-K18-M18+L18 -> 1577.7702 | P18: ='2018-2019 B STATEMENT '!B318 -> 1000 | Q18: =P18*0.99% -> 9.9 | R18: =E18+'Catch up Fee'!E18 -> 1300 | S18: =(R18-P18)*0.055 -> 16.5 | T18: 0 | U18: =T18*0.99% -> 0 | V18: =R18-T18+'Catch up Fee'!E18+S18 -> 1516.5 | W18: =(V18-T18)*0.055 -> 83.4075 | X18: 0 | Y18: =X18*0.99% -> 0 | Z18: =V18-X18+'Catch up Fee'!E18+W18 -> 1799.9075 | AA18: =(Z18-X18)*0.055 -> 98.994912 | AB18: ='2018-2019 B STATEMENT '!B402 -> 1150 | AC18: =AB18*0.99% -> 11.385 | AD18: =Z18-AB18+'Catch up Fee'!E18+AA18 -> 948.90241 | AE18: =(AD18-AB18)*0.055 -> -11.060367 | AF18: 0 | AG18: =AF18*0.99% -> 0 | AH18: =AD18-AF18+'Catch up Fee'!E18+AE18 -> 1137.842 | AI18: =(AH18-AF18)*0.055 -> 62.581312 | AJ18: ='2018-2019 B STATEMENT '!B451 -> 300 | AK18: =AJ18*0.99% -> 2.97 | AL18: =AH18-AJ18+'Catch up Fee'!E18+AI18 -> 1100.4234 | AM18: =(AL18-AJ18)*0.055 -> 44.023285 | AN18: 0 | AO18: =AN18*0.99% -> 0 | AP18: =AL18-AN18+'Catch up Fee'!E18+AM18 -> 1344.4466 | AQ18: =(AP18-AN18)*0.055 -> 73.944565 | AR18: 0 | AS18: =AR18*0.99% -> 0 | AT18: =AP18-AR18+'Catch up Fee'!E18+AQ18 -> 1618.3912 | AU18: =(AT18-AR18)*0.055 -> 89.011516 | AV18: 0 | AW18: =AV18*0.99% -> 0 | AX18: =AT18-AV18+'Catch up Fee'!E18+AU18 -> 1907.4027 | AY18: =(AX18-AV18)*0.055 -> 104.90715 | AZ18: 0 | BA18: =AZ18*0.99% -> 0 | BB18: =AX18-AZ18+'Catch up Fee'!E18+AY18 -> 2212.3099 | BC18: =(BB18-AZ18)*0.055 -> 121.67704 | BD18: 0 | BE18: =BD18*0.99% -> 0 | BF18: =BB18-BD18+'Catch up Fee'!E18+BC18 -> 2533.9869 | BG18: =(BF18-BD18)*0.055 -> 139.36928 | BH18: 0 | BI18: =BH18*0.99% -> 0 | BJ18: =BF18-BH18+'Catch up Fee'!E18+BG18 -> 2873.3562 | BK18: =(BJ18-BH18)*0.055 -> 158.03459 | BL18: =P18+T18+X18+AB18+AF18+AJ18+AR18+AN18+AV18+AZ18+BD18+BH18 -> 2450
A19: Member 18 | B19: 3/7/2018 | C19: 0 | D19: =200*12 -> 2400 | E19: =' 2018-2019'!J18 -> 150 | F19: =' 2018-2019'!F19 -> 0 | G19: =C19+D19 -> 2400 | H19: =BL19 -> 2400 | I19: =G19-H19-C19 -> 0 | J19: =I19+M19+E19+F19 -> 285.18112 | K19: =Q19+U19+Y19+AC19+AG19+AK19+AO19+AS19+AW19+BA19+BE19+BI19 -> 23.76 | L19: =(H19-K19-C19)*5.5% -> 130.6932 | M19: =S19+W19+AA19+AE19+AI19+AM19+AQ19+AU19+AY19+BC19+BG19+BK19 -> 135.18112 | N19: =M19 -> 135.18112 | O19: =H19-K19-M19+L19 -> 2371.7521 | P19: ='2018-2019 B STATEMENT '!B322 -> 200 | Q19: =P19*0.99% -> 1.98 | R19: =E19+'Catch up Fee'!E19 -> 350 | S19: =(R19-P19)*0.055 -> 8.25 | T19: ='2018-2019 B STATEMENT '!B351 -> 200 | U19: =T19*0.99% -> 1.98 | V19: =R19-T19+'Catch up Fee'!E19+S19 -> 358.25 | W19: =(V19-T19)*0.055 -> 8.70375 | X19: ='2018-2019 B STATEMENT '!B383 -> 200 | Y19: =X19*0.99% -> 1.98 | Z19: =V19-X19+'Catch up Fee'!E19+W19 -> 366.95375 | AA19: =(Z19-X19)*0.055 -> 9.1824563 | AB19: ='2018-2019 B STATEMENT '!B408 -> 200 | AC19: =AB19*0.99% -> 1.98 | AD19: =Z19-AB19+'Catch up Fee'!E19+AA19 -> 376.13621 | AE19: =(AD19-AB19)*0.055 -> 9.6874913 | AF19: ='2018-2019 B STATEMENT '!B428 -> 200 | AG19: =AF19*0.99% -> 1.98 | AH19: =AD19-AF19+'Catch up Fee'!E19+AE19 -> 385.8237 | AI19: =(AH19-AF19)*0.055 -> 10.220303 | AJ19: ='2018-2019 B STATEMENT '!B452 -> 200 | AK19: =AJ19*0.99% -> 1.98 | AL19: =AH19-AJ19+'Catch up Fee'!E19+AI19 -> 396.044 | AM19: =(AL19-AJ19)*0.055 -> 10.78242 | AN19: ='2018-2019 B STATEMENT '!B487 -> 200 | AO19: =AN19*0.99% -> 1.98 | AP19: =AL19-AN19+'Catch up Fee'!E19+AM19 -> 406.82642 | AQ19: =(AP19-AN19)*0.055 -> 11.375453 | AR19: ='2018-2019 B STATEMENT '!B521 -> 200 | AS19: =AR19*0.99% -> 1.98 | AT19: =AP19-AR19+'Catch up Fee'!E19+AQ19 -> 418.20187 | AU19: =(AT19-AR19)*0.055 -> 12.001103 | AV19: ='2018-2019 B STATEMENT '!B521 -> 200 | AW19: =AV19*0.99% -> 1.98 | AX19: =AT19-AV19+'Catch up Fee'!E19+AU19 -> 430.20298 | AY19: =(AX19-AV19)*0.055 -> 12.661164 | AZ19: ='2018-2019 B STATEMENT '!B539 -> 200 | BA19: =AZ19*0.99% -> 1.98 | BB19: =AX19-AZ19+'Catch up Fee'!E19+AY19 -> 442.86414 | BC19: =(BB19-AZ19)*0.055 -> 13.357528 | BD19: ='2018-2019 B STATEMENT '!B558 -> 200 | BE19: =BD19*0.99% -> 1.98 | BF19: =BB19-BD19+'Catch up Fee'!E19+BC19 -> 456.22167 | BG19: =(BF19-BD19)*0.055 -> 14.092192 | BH19: ='2018-2019 B STATEMENT '!B578 -> 200 | BI19: =BH19*0.99% -> 1.98 | BJ19: =BF19-BH19+'Catch up Fee'!E19+BG19 -> 470.31386 | BK19: =(BJ19-BH19)*0.055 -> 14.867262 | BL19: =P19+T19+X19+AB19+AF19+AJ19+AR19+AN19+AV19+AZ19+BD19+BH19 -> 2400
A20: Member 19 | B20: 16/7/2019 | C20: 100 | D20: =200*12 -> 2400 | E20: =' 2018-2019'!J19 -> 100 | F20: =' 2018-2019'!F20 -> 2400 | G20: =C20+D20 -> 2500 | H20: =BL20 -> 500 | I20: =G20-H20-C20 -> 1900 | J20: =I20+M20+E20 -> 2719.2293 | K20: =Q20+U20+Y20+AC20+AG20+AK20+AO20+AS20+AW20+BA20+BE20+BI20 -> 4.95 | L20: =(H20-K20-C20)*5.5% -> 21.72775 | M20: =S20+W20+AA20+AE20+AI20+AM20+AQ20+AU20+AY20+BC20+BG20+BK20 -> 719.22934 | N20: =M20 -> 719.22934 | O20: =H20-K20-M20+L20 -> -202.45159 | P20: 0 | Q20: =P20*0.99% -> 0 | R20: =E20+'Catch up Fee'!E20 -> 300 | S20: =(R20-P20)*0.055 -> 16.5 | T20: ='2018-2019 B STATEMENT '!B348+'2018-2019 B STATEMENT '!B352 -> 300 | U20: =T20*0.99% -> 2.97 | V20: =R20-T20+'Catch up Fee'!E20+S20 -> 216.5 | W20: =(V20-T20)*0.055 -> -4.5925 | X20: ='2018-2019 B STATEMENT '!B384 -> 200 | Y20: =X20*0.99% -> 1.98 | Z20: =V20-X20+'Catch up Fee'!E20+W20 -> 211.9075 | AA20: =(Z20-X20)*0.055 -> 0.6549125 | AB20: 0 | AC20: =AB20*0.99% -> 0 | AD20: =Z20-AB20+'Catch up Fee'!E20+AA20 -> 412.56241 | AE20: =(AD20-AB20)*0.055 -> 22.690933 | AF20: 0 | AG20: =AF20*0.99% -> 0 | AH20: =AD20-AF20+'Catch up Fee'!E20+AE20 -> 635.25335 | AI20: =(AH20-AF20)*0.055 -> 34.938934 | AJ20: 0 | AK20: =AJ20*0.99% -> 0 | AL20: =AH20-AJ20+'Catch up Fee'!E20+AI20 -> 870.19228 | AM20: =(AL20-AJ20)*0.055 -> 47.860575 | AN20: 0 | AO20: =AN20*0.99% -> 0 | AP20: =AL20-AN20+'Catch up Fee'!E20+AM20 -> 1118.0529 | AQ20: =(AP20-AN20)*0.055 -> 61.492907 | AR20: 0 | AS20: =AR20*0.99% -> 0 | AT20: =AP20-AR20+'Catch up Fee'!E20+AQ20 -> 1379.5458 | AU20: =(AT20-AR20)*0.055 -> 75.875017 | AV20: 0 | AW20: =AV20*0.99% -> 0 | AX20: =AT20-AV20+'Catch up Fee'!E20+AU20 -> 1655.4208 | AY20: =(AX20-AV20)*0.055 -> 91.048143 | AZ20: 0 | BA20: =AZ20*0.99% -> 0 | BB20: =AX20-AZ20+'Catch up Fee'!E20+AY20 -> 1946.4689 | BC20: =(BB20-AZ20)*0.055 -> 107.05579 | BD20: 0 | BE20: =BD20*0.99% -> 0 | BF20: =BB20-BD20+'Catch up Fee'!E20+BC20 -> 2253.5247 | BG20: =(BF20-BD20)*0.055 -> 123.94386 | BH20: 0 | BI20: =BH20*0.99% -> 0 | BJ20: =BF20-BH20+'Catch up Fee'!E20+BG20 -> 2577.4686 | BK20: =(BJ20-BH20)*0.055 -> 141.76077 | BL20: =P20+T20+X20+AB20+AF20+AJ20+AR20+AN20+AV20+AZ20+BD20+BH20 -> 500
A21: Member 20 | B21: 25/07/2018 | C21: 0 | D21: =200*12 -> 2400 | E21: =' 2018-2019'!J20 -> 2400 | F21: =' 2018-2019'!F21 -> 0 | G21: =C21+D21 -> 2400 | H21: =BL21 -> 2470 | I21: =G21-H21-C21 -> -70 | J21: =I21+M21+E21+F21 -> 5100.6657 | K21: =Q21+U21+Y21+AC21+AG21+AK21+AO21+AS21+AW21+BA21+BE21+BI21 -> 24.453 | L21: =(H21-K21-C21)*5.5% -> 134.50509 | M21: =S21+W21+AA21+AE21+AI21+AM21+AQ21+AU21+AY21+BC21+BG21+BK21 -> 2770.6657 | N21: =M21 -> 2770.6657 | O21: =H21-K21-M21+L21 -> -190.61357 | P21: ='2018-2019 B STATEMENT '!B321 -> 600 | Q21: =P21*0.99% -> 5.94 | R21: =E21+'Catch up Fee'!E21 -> 2600 | S21: =(R21-P21)*0.055 -> 110 | T21: 0 | U21: =T21*0.99% -> 0 | V21: =R21-T21+'Catch up Fee'!E21+S21 -> 2910 | W21: =(V21-T21)*0.055 -> 160.05 | X21: 0 | Y21: =X21*0.99% -> 0 | Z21: =V21-X21+'Catch up Fee'!E21+W21 -> 3270.05 | AA21: =(Z21-X21)*0.055 -> 179.85275 | AB21: 0 | AC21: =AB21*0.99% -> 0 | AD21: =Z21-AB21+'Catch up Fee'!E21+AA21 -> 3649.9028 | AE21: =(AD21-AB21)*0.055 -> 200.74465 | AF21: 0 | AG21: =AF21*0.99% -> 0 | AH21: =AD21-AF21+'Catch up Fee'!E21+AE21 -> 4050.6474 | AI21: =(AH21-AF21)*0.055 -> 222.78561 | AJ21: 0 | AK21: =AJ21*0.99% -> 0 | AL21: =AH21-AJ21+'Catch up Fee'!E21+AI21 -> 4473.433 | AM21: =(AL21-AJ21)*0.055 -> 246.03882 | AN21: 0 | AO21: =AN21*0.99% -> 0 | AP21: =AL21-AN21+'Catch up Fee'!E21+AM21 -> 4919.4718 | AQ21: =(AP21-AN21)*0.055 -> 270.57095 | AR21: 0 | AS21: =AR21*0.99% -> 0 | AT21: =AP21-AR21+'Catch up Fee'!E21+AQ21 -> 5390.0428 | AU21: =(AT21-AR21)*0.055 -> 296.45235 | AV21: 0 | AW21: =AV21*0.99% -> 0 | AX21: =AT21-AV21+'Catch up Fee'!E21+AU21 -> 5886.4951 | AY21: =(AX21-AV21)*0.055 -> 323.75723 | AZ21: ='2018-2019 B STATEMENT '!B548+'2018-2019 B STATEMENT '!B549 -> 1470 | BA21: =AZ21*0.99% -> 14.553 | BB21: =AX21-AZ21+'Catch up Fee'!E21+AY21 -> 4940.2524 | BC21: =(BB21-AZ21)*0.055 -> 190.86388 | BD21: 0 | BE21: =BD21*0.99% -> 0 | BF21: =BB21-BD21+'Catch up Fee'!E21+BC21 -> 5331.1162 | BG21: =(BF21-BD21)*0.055 -> 293.21139 | BH21: ='2018-2019 B STATEMENT '!B577 -> 400 | BI21: =BH21*0.99% -> 3.96 | BJ21: =BF21-BH21+'Catch up Fee'!E21+BG21 -> 5424.3276 | BK21: =(BJ21-BH21)*0.055 -> 276.33802 | BL21: =P21+T21+X21+AB21+AF21+AJ21+AR21+AN21+AV21+AZ21+BD21+BH21 -> 2470
A22: Member 21 | B22: 20/08/2018 | C22: 0 | D22: =200*12 -> 2400 | E22: =' 2018-2019'!J21 -> 1500 | F22: =' 2018-2019'!F22 -> 200 | G22: =C22+D22 -> 2400 | H22: =BL22 -> 0 | I22: =G22-H22-C22 -> 2400 | J22: =I22+M22+E22 -> 6309.1709 | K22: =Q22+U22+Y22+AC22+AG22+AK22+AO22+AS22+AW22+BA22+BE22+BI22 -> 0 | L22: =(H22-K22-C22)*5.5% -> 0 | M22: =S22+W22+AA22+AE22+AI22+AM22+AQ22+AU22+AY22+BC22+BG22+BK22 -> 2409.1709 | N22: =M22 -> 2409.1709 | O22: =H22-K22-M22+L22 -> -2409.1709 | P22: 0 | Q22: =P22*0.99% -> 0 | R22: =E22+'Catch up Fee'!E22 -> 1700 | S22: =(R22-P22)*0.055 -> 93.5 | T22: 0 | U22: =T22*0.99% -> 0 | V22: =R22-T22+'Catch up Fee'!E22+S22 -> 1993.5 | W22: =(V22-T22)*0.055 -> 109.6425 | X22: 0 | Y22: =X22*0.99% -> 0 | Z22: =V22-X22+'Catch up Fee'!E22+W22 -> 2303.1425 | AA22: =(Z22-X22)*0.055 -> 126.67284 | AB22: 0 | AC22: =AB22*0.99% -> 0 | AD22: =Z22-AB22+'Catch up Fee'!E22+AA22 -> 2629.8153 | AE22: =(AD22-AB22)*0.055 -> 144.63984 | AF22: 0 | AG22: =AF22*0.99% -> 0 | AH22: =AD22-AF22+'Catch up Fee'!E22+AE22 -> 2974.4552 | AI22: =(AH22-AF22)*0.055 -> 163.59503 | AJ22: 0 | AK22: =AJ22*0.99% -> 0 | AL22: =AH22-AJ22+'Catch up Fee'!E22+AI22 -> 3338.0502 | AM22: =(AL22-AJ22)*0.055 -> 183.59276 | AN22: 0 | AO22: =AN22*0.99% -> 0 | AP22: =AL22-AN22+'Catch up Fee'!E22+AM22 -> 3721.643 | AQ22: =(AP22-AN22)*0.055 -> 204.69036 | AR22: 0 | AS22: =AR22*0.99% -> 0 | AT22: =AP22-AR22+'Catch up Fee'!E22+AQ22 -> 4126.3333 | AU22: =(AT22-AR22)*0.055 -> 226.94833 | AV22: 0 | AW22: =AV22*0.99% -> 0 | AX22: =AT22-AV22+'Catch up Fee'!E22+AU22 -> 4553.2817 | AY22: =(AX22-AV22)*0.055 -> 250.43049 | AZ22: 0 | BA22: =AZ22*0.99% -> 0 | BB22: =AX22-AZ22+'Catch up Fee'!E22+AY22 -> 5003.7122 | BC22: =(BB22-AZ22)*0.055 -> 275.20417 | BD22: 0 | BE22: =BD22*0.99% -> 0 | BF22: =BB22-BD22+'Catch up Fee'!E22+BC22 -> 5478.9163 | BG22: =(BF22-BD22)*0.055 -> 301.3404 | BH22: 0 | BI22: =BH22*0.99% -> 0 | BJ22: =BF22-BH22+'Catch up Fee'!E22+BG22 -> 5980.2567 | BK22: =(BJ22-BH22)*0.055 -> 328.91412 | BL22: =P22+T22+X22+AB22+AF22+AJ22+AR22+AN22+AV22+AZ22+BD22+BH22 -> 0
A23: Member 22 | B23: 26/08/2018 | C23: 0 | D23: =200*12 -> 2400 | E23: =' 2018-2019'!J22 -> 1200 | F23: =' 2018-2019'!F23 -> 200 | G23: =C23+D23 -> 2400 | H23: =BL23 -> 1300 | I23: =G23-H23-C23 -> 1100 | J23: =I23+M23+E23 -> 3892.399 | K23: =Q23+U23+Y23+AC23+AG23+AK23+AO23+AS23+AW23+BA23+BE23+BI23 -> 12.87 | L23: =(H23-K23-C23)*5.5% -> 70.79215 | M23: =S23+W23+AA23+AE23+AI23+AM23+AQ23+AU23+AY23+BC23+BG23+BK23 -> 1592.399 | N23: =M23 -> 1592.399 | O23: =H23-K23-M23+L23 -> -234.47681 | P23: ='2018-2019 B STATEMENT '!B335 -> 400 | Q23: =P23*0.99% -> 3.96 | R23: =E23+'Catch up Fee'!E23 -> 1400 | S23: =(R23-P23)*0.055 -> 55 | T23: 0 | U23: =T23*0.99% -> 0 | V23: =R23-T23+'Catch up Fee'!E23+S23 -> 1655 | W23: =(V23-T23)*0.055 -> 91.025 | X23: 0 | Y23: =X23*0.99% -> 0 | Z23: =V23-X23+'Catch up Fee'!E23+W23 -> 1946.025 | AA23: =(Z23-X23)*0.055 -> 107.03138 | AB23: ='2018-2019 B STATEMENT '!B401+'2018-2019 B STATEMENT '!B424 -> 400 | AC23: =AB23*0.99% -> 3.96 | AD23: =Z23-AB23+'Catch up Fee'!E23+AA23 -> 1853.0564 | AE23: =(AD23-AB23)*0.055 -> 79.918101 | AF23: 0 | AG23: =AF23*0.99% -> 0 | AH23: =AD23-AF23+'Catch up Fee'!E23+AE23 -> 2132.9745 | AI23: =(AH23-AF23)*0.055 -> 117.3136 | AJ23: 0 | AK23: =AJ23*0.99% -> 0 | AL23: =AH23-AJ23+'Catch up Fee'!E23+AI23 -> 2450.2881 | AM23: =(AL23-AJ23)*0.055 -> 134.76584 | AN23: ='2018-2019 B STATEMENT '!B482 -> 500 | AO23: =AN23*0.99% -> 4.95 | AP23: =AL23-AN23+'Catch up Fee'!E23+AM23 -> 2285.0539 | AQ23: =(AP23-AN23)*0.055 -> 98.177965 | AR23: 0 | AS23: =AR23*0.99% -> 0 | AT23: =AP23-AR23+'Catch up Fee'!E23+AQ23 -> 2583.2319 | AU23: =(AT23-AR23)*0.055 -> 142.07775 | AV23: 0 | AW23: =AV23*0.99% -> 0 | AX23: =AT23-AV23+'Catch up Fee'!E23+AU23 -> 2925.3096 | AY23: =(AX23-AV23)*0.055 -> 160.89203 | AZ23: 0 | BA23: =AZ23*0.99% -> 0 | BB23: =AX23-AZ23+'Catch up Fee'!E23+AY23 -> 3286.2017 | BC23: =(BB23-AZ23)*0.055 -> 180.74109 | BD23: 0 | BE23: =BD23*0.99% -> 0 | BF23: =BB23-BD23+'Catch up Fee'!E23+BC23 -> 3666.9428 | BG23: =(BF23-BD23)*0.055 -> 201.68185 | BH23: 0 | BI23: =BH23*0.99% -> 0 | BJ23: =BF23-BH23+'Catch up Fee'!E23+BG23 -> 4068.6246 | BK23: =(BJ23-BH23)*0.055 -> 223.77435 | BL23: =P23+T23+X23+AB23+AF23+AJ23+AR23+AN23+AV23+AZ23+BD23+BH23 -> 1300
A24: Member 23 | B24: 3/7/2018 | C24: 0 | D24: =200*12 -> 2400 | E24: =' 2018-2019'!J23 -> -300 | F24: =' 2018-2019'!F24 -> 0 | G24: =C24+D24 -> 2400 | H24: =BL24 -> 0 | I24: =G24-H24-C24 -> 2400 | J24: =I24+M24+E24+F24 -> 2886.9974 | K24: =Q24+U24+Y24+AC24+AG24+AK24+AO24+AS24+AW24+BA24+BE24+BI24 -> 0 | L24: =(H24-K24-C24)*5.5% -> 0 | M24: =S24+W24+AA24+AE24+AI24+AM24+AQ24+AU24+AY24+BC24+BG24+BK24 -> 786.99738 | N24: =M24 -> 786.99738 | O24: =H24-K24-M24+L24 -> -786.99738 | P24: 0 | Q24: =P24*0.99% -> 0 | R24: =E24+'Catch up Fee'!E24 -> -100 | S24: =(R24-P24)*0.055 -> -5.5 | T24: 0 | U24: =T24*0.99% -> 0 | V24: =R24-T24+'Catch up Fee'!E24+S24 -> 94.5 | W24: =(V24-T24)*0.055 -> 5.1975 | X24: 0 | Y24: =X24*0.99% -> 0 | Z24: =V24-X24+'Catch up Fee'!E24+W24 -> 299.6975 | AA24: =(Z24-X24)*0.055 -> 16.483362 | AB24: 0 | AC24: =AB24*0.99% -> 0 | AD24: =Z24-AB24+'Catch up Fee'!E24+AA24 -> 516.18086 | AE24: =(AD24-AB24)*0.055 -> 28.389947 | AF24: 0 | AG24: =AF24*0.99% -> 0 | AH24: =AD24-AF24+'Catch up Fee'!E24+AE24 -> 744.57081 | AI24: =(AH24-AF24)*0.055 -> 40.951395 | AJ24: 0 | AK24: =AJ24*0.99% -> 0 | AL24: =AH24-AJ24+'Catch up Fee'!E24+AI24 -> 985.5222 | AM24: =(AL24-AJ24)*0.055 -> 54.203721 | AN24: 0 | AO24: =AN24*0.99% -> 0 | AP24: =AL24-AN24+'Catch up Fee'!E24+AM24 -> 1239.7259 | AQ24: =(AP24-AN24)*0.055 -> 68.184926 | AR24: 0 | AS24: =AR24*0.99% -> 0 | AT24: =AP24-AR24+'Catch up Fee'!E24+AQ24 -> 1507.9109 | AU24: =(AT24-AR24)*0.055 -> 82.935097 | AV24: 0 | AW24: =AV24*0.99% -> 0 | AX24: =AT24-AV24+'Catch up Fee'!E24+AU24 -> 1790.8459 | AY24: =(AX24-AV24)*0.055 -> 98.496527 | AZ24: 0 | BA24: =AZ24*0.99% -> 0 | BB24: =AX24-AZ24+'Catch up Fee'!E24+AY24 -> 2089.3425 | BC24: =(BB24-AZ24)*0.055 -> 114.91384 | BD24: 0 | BE24: =BD24*0.99% -> 0 | BF24: =BB24-BD24+'Catch up Fee'!E24+BC24 -> 2404.2563 | BG24: =(BF24-BD24)*0.055 -> 132.2341 | BH24: 0 | BI24: =BH24*0.99% -> 0 | BJ24: =BF24-BH24+'Catch up Fee'!E24+BG24 -> 2736.4904 | BK24: =(BJ24-BH24)*0.055 -> 150.50697 | BL24: =P24+T24+X24+AB24+AF24+AJ24+AR24+AN24+AV24+AZ24+BD24+BH24 -> 0
A25: Member 24 | B25: 27/08/2018 | C25: 0 | D25: =200*12 -> 2400 | E25: =' 2018-2019'!J25 -> 2500 | F25: =' 2018-2019'!F25 -> 200 | G25: =C25+D25 -> 2400 | H25: =BL25 -> 3000 | I25: =G25-H25-C25 -> -600 | J25: =I25+M25+E25 -> 3922.8855 | K25: =Q25+U25+Y25+AC25+AG25+AK25+AO25+AS25+AW25+BA25+BE25+BI25 -> 29.7 | L25: =(H25-K25-C25)*5.5% -> 163.3665 | M25: =S25+W25+AA25+AE25+AI25+AM25+AQ25+AU25+AY25+BC25+BG25+BK25 -> 2022.8855 | N25: =M25 -> 2022.8855 | O25: =H25-K25-M25+L25 -> 1110.781 | P25: 0 | Q25: =P25*0.99% -> 0 | R25: =E25+'Catch up Fee'!E25 -> 2700 | S25: =(R25-P25)*0.055 -> 148.5 | T25: 0 | U25: =T25*0.99% -> 0 | V25: =R25-T25+'Catch up Fee'!E25+S25 -> 3048.5 | W25: =(V25-T25)*0.055 -> 167.6675 | X25: ='2018-2019 B STATEMENT '!B98 -> 300 | Y25: =X25*0.99% -> 2.97 | Z25: =V25-X25+'Catch up Fee'!E25+W25 -> 3116.1675 | AA25: =(Z25-X25)*0.055 -> 154.88921 | AB25: ='2018-2019 B STATEMENT '!B373 -> 300 | AC25: =AB25*0.99% -> 2.97 | AD25: =Z25-AB25+'Catch up Fee'!E25+AA25 -> 3171.0567 | AE25: =(AD25-AB25)*0.055 -> 157.90812 | AF25: ='2018-2019 B STATEMENT '!B403 -> 300 | AG25: =AF25*0.99% -> 2.97 | AH25: =AD25-AF25+'Catch up Fee'!E25+AE25 -> 3228.9648 | AI25: =(AH25-AF25)*0.055 -> 161.09307 | AJ25: ='2018-2019 B STATEMENT '!B427 -> 300 | AK25: =AJ25*0.99% -> 2.97 | AL25: =AH25-AJ25+'Catch up Fee'!E25+AI25 -> 3290.0579 | AM25: =(AL25-AJ25)*0.055 -> 164.45318 | AN25: ='2018-2019 B STATEMENT '!B449 -> 300 | AO25: =AN25*0.99% -> 2.97 | AP25: =AL25-AN25+'Catch up Fee'!E25+AM25 -> 3354.5111 | AQ25: =(AP25-AN25)*0.055 -> 167.99811 | AR25: ='2018-2019 B STATEMENT '!B479 -> 300 | AS25: =AR25*0.99% -> 2.97 | AT25: =AP25-AR25+'Catch up Fee'!E25+AQ25 -> 3422.5092 | AU25: =(AT25-AR25)*0.055 -> 171.73801 | AV25: ='2018-2019 B STATEMENT '!B496 -> 300 | AW25: =AV25*0.99% -> 2.97 | AX25: =AT25-AV25+'Catch up Fee'!E25+AU25 -> 3494.2472 | AY25: =(AX25-AV25)*0.055 -> 175.6836 | AZ25: ='2018-2019 B STATEMENT '!B514 -> 300 | BA25: =AZ25*0.99% -> 2.97 | BB25: =AX25-AZ25+'Catch up Fee'!E25+AY25 -> 3569.9308 | BC25: =(BB25-AZ25)*0.055 -> 179.84619 | BD25: ='2018-2019 B STATEMENT '!B517 -> 300 | BE25: =BD25*0.99% -> 2.97 | BF25: =BB25-BD25+'Catch up Fee'!E25+BC25 -> 3649.777 | BG25: =(BF25-BD25)*0.055 -> 184.23773 | BH25: ='2018-2019 B STATEMENT '!B531 -> 300 | BI25: =BH25*0.99% -> 2.97 | BJ25: =BF25-BH25+'Catch up Fee'!E25+BG25 -> 3734.0147 | BK25: =(BJ25-BH25)*0.055 -> 188.87081 | BL25: =P25+T25+X25+AB25+AF25+AJ25+AR25+AN25+AV25+AZ25+BD25+BH25 -> 3000
A26: Member 25 | B26: 29/06/2018 | C26: 0 | D26: =200*12 -> 2400 | E26: =' 2018-2019'!J25 -> 2500 | F26: =' 2018-2019'!F26 -> 0 | G26: =C26+D26 -> 2400 | H26: =BL26 -> 400 | I26: =G26-H26-C26 -> 2000 | J26: =I26+M26+E26+F26 -> 7770.7323 | K26: =Q26+U26+Y26+AC26+AG26+AK26+AO26+AS26+AW26+BA26+BE26+BI26 -> 3.96 | L26: =(H26-K26-C26)*5.5% -> 21.7822 | M26: =S26+W26+AA26+AE26+AI26+AM26+AQ26+AU26+AY26+BC26+BG26+BK26 -> 3270.7323 | N26: =M26 -> 3270.7323 | O26: =H26-K26-M26+L26 -> -2852.9101 | P26: ='2018-2019 B STATEMENT '!B336 -> 400 | Q26: =P26*0.99% -> 3.96 | R26: =E26+'Catch up Fee'!E26 -> 2700 | S26: =(R26-P26)*0.055 -> 126.5 | T26: ='2018-2019 B STATEMENT '!B345 -> 0 | U26: =T26*0.99% -> 0 | V26: =R26-T26+'Catch up Fee'!E26+S26 -> 3026.5 | W26: =(V26-T26)*0.055 -> 166.4575 | X26: 0 | Y26: =X26*0.99% -> 0 | Z26: =V26-X26+'Catch up Fee'!E26+W26 -> 3392.9575 | AA26: =(Z26-X26)*0.055 -> 186.61266 | AB26: 0 | AC26: =AB26*0.99% -> 0 | AD26: =Z26-AB26+'Catch up Fee'!E26+AA26 -> 3779.5702 | AE26: =(AD26-AB26)*0.055 -> 207.87636 | AF26: 0 | AG26: =AF26*0.99% -> 0 | AH26: =AD26-AF26+'Catch up Fee'!E26+AE26 -> 4187.4465 | AI26: =(AH26-AF26)*0.055 -> 230.30956 | AJ26: ='2018-2019 B STATEMENT '!B472 -> 0 | AK26: =AJ26*0.99% -> 0 | AL26: =AH26-AJ26+'Catch up Fee'!E26+AI26 -> 4617.7561 | AM26: =(AL26-AJ26)*0.055 -> 253.97658 | AN26: 0 | AO26: =AN26*0.99% -> 0 | AP26: =AL26-AN26+'Catch up Fee'!E26+AM26 -> 5071.7327 | AQ26: =(AP26-AN26)*0.055 -> 278.9453 | AR26: ='2018-2019 B STATEMENT '!B509 -> 0 | AS26: =AR26*0.99% -> 0 | AT26: =AP26-AR26+'Catch up Fee'!E26+AQ26 -> 5550.678 | AU26: =(AT26-AR26)*0.055 -> 305.28729 | AV26: 0 | AW26: =AV26*0.99% -> 0 | AX26: =AT26-AV26+'Catch up Fee'!E26+AU26 -> 6055.9652 | AY26: =(AX26-AV26)*0.055 -> 333.07809 | AZ26: 0 | BA26: =AZ26*0.99% -> 0 | BB26: =AX26-AZ26+'Catch up Fee'!E26+AY26 -> 6589.0433 | BC26: =(BB26-AZ26)*0.055 -> 362.39738 | BD26: 0 | BE26: =BD26*0.99% -> 0 | BF26: =BB26-BD26+'Catch up Fee'!E26+BC26 -> 7151.4407 | BG26: =(BF26-BD26)*0.055 -> 393.32924 | BH26: 0 | BI26: =BH26*0.99% -> 0 | BJ26: =BF26-BH26+'Catch up Fee'!E26+BG26 -> 7744.77 | BK26: =(BJ26-BH26)*0.055 -> 425.96235 | BL26: =P26+T26+X26+AB26+AF26+AJ26+AR26+AN26+AV26+AZ26+BD26+BH26 -> 400
A27: Member 26 | B27: 4/7/2018 | C27: 0 | D27: =200*12 -> 2400 | E27: =' 2018-2019'!J26 -> 450 | F27: =' 2018-2019'!F27 -> 0 | G27: =C27+D27 -> 2400 | H27: =BL27 -> 1400 | I27: =G27-H27-C27 -> 1000 | J27: =I27+M27+E27+F27 -> 2774.1419 | K27: =Q27+U27+Y27+AC27+AG27+AK27+AO27+AS27+AW27+BA27+BE27+BI27 -> 13.86 | L27: =(H27-K27-C27)*5.5% -> 76.2377 | M27: =S27+W27+AA27+AE27+AI27+AM27+AQ27+AU27+AY27+BC27+BG27+BK27 -> 1324.1419 | N27: =M27 -> 1324.1419 | O27: =H27-K27-M27+L27 -> 138.23582 | P27: ='2018-2019 B STATEMENT '!B320 -> 1400 | Q27: =P27*0.99% -> 13.86 | R27: =E27+'Catch up Fee'!E27 -> 650 | S27: =(R27-P27)*0.055 -> -41.25 | T27: 0 | U27: =T27*0.99% -> 0 | V27: =R27-T27+'Catch up Fee'!E27+S27 -> 808.75 | W27: =(V27-T27)*0.055 -> 44.48125 | X27: 0 | Y27: =X27*0.99% -> 0 | Z27: =V27-X27+'Catch up Fee'!E27+W27 -> 1053.2313 | AA27: =(Z27-X27)*0.055 -> 57.927719 | AB27: 0 | AC27: =AB27*0.99% -> 0 | AD27: =Z27-AB27+'Catch up Fee'!E27+AA27 -> 1311.159 | AE27: =(AD27-AB27)*0.055 -> 72.113743 | AF27: 0 | AG27: =AF27*0.99% -> 0 | AH27: =AD27-AF27+'Catch up Fee'!E27+AE27 -> 1583.2727 | AI27: =(AH27-AF27)*0.055 -> 87.079999 | AJ27: 0 | AK27: =AJ27*0.99% -> 0 | AL27: =AH27-AJ27+'Catch up Fee'!E27+AI27 -> 1870.3527 | AM27: =(AL27-AJ27)*0.055 -> 102.8694 | AN27: 0 | AO27: =AN27*0.99% -> 0 | AP27: =AL27-AN27+'Catch up Fee'!E27+AM27 -> 2173.2221 | AQ27: =(AP27-AN27)*0.055 -> 119.52722 | AR27: 0 | AS27: =AR27*0.99% -> 0 | AT27: =AP27-AR27+'Catch up Fee'!E27+AQ27 -> 2492.7493 | AU27: =(AT27-AR27)*0.055 -> 137.10121 | AV27: 0 | AW27: =AV27*0.99% -> 0 | AX27: =AT27-AV27+'Catch up Fee'!E27+AU27 -> 2829.8505 | AY27: =(AX27-AV27)*0.055 -> 155.64178 | AZ27: 0 | BA27: =AZ27*0.99% -> 0 | BB27: =AX27-AZ27+'Catch up Fee'!E27+AY27 -> 3185.4923 | BC27: =(BB27-AZ27)*0.055 -> 175.20208 | BD27: 0 | BE27: =BD27*0.99% -> 0 | BF27: =BB27-BD27+'Catch up Fee'!E27+BC27 -> 3560.6944 | BG27: =(BF27-BD27)*0.055 -> 195.83819 | BH27: 0 | BI27: =BH27*0.99% -> 0 | BJ27: =BF27-BH27+'Catch up Fee'!E27+BG27 -> 3956.5326 | BK27: =(BJ27-BH27)*0.055 -> 217.60929 | BL27: =P27+T27+X27+AB27+AF27+AJ27+AR27+AN27+AV27+AZ27+BD27+BH27 -> 1400
A28: Member 27 | B28: 3/7/2018 | C28: 0 | D28: =200*12 -> 2400 | E28: =' 2018-2019'!J27 -> 1700 | F28: =' 2018-2019'!F28 -> 0 | G28: =C28+D28 -> 2400 | H28: =BL28 -> 300 | I28: =G28-H28-C28 -> 2100 | J28: =I28+M28+E28+F28 -> 6289.3557 | K28: =Q28+U28+Y28+AC28+AG28+AK28+AO28+AS28+AW28+BA28+BE28+BI28 -> 2.97 | L28: =(H28-K28-C28)*5.5% -> 16.33665 | M28: =S28+W28+AA28+AE28+AI28+AM28+AQ28+AU28+AY28+BC28+BG28+BK28 -> 2489.3557 | N28: =M28 -> 2489.3557 | O28: =H28-K28-M28+L28 -> -2175.9891 | P28: ='2018-2019 B STATEMENT '!B343 -> 100 | Q28: =P28*0.99% -> 0.99 | R28: =E28+'Catch up Fee'!E28 -> 1900 | S28: =(R28-P28)*0.055 -> 99 | T28: 0 | U28: =T28*0.99% -> 0 | V28: =R28-T28+'Catch up Fee'!E28+S28 -> 2199 | W28: =(V28-T28)*0.055 -> 120.945 | X28: 0 | Y28: =X28*0.99% -> 0 | Z28: =V28-X28+'Catch up Fee'!E28+W28 -> 2519.945 | AA28: =(Z28-X28)*0.055 -> 138.59698 | AB28: 0 | AC28: =AB28*0.99% -> 0 | AD28: =Z28-AB28+'Catch up Fee'!E28+AA28 -> 2858.542 | AE28: =(AD28-AB28)*0.055 -> 157.21981 | AF28: 0 | AG28: =AF28*0.99% -> 0 | AH28: =AD28-AF28+'Catch up Fee'!E28+AE28 -> 3215.7618 | AI28: =(AH28-AF28)*0.055 -> 176.8669 | AJ28: 0 | AK28: =AJ28*0.99% -> 0 | AL28: =AH28-AJ28+'Catch up Fee'!E28+AI28 -> 3592.6287 | AM28: =(AL28-AJ28)*0.055 -> 197.59458 | AN28: ='2018-2019 B STATEMENT '!B480 -> 200 | AO28: =AN28*0.99% -> 1.98 | AP28: =AL28-AN28+'Catch up Fee'!E28+AM28 -> 3790.2233 | AQ28: =(AP28-AN28)*0.055 -> 197.46228 | AR28: 0 | AS28: =AR28*0.99% -> 0 | AT28: =AP28-AR28+'Catch up Fee'!E28+AQ28 -> 4187.6855 | AU28: =(AT28-AR28)*0.055 -> 230.3227 | AV28: 0 | AW28: =AV28*0.99% -> 0 | AX28: =AT28-AV28+'Catch up Fee'!E28+AU28 -> 4618.0082 | AY28: =(AX28-AV28)*0.055 -> 253.99045 | AZ28: 0 | BA28: =AZ28*0.99% -> 0 | BB28: =AX28-AZ28+'Catch up Fee'!E28+AY28 -> 5071.9987 | BC28: =(BB28-AZ28)*0.055 -> 278.95993 | BD28: 0 | BE28: =BD28*0.99% -> 0 | BF28: =BB28-BD28+'Catch up Fee'!E28+BC28 -> 5550.9586 | BG28: =(BF28-BD28)*0.055 -> 305.30272 | BH28: 0 | BI28: =BH28*0.99% -> 0 | BJ28: =BF28-BH28+'Catch up Fee'!E28+BG28 -> 6056.2613 | BK28: =(BJ28-BH28)*0.055 -> 333.09437 | BL28: =P28+T28+X28+AB28+AF28+AJ28+AR28+AN28+AV28+AZ28+BD28+BH28 -> 300
A29: Member 28 | B29: 25/10/2019 | C29: 100 | D29: =200*12 -> 2400 | E29: =' 2018-2019'!J28 -> 2400 | F29: =' 2018-2019'!F29 -> 3000 | G29: =C29+D29 -> 2500 | H29: =BL29 -> 0 | I29: =G29-H29-C29 -> 2400 | J29: =I29+M29+E29 -> 5947.4804 | K29: =Q29+U29+Y29+AC29+AG29+AK29+AO29+AS29+AW29+BA29+BE29+BI29 -> 0 | L29: =(H29-K29-C29)*5.5% -> -5.5 | M29: =S29+W29+AA29+AE29+AI29+AM29+AQ29+AU29+AY29+BC29+BG29+BK29 -> 1147.4804 | N29: =M29 -> 1147.4804 | O29: =H29-K29-M29+L29 -> -1152.9804 | P29: 0 | Q29: =P29*0.99% -> 0 | R29: =C29+'Catch up Fee'!E29 -> 300 | S29: =(R29-P29)*0.055 -> 16.5 | T29: 0 | U29: =T29*0.99% -> 0 | V29: =R29-T29+'Catch up Fee'!E29+S29 -> 516.5 | W29: =(V29-T29)*0.055 -> 28.4075 | X29: 0 | Y29: =X29*0.99% -> 0 | Z29: =V29-X29+'Catch up Fee'!E29+W29 -> 744.9075 | AA29: =(Z29-X29)*0.055 -> 40.969912 | AB29: 0 | AC29: =AB29*0.99% -> 0 | AD29: =Z29-AB29+'Catch up Fee'!E29+AA29 -> 985.87741 | AE29: =(AD29-AB29)*0.055 -> 54.223258 | AF29: 0 | AG29: =AF29*0.99% -> 0 | AH29: =AD29-AF29+'Catch up Fee'!E29+AE29 -> 1240.1007 | AI29: =(AH29-AF29)*0.055 -> 68.205537 | AJ29: 0 | AK29: =AJ29*0.99% -> 0 | AL29: =AH29-AJ29+'Catch up Fee'!E29+AI29 -> 1508.3062 | AM29: =(AL29-AJ29)*0.055 -> 82.956841 | AN29: 0 | AO29: =AN29*0.99% -> 0 | AP29: =AL29-AN29+'Catch up Fee'!E29+AM29 -> 1791.263 | AQ29: =(AP29-AN29)*0.055 -> 98.519468 | AR29: 0 | AS29: =AR29*0.99% -> 0 | AT29: =AP29-AR29+'Catch up Fee'!E29+AQ29 -> 2089.7825 | AU29: =(AT29-AR29)*0.055 -> 114.93804 | AV29: 0 | AW29: =AV29*0.99% -> 0 | AX29: =AT29-AV29+'Catch up Fee'!E29+AU29 -> 2404.7206 | AY29: =(AX29-AV29)*0.055 -> 132.25963 | AZ29: 0 | BA29: =AZ29*0.99% -> 0 | BB29: =AX29-AZ29+'Catch up Fee'!E29+AY29 -> 2736.9802 | BC29: =(BB29-AZ29)*0.055 -> 150.53391 | BD29: 0 | BE29: =BD29*0.99% -> 0 | BF29: =BB29-BD29+'Catch up Fee'!E29+BC29 -> 3087.5141 | BG29: =(BF29-BD29)*0.055 -> 169.81328 | BH29: 0 | BI29: =BH29*0.99% -> 0 | BJ29: =BF29-BH29+'Catch up Fee'!E29+BG29 -> 3457.3274 | BK29: =(BJ29-BH29)*0.055 -> 190.15301 | BL29: =P29+T29+X29+AB29+AF29+AJ29+AR29+AN29+AV29+AZ29+BD29+BH29 -> 0
A30: Member 29 | B30: 31/08/2018 | C30: 0 | D30: =200*12 -> 2400 | E30: =' 2018-2019'!J29 -> 1900 | F30: =' 2018-2019'!F30 -> 200 | G30: =C30+D30 -> 2400 | H30: =BL30 -> 1300 | I30: =G30-H30-C30 -> 1100 | J30: =I30+M30+E30 -> 4733.3008 | K30: =Q30+U30+Y30+AC30+AG30+AK30+AO30+AS30+AW30+BA30+BE30+BI30 -> 12.87 | L30: =(H30-K30-C30)*5.5% -> 70.79215 | M30: =S30+W30+AA30+AE30+AI30+AM30+AQ30+AU30+AY30+BC30+BG30+BK30 -> 1733.3008 | N30: =M30 -> 1733.3008 | O30: =H30-K30-M30+L30 -> -375.37866 | P30: 0 | Q30: =P30*0.99% -> 0 | R30: =E30+'Catch up Fee'!E30 -> 2100 | S30: =(R30-P30)*0.055 -> 115.5 | T30: 0 | U30: =T30*0.99% -> 0 | V30: =R30-T30+'Catch up Fee'!E30+S30 -> 2415.5 | W30: =(V30-T30)*0.055 -> 132.8525 | X30: ='2018-2019 B STATEMENT '!B374 -> 1300 | Y30: =X30*0.99% -> 12.87 | Z30: =V30-X30+'Catch up Fee'!E30+W30 -> 1448.3525 | AA30: =(Z30-X30)*0.055 -> 8.1593875 | AB30: 0 | AC30: =AB30*0.99% -> 0 | AD30: =Z30-AB30+'Catch up Fee'!E30+AA30 -> 1656.5119 | AE30: =(AD30-AB30)*0.055 -> 91.108154 | AF30: 0 | AG30: =AF30*0.99% -> 0 | AH30: =AD30-AF30+'Catch up Fee'!E30+AE30 -> 1947.62 | AI30: =(AH30-AF30)*0.055 -> 107.1191 | AJ30: 0 | AK30: =AJ30*0.99% -> 0 | AL30: =AH30-AJ30+'Catch up Fee'!E30+AI30 -> 2254.7391 | AM30: =(AL30-AJ30)*0.055 -> 124.01065 | AN30: 0 | AO30: =AN30*0.99% -> 0 | AP30: =AL30-AN30+'Catch up Fee'!E30+AM30 -> 2578.7498 | AQ30: =(AP30-AN30)*0.055 -> 141.83124 | AR30: 0 | AS30: =AR30*0.99% -> 0 | AT30: =AP30-AR30+'Catch up Fee'!E30+AQ30 -> 2920.581 | AU30: =(AT30-AR30)*0.055 -> 160.63196 | AV30: 0 | AW30: =AV30*0.99% -> 0 | AX30: =AT30-AV30+'Catch up Fee'!E30+AU30 -> 3281.213 | AY30: =(AX30-AV30)*0.055 -> 180.46671 | AZ30: 0 | BA30: =AZ30*0.99% -> 0 | BB30: =AX30-AZ30+'Catch up Fee'!E30+AY30 -> 3661.6797 | BC30: =(BB30-AZ30)*0.055 -> 201.39238 | BD30: 0 | BE30: =BD30*0.99% -> 0 | BF30: =BB30-BD30+'Catch up Fee'!E30+BC30 -> 4063.0721 | BG30: =(BF30-BD30)*0.055 -> 223.46896 | BH30: 0 | BI30: =BH30*0.99% -> 0 | BJ30: =BF30-BH30+'Catch up Fee'!E30+BG30 -> 4486.5411 | BK30: =(BJ30-BH30)*0.055 -> 246.75976 | BL30: =P30+T30+X30+AB30+AF30+AJ30+AR30+AN30+AV30+AZ30+BD30+BH30 -> 1300
A31: Member 30 | B31: 3/7/2018 | C31: 0 | D31: =200*12 -> 2400 | E31: =' 2018-2019'!J30 -> 400 | F31: =' 2018-2019'!F31 -> 0 | G31: =C31+D31 -> 2400 | H31: =BL31 -> 1800 | I31: =G31-H31-C31 -> 600 | J31: =I31+M31+E31+F31 -> 1550.314 | K31: =Q31+U31+Y31+AC31+AG31+AK31+AO31+AS31+AW31+BA31+BE31+BI31 -> 17.82 | L31: =(H31-K31-C31)*5.5% -> 98.0199 | M31: =S31+W31+AA31+AE31+AI31+AM31+AQ31+AU31+AY31+BC31+BG31+BK31 -> 550.314 | N31: =M31 -> 550.314 | O31: =H31-K31-M31+L31 -> 1329.8859 | P31: ='2018-2019 B STATEMENT '!B332 -> 600 | Q31: =P31*0.99% -> 5.94 | R31: =E31+'Catch up Fee'!E31 -> 600 | S31: =(R31-P31)*0.055 -> 0 | T31: ='2018-2019 B STATEMENT '!B349 -> 600 | U31: =T31*0.99% -> 5.94 | V31: =R31-T31+'Catch up Fee'!E31+S31 -> 200 | W31: =(V31-T31)*0.055 -> -22 | X31: 0 | Y31: =X31*0.99% -> 0 | Z31: =V31-X31+'Catch up Fee'!E31+W31 -> 378 | AA31: =(Z31-X31)*0.055 -> 20.79 | AB31: 0 | AC31: =AB31*0.99% -> 0 | AD31: =Z31-AB31+'Catch up Fee'!E31+AA31 -> 598.79 | AE31: =(AD31-AB31)*0.055 -> 32.93345 | AF31: 0 | AG31: =AF31*0.99% -> 0 | AH31: =AD31-AF31+'Catch up Fee'!E31+AE31 -> 831.72345 | AI31: =(AH31-AF31)*0.055 -> 45.74479 | AJ31: 0 | AK31: =AJ31*0.99% -> 0 | AL31: =AH31-AJ31+'Catch up Fee'!E31+AI31 -> 1077.4682 | AM31: =(AL31-AJ31)*0.055 -> 59.260753 | AN31: ='2018-2019 B STATEMENT '!B489 -> 600 | AO31: =AN31*0.99% -> 5.94 | AP31: =AL31-AN31+'Catch up Fee'!E31+AM31 -> 736.72899 | AQ31: =(AP31-AN31)*0.055 -> 7.5200946 | AR31: 0 | AS31: =AR31*0.99% -> 0 | AT31: =AP31-AR31+'Catch up Fee'!E31+AQ31 -> 944.24909 | AU31: =(AT31-AR31)*0.055 -> 51.9337 | AV31: 0 | AW31: =AV31*0.99% -> 0 | AX31: =AT31-AV31+'Catch up Fee'!E31+AU31 -> 1196.1828 | AY31: =(AX31-AV31)*0.055 -> 65.790053 | AZ31: 0 | BA31: =AZ31*0.99% -> 0 | BB31: =AX31-AZ31+'Catch up Fee'!E31+AY31 -> 1461.9728 | BC31: =(BB31-AZ31)*0.055 -> 80.408506 | BD31: 0 | BE31: =BD31*0.99% -> 0 | BF31: =BB31-BD31+'Catch up Fee'!E31+BC31 -> 1742.3813 | BG31: =(BF31-BD31)*0.055 -> 95.830974 | BH31: 0 | BI31: =BH31*0.99% -> 0 | BJ31: =BF31-BH31+'Catch up Fee'!E31+BG31 -> 2038.2123 | BK31: =(BJ31-BH31)*0.055 -> 112.10168 | BL31: =P31+T31+X31+AB31+AF31+AJ31+AR31+AN31+AV31+AZ31+BD31+BH31 -> 1800
A32: Member 31 | B32: 28/07/2018 | C32: 0 | D32: =200*12 -> 2400 | E32: =' 2018-2019'!J31 -> 700 | F32: =' 2018-2019'!F32 -> 0 | G32: =C32+D32 -> 2400 | H32: =BL32 -> 0 | I32: =G32-H32-C32 -> 2400 | J32: =I32+M32+E32+F32 -> 4788.2049 | K32: =Q32+U32+Y32+AC32+AG32+AK32+AO32+AS32+AW32+BA32+BE32+BI32 -> 0 | L32: =(H32-K32-C32)*5.5% -> 0 | M32: =S32+W32+AA32+AE32+AI32+AM32+AQ32+AU32+AY32+BC32+BG32+BK32 -> 1688.2049 | N32: =M32 -> 1688.2049 | O32: =H32-K32-M32+L32 -> -1688.2049 | P32: 0 | Q32: =P32*0.99% -> 0 | R32: =E32+'Catch up Fee'!E32 -> 900 | S32: =(R32-P32)*0.055 -> 49.5 | T32: 0 | U32: =T32*0.99% -> 0 | V32: =R32-T32+'Catch up Fee'!E32+S32 -> 1149.5 | W32: =(V32-T32)*0.055 -> 63.2225 | X32: 0 | Y32: =X32*0.99% -> 0 | Z32: =V32-X32+'Catch up Fee'!E32+W32 -> 1412.7225 | AA32: =(Z32-X32)*0.055 -> 77.699738 | AB32: 0 | AC32: =AB32*0.99% -> 0 | AD32: =Z32-AB32+'Catch up Fee'!E32+AA32 -> 1690.4222 | AE32: =(AD32-AB32)*0.055 -> 92.973223 | AF32: 0 | AG32: =AF32*0.99% -> 0 | AH32: =AD32-AF32+'Catch up Fee'!E32+AE32 -> 1983.3955 | AI32: =(AH32-AF32)*0.055 -> 109.08675 | AJ32: 0 | AK32: =AJ32*0.99% -> 0 | AL32: =AH32-AJ32+'Catch up Fee'!E32+AI32 -> 2292.4822 | AM32: =(AL32-AJ32)*0.055 -> 126.08652 | AN32: 0 | AO32: =AN32*0.99% -> 0 | AP32: =AL32-AN32+'Catch up Fee'!E32+AM32 -> 2618.5687 | AQ32: =(AP32-AN32)*0.055 -> 144.02128 | AR32: 0 | AS32: =AR32*0.99% -> 0 | AT32: =AP32-AR32+'Catch up Fee'!E32+AQ32 -> 2962.59 | AU32: =(AT32-AR32)*0.055 -> 162.94245 | AV32: 0 | AW32: =AV32*0.99% -> 0 | AX32: =AT32-AV32+'Catch up Fee'!E32+AU32 -> 3325.5325 | AY32: =(AX32-AV32)*0.055 -> 182.90429 | AZ32: 0 | BA32: =AZ32*0.99% -> 0 | BB32: =AX32-AZ32+'Catch up Fee'!E32+AY32 -> 3708.4367 | BC32: =(BB32-AZ32)*0.055 -> 203.96402 | BD32: 0 | BE32: =BD32*0.99% -> 0 | BF32: =BB32-BD32+'Catch up Fee'!E32+BC32 -> 4112.4008 | BG32: =(BF32-BD32)*0.055 -> 226.18204 | BH32: 0 | BI32: =BH32*0.99% -> 0 | BJ32: =BF32-BH32+'Catch up Fee'!E32+BG32 -> 4538.5828 | BK32: =(BJ32-BH32)*0.055 -> 249.62205 | BL32: =P32+T32+X32+AB32+AF32+AJ32+AR32+AN32+AV32+AZ32+BD32+BH32 -> 0
A33: Member 32 | B33: 22/08/2018 | C33: 0 | D33: =200*12 -> 2400 | E33: =' 2018-2019'!J32 -> 1900 | F33: =' 2018-2019'!F33 -> 200 | G33: =C33+D33 -> 2400 | H33: =BL33 -> 0 | I33: =G33-H33-C33 -> 2400 | J33: =I33+M33+E33 -> 7069.6539 | K33: =Q33+U33+Y33+AC33+AG33+AK33+AO33+AS33+AW33+BA33+BE33+BI33 -> 0 | L33: =(H33-K33-C33)*5.5% -> 0 | M33: =S33+W33+AA33+AE33+AI33+AM33+AQ33+AU33+AY33+BC33+BG33+BK33 -> 2769.6539 | N33: =M33 -> 2769.6539 | O33: =H33-K33-M33+L33 -> -2769.6539 | P33: 0 | Q33: =P33*0.99% -> 0 | R33: =E33+'Catch up Fee'!E33 -> 2100 | S33: =(R33-P33)*0.055 -> 115.5 | T33: 0 | U33: =T33*0.99% -> 0 | V33: =R33-T33+'Catch up Fee'!E33+S33 -> 2415.5 | W33: =(V33-T33)*0.055 -> 132.8525 | X33: 0 | Y33: =X33*0.99% -> 0 | Z33: =V33-X33+'Catch up Fee'!E33+W33 -> 2748.3525 | AA33: =(Z33-X33)*0.055 -> 151.15939 | AB33: 0 | AC33: =AB33*0.99% -> 0 | AD33: =Z33-AB33+'Catch up Fee'!E33+AA33 -> 3099.5119 | AE33: =(AD33-AB33)*0.055 -> 170.47315 | AF33: 0 | AG33: =AF33*0.99% -> 0 | AH33: =AD33-AF33+'Catch up Fee'!E33+AE33 -> 3469.985 | AI33: =(AH33-AF33)*0.055 -> 190.84918 | AJ33: 0 | AK33: =AJ33*0.99% -> 0 | AL33: =AH33-AJ33+'Catch up Fee'!E33+AI33 -> 3860.8342 | AM33: =(AL33-AJ33)*0.055 -> 212.34588 | AN33: 0 | AO33: =AN33*0.99% -> 0 | AP33: =AL33-AN33+'Catch up Fee'!E33+AM33 -> 4273.1801 | AQ33: =(AP33-AN33)*0.055 -> 235.02491 | AR33: 0 | AS33: =AR33*0.99% -> 0 | AT33: =AP33-AR33+'Catch up Fee'!E33+AQ33 -> 4708.205 | AU33: =(AT33-AR33)*0.055 -> 258.95128 | AV33: 0 | AW33: =AV33*0.99% -> 0 | AX33: =AT33-AV33+'Catch up Fee'!E33+AU33 -> 5167.1563 | AY33: =(AX33-AV33)*0.055 -> 284.1936 | AZ33: 0 | BA33: =AZ33*0.99% -> 0 | BB33: =AX33-AZ33+'Catch up Fee'!E33+AY33 -> 5651.3499 | BC33: =(BB33-AZ33)*0.055 -> 310.82424 | BD33: 0 | BE33: =BD33*0.99% -> 0 | BF33: =BB33-BD33+'Catch up Fee'!E33+BC33 -> 6162.1741 | BG33: =(BF33-BD33)*0.055 -> 338.91958 | BH33: 0 | BI33: =BH33*0.99% -> 0 | BJ33: =BF33-BH33+'Catch up Fee'!E33+BG33 -> 6701.0937 | BK33: =(BJ33-BH33)*0.055 -> 368.56015 | BL33: =P33+T33+X33+AB33+AF33+AJ33+AR33+AN33+AV33+AZ33+BD33+BH33 -> 0
A34: Member 33 | C34: 0 | D34: =200*12 -> 2400 | E34: =' 2018-2019'!J33 -> 1200 | F34: =' 2018-2019'!F34 -> 0 | G34: =C34+D34 -> 2400 | H34: =BL34 -> 0 | I34: =G34-H34-C34 -> 2400 | J34: =I34+M34+E34+F34 -> 5738.8086 | K34: =Q34+U34+Y34+AC34+AG34+AK34+AO34+AS34+AW34+BA34+BE34+BI34 -> 0 | L34: =(H34-K34-C34)*5.5% -> 0 | M34: =S34+W34+AA34+AE34+AI34+AM34+AQ34+AU34+AY34+BC34+BG34+BK34 -> 2138.8086 | N34: =M34 -> 2138.8086 | O34: =H34-K34-M34+L34 -> -2138.8086 | P34: 0 | Q34: =P34*0.99% -> 0 | R34: =E34+'Catch up Fee'!E34 -> 1400 | S34: =(R34-P34)*0.055 -> 77 | T34: 0 | U34: =T34*0.99% -> 0 | V34: =R34-T34+'Catch up Fee'!E34+S34 -> 1677 | W34: =(V34-T34)*0.055 -> 92.235 | X34: 0 | Y34: =X34*0.99% -> 0 | Z34: =V34-X34+'Catch up Fee'!E34+W34 -> 1969.235 | AA34: =(Z34-X34)*0.055 -> 108.30792 | AB34: 0 | AC34: =AB34*0.99% -> 0 | AD34: =Z34-AB34+'Catch up Fee'!E34+AA34 -> 2277.5429 | AE34: =(AD34-AB34)*0.055 -> 125.26486 | AF34: 0 | AG34: =AF34*0.99% -> 0 | AH34: =AD34-AF34+'Catch up Fee'!E34+AE34 -> 2602.8078 | AI34: =(AH34-AF34)*0.055 -> 143.15443 | AJ34: 0 | AK34: =AJ34*0.99% -> 0 | AL34: =AH34-AJ34+'Catch up Fee'!E34+AI34 -> 2945.9622 | AM34: =(AL34-AJ34)*0.055 -> 162.02792 | AN34: 0 | AO34: =AN34*0.99% -> 0 | AP34: =AL34-AN34+'Catch up Fee'!E34+AM34 -> 3307.9901 | AQ34: =(AP34-AN34)*0.055 -> 181.93946 | AR34: 0 | AS34: =AR34*0.99% -> 0 | AT34: =AP34-AR34+'Catch up Fee'!E34+AQ34 -> 3689.9296 | AU34: =(AT34-AR34)*0.055 -> 202.94613 | AV34: 0 | AW34: =AV34*0.99% -> 0 | AX34: =AT34-AV34+'Catch up Fee'!E34+AU34 -> 4092.8757 | AY34: =(AX34-AV34)*0.055 -> 225.10816 | AZ34: 0 | BA34: =AZ34*0.99% -> 0 | BB34: =AX34-AZ34+'Catch up Fee'!E34+AY34 -> 4517.9839 | BC34: =(BB34-AZ34)*0.055 -> 248.48911 | BD34: 0 | BE34: =BD34*0.99% -> 0 | BF34: =BB34-BD34+'Catch up Fee'!E34+BC34 -> 4966.473 | BG34: =(BF34-BD34)*0.055 -> 273.15601 | BH34: 0 | BI34: =BH34*0.99% -> 0 | BJ34: =BF34-BH34+'Catch up Fee'!E34+BG34 -> 5439.629 | BK34: =(BJ34-BH34)*0.055 -> 299.1796 | BL34: =P34+T34+X34+AB34+AF34+AJ34+AR34+AN34+AV34+AZ34+BD34+BH34 -> 0
A35: Member 34 | B35: 15/08/2018 | C35: 0 | D35: =200*12 -> 2400 | E35: =' 2018-2019'!J34 -> 2400 | F35: =' 2018-2019'!F35 -> 200 | G35: =C35+D35 -> 2400 | H35: =BL35 -> 0 | I35: =G35-H35-C35 -> 2400 | J35: =I35+M35+E35 -> 8020.2576 | K35: =Q35+U35+Y35+AC35+AG35+AK35+AO35+AS35+AW35+BA35+BE35+BI35 -> 0 | L35: =(H35-K35-C35)*5.5% -> 0 | M35: =S35+W35+AA35+AE35+AI35+AM35+AQ35+AU35+AY35+BC35+BG35+BK35 -> 3220.2576 | N35: =M35 -> 3220.2576 | O35: =H35-K35-M35+L35 -> -3220.2576 | P35: 0 | Q35: =P35*0.99% -> 0 | R35: =E35+'Catch up Fee'!E35 -> 2600 | S35: =(R35-P35)*0.055 -> 143 | T35: 0 | U35: =T35*0.99% -> 0 | V35: =R35-T35+'Catch up Fee'!E35+S35 -> 2943 | W35: =(V35-T35)*0.055 -> 161.865 | Y35: =X35*0.99% -> 0 | Z35: =V35-X35+'Catch up Fee'!E35+W35 -> 3304.865 | AA35: =(Z35-X35)*0.055 -> 181.76757 | AC35: =AB35*0.99% -> 0 | AD35: =Z35-AB35+'Catch up Fee'!E35+AA35 -> 3686.6326 | AE35: =(AD35-AB35)*0.055 -> 202.76479 | AG35: =AF35*0.99% -> 0 | AH35: =AD35-AF35+'Catch up Fee'!E35+AE35 -> 4089.3974 | AI35: =(AH35-AF35)*0.055 -> 224.91686 | AK35: =AJ35*0.99% -> 0 | AL35: =AH35-AJ35+'Catch up Fee'!E35+AI35 -> 4514.3142 | AM35: =(AL35-AJ35)*0.055 -> 248.28728 | AO35: =AN35*0.99% -> 0 | AP35: =AL35-AN35+'Catch up Fee'!E35+AM35 -> 4962.6015 | AQ35: =(AP35-AN35)*0.055 -> 272.94308 | AS35: =AR35*0.99% -> 0 | AT35: =AP35-AR35+'Catch up Fee'!E35+AQ35 -> 5435.5446 | AU35: =(AT35-AR35)*0.055 -> 298.95495 | AW35: =AV35*0.99% -> 0 | AX35: =AT35-AV35+'Catch up Fee'!E35+AU35 -> 5934.4995 | AY35: =(AX35-AV35)*0.055 -> 326.39747 | BA35: =AZ35*0.99% -> 0 | BB35: =AX35-AZ35+'Catch up Fee'!E35+AY35 -> 6460.897 | BC35: =(BB35-AZ35)*0.055 -> 355.34934 | BE35: =BD35*0.99% -> 0 | BF35: =BB35-BD35+'Catch up Fee'!E35+BC35 -> 7016.2463 | BG35: =(BF35-BD35)*0.055 -> 385.89355 | BI35: =BH35*0.99% -> 0 | BJ35: =BF35-BH35+'Catch up Fee'!E35+BG35 -> 7602.1399 | BK35: =(BJ35-BH35)*0.055 -> 418.11769 | BL35: =P35+T35+X35+AB35+AF35+AJ35+AR35+AN35+AV35+AZ35+BD35+BH35 -> 0
A36: Member 35 | C36: 0 | D36: =200*12 -> 2400 | E36: =' 2018-2019'!J35 -> 2000 | F36: =' 2018-2019'!F36 -> 0 | G36: =C36+D36 -> 2400 | H36: =BL36 -> 0 | I36: =G36-H36-C36 -> 2400 | J36: =I36+M36+E36+F36 -> 7259.7746 | K36: =Q36+U36+Y36+AC36+AG36+AK36+AO36+AS36+AW36+BA36+BE36+BI36 -> 0 | L36: =(H36-K36-C36)*5.5% -> 0 | M36: =S36+W36+AA36+AE36+AI36+AM36+AQ36+AU36+AY36+BC36+BG36+BK36 -> 2859.7746 | N36: =M36 -> 2859.7746 | O36: =H36-K36-M36+L36 -> -2859.7746 | P36: 0 | Q36: =P36*0.99% -> 0 | R36: =E36+'Catch up Fee'!E36 -> 2200 | S36: =(R36-P36)*0.055 -> 121 | T36: 0 | U36: =T36*0.99% -> 0 | V36: =R36-T36+'Catch up Fee'!E36+S36 -> 2521 | W36: =(V36-T36)*0.055 -> 138.655 | X36: 0 | Y36: =X36*0.99% -> 0 | Z36: =V36-X36+'Catch up Fee'!E36+W36 -> 2859.655 | AA36: =(Z36-X36)*0.055 -> 157.28102 | AB36: 0 | AC36: =AB36*0.99% -> 0 | AD36: =Z36-AB36+'Catch up Fee'!E36+AA36 -> 3216.936 | AE36: =(AD36-AB36)*0.055 -> 176.93148 | AF36: 0 | AG36: =AF36*0.99% -> 0 | AH36: =AD36-AF36+'Catch up Fee'!E36+AE36 -> 3593.8675 | AI36: =(AH36-AF36)*0.055 -> 197.66271 | AJ36: 0 | AK36: =AJ36*0.99% -> 0 | AL36: =AH36-AJ36+'Catch up Fee'!E36+AI36 -> 3991.5302 | AM36: =(AL36-AJ36)*0.055 -> 219.53416 | AN36: 0 | AO36: =AN36*0.99% -> 0 | AP36: =AL36-AN36+'Catch up Fee'!E36+AM36 -> 4411.0644 | AQ36: =(AP36-AN36)*0.055 -> 242.60854 | AR36: 0 | AS36: =AR36*0.99% -> 0 | AT36: =AP36-AR36+'Catch up Fee'!E36+AQ36 -> 4853.6729 | AU36: =(AT36-AR36)*0.055 -> 266.95201 | AV36: 0 | AW36: =AV36*0.99% -> 0 | AX36: =AT36-AV36+'Catch up Fee'!E36+AU36 -> 5320.6249 | AY36: =(AX36-AV36)*0.055 -> 292.63437 | AZ36: 0 | BA36: =AZ36*0.99% -> 0 | BB36: =AX36-AZ36+'Catch up Fee'!E36+AY36 -> 5813.2593 | BC36: =(BB36-AZ36)*0.055 -> 319.72926 | BD36: 0 | BE36: =BD36*0.99% -> 0 | BF36: =BB36-BD36+'Catch up Fee'!E36+BC36 -> 6332.9886 | BG36: =(BF36-BD36)*0.055 -> 348.31437 | BH36: 0 | BI36: =BH36*0.99% -> 0 | BJ36: =BF36-BH36+'Catch up Fee'!E36+BG36 -> 6881.3029 | BK36: =(BJ36-BH36)*0.055 -> 378.47166 | BL36: =P36+T36+X36+AB36+AF36+AJ36+AR36+AN36+AV36+AZ36+BD36+BH36 -> 0
A37: Member 36 | B37: 20/08/2019 | C37: 100 | D37: =200*12 -> 2400 | E37: =' 2018-2019'!J36 -> 2400 | F37: =' 2018-2019'!F37 -> 2600 | G37: =C37+D37 -> 2500 | H37: =BL37 -> 1700 | I37: =G37-H37-C37 -> 700 | J37: =I37+M37+E37 -> 5605.6768 | K37: =Q37+U37+Y37+AC37+AG37+AK37+AO37+AS37+AW37+BA37+BE37+BI37 -> 16.83 | L37: =(H37-K37-C37)*5.5% -> 87.07435 | M37: =S37+W37+AA37+AE37+AI37+AM37+AQ37+AU37+AY37+BC37+BG37+BK37 -> 2505.6768 | N37: =M37 -> 2505.6768 | O37: =H37-K37-M37+L37 -> -735.4325 | P37: 0 | Q37: =P37*0.99% -> 0 | R37: =E37+'Catch up Fee'!E37 -> 2600 | S37: =(R37-P37)*0.055 -> 143 | T37: 0 | U37: =T37*0.99% -> 0 | V37: =R37-T37+'Catch up Fee'!E37+S37 -> 2943 | W37: =(V37-T37)*0.055 -> 161.865 | X37: ='2018-2019 B STATEMENT '!B377+'2018-2019 B STATEMENT '!B400 -> 300 | Y37: =X37*0.99% -> 2.97 | Z37: =V37-X37+'Catch up Fee'!E37+W37 -> 3004.865 | AA37: =(Z37-X37)*0.055 -> 148.76757 | AB37: ='2018-2019 B STATEMENT '!B421 -> 200 | AC37: =AB37*0.99% -> 1.98 | AD37: =Z37-AB37+'Catch up Fee'!E37+AA37 -> 3153.6326 | AE37: =(AD37-AB37)*0.055 -> 162.44979 | AF37: ='2018-2019 B STATEMENT '!B444 -> 200 | AG37: =AF37*0.99% -> 1.98 | AH37: =AD37-AF37+'Catch up Fee'!E37+AE37 -> 3316.0824 | AI37: =(AH37-AF37)*0.055 -> 171.38453 | AK37: =AJ37*0.99% -> 0 | AL37: =AH37-AJ37+'Catch up Fee'!E37+AI37 -> 3687.4669 | AM37: =(AL37-AJ37)*0.055 -> 202.81068 | AO37: =AN37*0.99% -> 0 | AP37: =AL37-AN37+'Catch up Fee'!E37+AM37 -> 4090.2776 | AQ37: =(AP37-AN37)*0.055 -> 224.96527 | AS37: =AR37*0.99% -> 0 | AT37: =AP37-AR37+'Catch up Fee'!E37+AQ37 -> 4515.2428 | AU37: =(AT37-AR37)*0.055 -> 248.33836 | AV37: ='2018-2019 B STATEMENT '!B512 -> 400 | AW37: =AV37*0.99% -> 3.96 | AX37: =AT37-AV37+'Catch up Fee'!E37+AU37 -> 4563.5812 | AY37: =(AX37-AV37)*0.055 -> 228.99697 | BA37: =AZ37*0.99% -> 0 | BB37: =AX37-AZ37+'Catch up Fee'!E37+AY37 -> 4992.5782 | BC37: =(BB37-AZ37)*0.055 -> 274.5918 | BD37: ='2018-2019 B STATEMENT '!B569 -> 400 | BE37: =BD37*0.99% -> 3.96 | BF37: =BB37-BD37+'Catch up Fee'!E37+BC37 -> 5067.17 | BG37: =(BF37-BD37)*0.055 -> 256.69435 | BH37: ='2018-2019 B STATEMENT '!B584 -> 200 | BI37: =BH37*0.99% -> 1.98 | BJ37: =BF37-BH37+'Catch up Fee'!E37+BG37 -> 5323.8643 | BK37: =(BJ37-BH37)*0.055 -> 281.81254 | BL37: =P37+T37+X37+AB37+AF37+AJ37+AR37+AN37+AV37+AZ37+BD37+BH37 -> 1700
